Workbook
Name MULT_RETAIL_CONS: 'SKU with PRICES'!$Z$11
Name RATE_WHOLESALE_CONS: 'SKU with PRICES'!$Z$12
Name RATE_CORPORATE_CONS: 'SKU with PRICES'!$Z$13
Name RATE_INFLUENCER_CONS: 'SKU with PRICES'!$Z$14
Name VAT_REGISTERED: 'GUARDRAILS'!$C$7
Name R4_FLOOR: 'GUARDRAILS'!$C$8
Name MIN_TIER_RATE: 'GUARDRAILS'!$C$12
Name MULT_RETAIL: 'GUARDRAILS'!$C$14
Name MULT_RETAIL_CORE: 'GUARDRAILS'!$C$14
Name R4_MARKUP: 'GUARDRAILS'!$C$5
Name VAT_RATE: 'GUARDRAILS'!$C$6
Name TIER_WHOLESALE: 'GUARDRAILS'!$C$9
Name TIER_CORPORATE: 'GUARDRAILS'!$C$10
Name TIER_INFLUENCER: 'GUARDRAILS'!$C$11
Name SAFETY_BUFFER: 'GUARDRAILS'!$C$13
Name FX_USD_KES: 'GUARDRAILS'!$C$15
Name FREIGHT_RATE: 'GUARDRAILS'!$C$16
Name RATE_WHOLESALE: 'GUARDRAILS'!$C$9
Name RATE_CORPORATE: 'GUARDRAILS'!$C$10
Name RATE_INFLUENCER: 'GUARDRAILS'!$C$11
Name SHRINK_ACTUAL: 'GUARDRAILS'!$C$20
Name SHRINK_PLAN: 'GUARDRAILS'!$C$21
Name EVENT_COST: 'GUARDRAILS'!$C$22
Name UNITS_PER_EVENT: 'GUARDRAILS'!$C$23
Name FEE_BANK: 'GUARDRAILS'!$C$25
Name FEE_MPESA: 'GUARDRAILS'!$C$26
Name FEE_CASH: 'GUARDRAILS'!$C$27
Name MARKETING_MONTHLY: 'GUARDRAILS'!$C$29
Name ACT_EVENTS: 'GUARDRAILS'!$C$30
Name ACT_REVENUE_EST: 'GUARDRAILS'!$C$31
Name FIXED_MONTHLY: 'GUARDRAILS'!$C$28
Name AGENT_RATE: 'GUARDRAILS'!$C$24

Sheet FIXED_COSTS
A1: FIXED AND RECURRING COSTS — these were recorded all along
A2: I modelled FIXED_MONTHLY as 600 on 23 Sep and said salaries and warehouse rent were in no register. They were in the record from 9 September. That was my failure to search, and it understated the fixed base by a factor of 165.
A4: ITEM | B4: KES TOTAL | C4: PER MONTH | D4: PERIOD | E4: BASIS | F4: SOURCE / NOTE
A5: Salaries | B5: 344800 | C5: 86200 | D5: Jun-Sep 2026 | E5: EVIDENCED | F5: F-12, 9 Sep. Owner-funded personally, treated as a loan. No payroll registration, no PAYE record, no contracts — the most urgent compliance item in the estate.
A6: Warehouse rent | B6: 84000 | C6: 12000 | D6: Mar-Sep 2026 | E6: EVIDENCED | F6: F-11 / Q13c. Paid since Mar 2026, no written lease. First recurring fixed cost ever identified. Rent start and the 12 Mar count are almost certainly the same event — the anchor has a LOC_ID nobody wrote down.
A7: Bank maintenance | C7: 600 | D7: monthly | E7: EVIDENCED | F7: Incl. 20% excise. Transfer charges are separate, at ~0.69% of value moved.
A8: FIXED SUBTOTAL | C8: 98800 | D8: monthly | F8: salaries + warehouse + bank
A9: Activation SPACE | B9: 110000 | D9: Mar-Aug 2026 | E9: RULED | F9: Owner ruling 10 Sep. ~16 of 26 Saturdays used a paid venue; 10 were free or nominal.
A10: Activation STAFF | B10: 72000 | D10: Mar-Aug 2026 | E10: EVIDENCED | F10: 36 staff-days at 2,000. Reconciles exactly: 10 double-staffed + 16 single-staffed = 26 events.
A11: MARKETING SUBTOTAL | B11: 182000 | C11: 30333 | D11: 6 months | F11: Exactly 7,000 per event across 26 events
A12: TOTAL RECURRING | C12: 129133 | D12: monthly | F12: fixed + marketing
A13: Annualised | C13: 1549600 | D13: per year
A15: NOT YET IN HERE
A16: 1. Director's loan ~KES 923,000-1,331,000 — no agreement, no board minute, no ledger account.
A17: 2. aCatalyst balance 126,976, due ~28 Oct 2026. Against a 10 Sep bank balance of 75,849.45.
A18: 3. Digital consultancy 100,000 for two months, of which 50,000 has no receipt of any kind.
A19: 4. PAYE and statutory deductions — four months unfiled. Quantum unknown and not mine to estimate.
A20: 5. Transport, packaging and insurance — no figure anywhere.

Sheet BREAK_EVEN
A1: BREAK-EVEN — how much must sell before the month pays for itself
A2: Basket = one of each of the 31 publishable SKUs. Average price KES 6,677. Live against GUARDRAILS.
A4: SHRINKAGE | B4: CONTRIB MARGIN | C4: CONTRIB / UNIT | D4: UNITS / MONTH | E4: REVENUE / MONTH | F4: REVENUE / YEAR | G4: VERDICT
A5: historical 37.3% | B5: =(SUM(UNIT_ECONOMICS!$P$7:$P$37)-SUM(UNIT_ECONOMICS!$F$7:$F$37)-SUM(UNIT_ECONOMICS!$F$7:$F$37)*(SHRINK_ACTUAL/(1-SHRINK_ACTUAL))-SUM(UNIT_ECONOMICS!$P$7:$P$37)*FEE_MPESA)/SUM(UNIT_ECONOMICS!$P$7:$P$37) | C5: =(SUM(UNIT_ECONOMICS!$P$7:$P$37)-SUM(UNIT_ECONOMICS!$F$7:$F$37)-SUM(UNIT_ECONOMICS!$F$7:$F$37)*(SHRINK_ACTUAL/(1-SHRINK_ACTUAL))-SUM(UNIT_ECONOMICS!$P$7:$P$37)*FEE_MPESA)/31 | D5: =IF($C5<=0,"unreachable",ROUND((FIXED_MONTHLY+MARKETING_MONTHLY)/$C5,0)) | E5: =IF($B5<=0,"unreachable",ROUND((FIXED_MONTHLY+MARKETING_MONTHLY)/$B5,0)) | F5: =IF(ISNUMBER($E5),$E5*12,"unreachable") | G5: =IF(NOT(ISNUMBER($D5)),"impossible at any volume",IF($D5>100,"very hard","reachable"))
A6: plan 10% | B6: =(SUM(UNIT_ECONOMICS!$P$7:$P$37)-SUM(UNIT_ECONOMICS!$F$7:$F$37)-SUM(UNIT_ECONOMICS!$F$7:$F$37)*(SHRINK_PLAN/(1-SHRINK_PLAN))-SUM(UNIT_ECONOMICS!$P$7:$P$37)*FEE_MPESA)/SUM(UNIT_ECONOMICS!$P$7:$P$37) | C6: =(SUM(UNIT_ECONOMICS!$P$7:$P$37)-SUM(UNIT_ECONOMICS!$F$7:$F$37)-SUM(UNIT_ECONOMICS!$F$7:$F$37)*(SHRINK_PLAN/(1-SHRINK_PLAN))-SUM(UNIT_ECONOMICS!$P$7:$P$37)*FEE_MPESA)/31 | D6: =IF($C6<=0,"unreachable",ROUND((FIXED_MONTHLY+MARKETING_MONTHLY)/$C6,0)) | E6: =IF($B6<=0,"unreachable",ROUND((FIXED_MONTHLY+MARKETING_MONTHLY)/$B6,0)) | F6: =IF(ISNUMBER($E6),$E6*12,"unreachable") | G6: =IF(NOT(ISNUMBER($D6)),"impossible at any volume",IF($D6>100,"very hard","reachable"))
A7: best case 5% | B7: =(SUM(UNIT_ECONOMICS!$P$7:$P$37)-SUM(UNIT_ECONOMICS!$F$7:$F$37)-SUM(UNIT_ECONOMICS!$F$7:$F$37)*(0.05/(1-0.05))-SUM(UNIT_ECONOMICS!$P$7:$P$37)*FEE_MPESA)/SUM(UNIT_ECONOMICS!$P$7:$P$37) | C7: =(SUM(UNIT_ECONOMICS!$P$7:$P$37)-SUM(UNIT_ECONOMICS!$F$7:$F$37)-SUM(UNIT_ECONOMICS!$F$7:$F$37)*(0.05/(1-0.05))-SUM(UNIT_ECONOMICS!$P$7:$P$37)*FEE_MPESA)/31 | D7: =IF($C7<=0,"unreachable",ROUND((FIXED_MONTHLY+MARKETING_MONTHLY)/$C7,0)) | E7: =IF($B7<=0,"unreachable",ROUND((FIXED_MONTHLY+MARKETING_MONTHLY)/$B7,0)) | F7: =IF(ISNUMBER($E7),$E7*12,"unreachable") | G7: =IF(NOT(ISNUMBER($D7)),"impossible at any volume",IF($D7>100,"very hard","reachable"))
A9: All-time recorded Kenyan revenue, for scale | E9: 264862
A10: At plan shrinkage the business must sell more every MONTH than it has recorded in its entire life. That is the finding; it is not a pricing finding.
A12: ACTIVATION AS MARKETING — the payback test
A13: Owner ruling, 23 Sep 2026: activation is marketing, not a sales channel. It is no longer charged per unit. It must instead pay back as a programme.
A14: SHRINKAGE | B14: PROGRAMME COST | C14: REVENUE NEEDED | D14: REVENUE ESTIMATED | E14: CONTRIB GENERATED | F14: NET | G14: VERDICT
A15: historical 37.3% | B15: =MARKETING_MONTHLY*6 | C15: =ROUND($B15/((SUM(UNIT_ECONOMICS!$P$7:$P$37)-SUM(UNIT_ECONOMICS!$F$7:$F$37)-SUM(UNIT_ECONOMICS!$F$7:$F$37)*(SHRINK_ACTUAL/(1-SHRINK_ACTUAL))-SUM(UNIT_ECONOMICS!$P$7:$P$37)*FEE_MPESA)/SUM(UNIT_ECONOMICS!$P$7:$P$37)),0) | D15: =ACT_REVENUE_EST | E15: =ROUND($D15*((SUM(UNIT_ECONOMICS!$P$7:$P$37)-SUM(UNIT_ECONOMICS!$F$7:$F$37)-SUM(UNIT_ECONOMICS!$F$7:$F$37)*(SHRINK_ACTUAL/(1-SHRINK_ACTUAL))-SUM(UNIT_ECONOMICS!$P$7:$P$37)*FEE_MPESA)/SUM(UNIT_ECONOMICS!$P$7:$P$37)),0) | F15: =$E15-$B15 | G15: =IF($F15>=0,"PAYS BACK","SHORT "&TEXT(-$F15,"#,##0"))
A16: plan 10% | B16: =MARKETING_MONTHLY*6 | C16: =ROUND($B16/((SUM(UNIT_ECONOMICS!$P$7:$P$37)-SUM(UNIT_ECONOMICS!$F$7:$F$37)-SUM(UNIT_ECONOMICS!$F$7:$F$37)*(SHRINK_PLAN/(1-SHRINK_PLAN))-SUM(UNIT_ECONOMICS!$P$7:$P$37)*FEE_MPESA)/SUM(UNIT_ECONOMICS!$P$7:$P$37)),0) | D16: =ACT_REVENUE_EST | E16: =ROUND($D16*((SUM(UNIT_ECONOMICS!$P$7:$P$37)-SUM(UNIT_ECONOMICS!$F$7:$F$37)-SUM(UNIT_ECONOMICS!$F$7:$F$37)*(SHRINK_PLAN/(1-SHRINK_PLAN))-SUM(UNIT_ECONOMICS!$P$7:$P$37)*FEE_MPESA)/SUM(UNIT_ECONOMICS!$P$7:$P$37)),0) | F16: =$E16-$B16 | G16: =IF($F16>=0,"PAYS BACK","SHORT "&TEXT(-$F16,"#,##0"))
A17: best case 5% | B17: =MARKETING_MONTHLY*6 | C17: =ROUND($B17/((SUM(UNIT_ECONOMICS!$P$7:$P$37)-SUM(UNIT_ECONOMICS!$F$7:$F$37)-SUM(UNIT_ECONOMICS!$F$7:$F$37)*(0.05/(1-0.05))-SUM(UNIT_ECONOMICS!$P$7:$P$37)*FEE_MPESA)/SUM(UNIT_ECONOMICS!$P$7:$P$37)),0) | D17: =ACT_REVENUE_EST | E17: =ROUND($D17*((SUM(UNIT_ECONOMICS!$P$7:$P$37)-SUM(UNIT_ECONOMICS!$F$7:$F$37)-SUM(UNIT_ECONOMICS!$F$7:$F$37)*(0.05/(1-0.05))-SUM(UNIT_ECONOMICS!$P$7:$P$37)*FEE_MPESA)/SUM(UNIT_ECONOMICS!$P$7:$P$37)),0) | F17: =$E17-$B17 | G17: =IF($F17>=0,"PAYS BACK","SHORT "&TEXT(-$F17,"#,##0"))
A19: Reclassifying did not hide the problem — it sized it.
A20: Charged per unit the programme looked catastrophic (-49% margin), and about a third of that was a double-count of mine. Judged as marketing, at plan shrinkage it is short by about 30,000 over six months — within touching distance. At historical shrinkage it is short by 146,000 and no amount of marketing discipline reaches it. The same variable decides this as decides everything else.
A22: On RECORDED activation revenue of 5,700 the programme is short by ~180,000 at any shrinkage rate. The gap between 5,700 and 426,647 is the till statement, and it is still the single highest-value missing document.

Sheet UNIT_ECONOMICS
A1: UNIT ECONOMICS — what one unit actually leaves behind
A2: The R4 floor covers landed cost only. Everything right of GROSS is the cost of serving the unit. ACTIVATION IS NO LONGER CHARGED HERE — owner ruling 23 Sep: it is marketing. See BREAK_EVEN.
A4: CHANNEL | B4: RETAIL | C4: SHRINKAGE | D4: ACTUAL | E4: PAYMENT | F4: MPESA | H4: ACTIVATION? | I4: NO | J4: <- keep NO. Activation is a marketing programme now, tested on BREAK_EVEN.
A6: PARENT_SKU | B6: PRODUCT | C6: PRICE | D6: VAT OUT | E6: NET REV | F6: LANDED | G6: GROSS | H6: SHRINK | I6: PAY FEE | J6: AGENT | K6: EVENT | L6: CONTRIBUTION | M6: CONTR % | N6: VERDICT | P6: BASE_RETAIL
A7: UC-HOU-PHRO-001 | B7: =IFERROR(INDEX(GATE!$B:$B,MATCH($A7,GATE!$A:$A,0)),"") | C7: =IFERROR(INDEX(GATE!$G:$G,MATCH($A7,GATE!$A:$A,0))*IF($B$4="RETAIL",1,IF($B$4="WHOLESALE",TIER_WHOLESALE,IF($B$4="CORPORATE",TIER_CORPORATE,TIER_INFLUENCER))),"") | D7: =IF($C7="","",IF(VAT_REGISTERED="YES",ROUND($C7-$C7/(1+VAT_RATE),2),0)) | E7: =IF($C7="","",$C7-$D7) | F7: =IFERROR(INDEX(GATE!$D:$D,MATCH($A7,GATE!$A:$A,0)),"") | G7: =IF(OR($E7="",$F7=""),"",$E7-$F7) | H7: =IF($F7="","",ROUND(-$F7*(IF($D$4="ACTUAL",SHRINK_ACTUAL,SHRINK_PLAN)/(1-IF($D$4="ACTUAL",SHRINK_ACTUAL,SHRINK_PLAN))),2)) | I7: =IF($C7="","",ROUND(-$C7*IF($F$4="BANK",FEE_BANK,IF($F$4="MPESA",FEE_MPESA,FEE_CASH)),2)) | J7: =IF($C7="","",IF($I$4="YES",ROUND(-$C7*AGENT_RATE,2),0)) | K7: =IF($C7="","",IF($I$4="YES",ROUND(-EVENT_COST/UNITS_PER_EVENT,2),0)) | L7: =IF($G7="","",ROUND($G7+$H7+$I7+$J7+$K7,2)) | M7: =IF(OR($L7="",$C7=""),"",$L7/$C7) | N7: =IF($L7="","",IF($L7<0,"LOSS",IF($M7<0.15,"THIN","OK"))) | P7: =IFERROR(INDEX(GATE!$G:$G,MATCH($A7,GATE!$A:$A,0)),"")
A8: UC-HOU-URO-001 | B8: =IFERROR(INDEX(GATE!$B:$B,MATCH($A8,GATE!$A:$A,0)),"") | C8: =IFERROR(INDEX(GATE!$G:$G,MATCH($A8,GATE!$A:$A,0))*IF($B$4="RETAIL",1,IF($B$4="WHOLESALE",TIER_WHOLESALE,IF($B$4="CORPORATE",TIER_CORPORATE,TIER_INFLUENCER))),"") | D8: =IF($C8="","",IF(VAT_REGISTERED="YES",ROUND($C8-$C8/(1+VAT_RATE),2),0)) | E8: =IF($C8="","",$C8-$D8) | F8: =IFERROR(INDEX(GATE!$D:$D,MATCH($A8,GATE!$A:$A,0)),"") | G8: =IF(OR($E8="",$F8=""),"",$E8-$F8) | H8: =IF($F8="","",ROUND(-$F8*(IF($D$4="ACTUAL",SHRINK_ACTUAL,SHRINK_PLAN)/(1-IF($D$4="ACTUAL",SHRINK_ACTUAL,SHRINK_PLAN))),2)) | I8: =IF($C8="","",ROUND(-$C8*IF($F$4="BANK",FEE_BANK,IF($F$4="MPESA",FEE_MPESA,FEE_CASH)),2)) | J8: =IF($C8="","",IF($I$4="YES",ROUND(-$C8*AGENT_RATE,2),0)) | K8: =IF($C8="","",IF($I$4="YES",ROUND(-EVENT_COST/UNITS_PER_EVENT,2),0)) | L8: =IF($G8="","",ROUND($G8+$H8+$I8+$J8+$K8,2)) | M8: =IF(OR($L8="",$C8=""),"",$L8/$C8) | N8: =IF($L8="","",IF($L8<0,"LOSS",IF($M8<0.15,"THIN","OK"))) | P8: =IFERROR(INDEX(GATE!$G:$G,MATCH($A8,GATE!$A:$A,0)),"")
A9: UC-HOU-URO-002 | B9: =IFERROR(INDEX(GATE!$B:$B,MATCH($A9,GATE!$A:$A,0)),"") | C9: =IFERROR(INDEX(GATE!$G:$G,MATCH($A9,GATE!$A:$A,0))*IF($B$4="RETAIL",1,IF($B$4="WHOLESALE",TIER_WHOLESALE,IF($B$4="CORPORATE",TIER_CORPORATE,TIER_INFLUENCER))),"") | D9: =IF($C9="","",IF(VAT_REGISTERED="YES",ROUND($C9-$C9/(1+VAT_RATE),2),0)) | E9: =IF($C9="","",$C9-$D9) | F9: =IFERROR(INDEX(GATE!$D:$D,MATCH($A9,GATE!$A:$A,0)),"") | G9: =IF(OR($E9="",$F9=""),"",$E9-$F9) | H9: =IF($F9="","",ROUND(-$F9*(IF($D$4="ACTUAL",SHRINK_ACTUAL,SHRINK_PLAN)/(1-IF($D$4="ACTUAL",SHRINK_ACTUAL,SHRINK_PLAN))),2)) | I9: =IF($C9="","",ROUND(-$C9*IF($F$4="BANK",FEE_BANK,IF($F$4="MPESA",FEE_MPESA,FEE_CASH)),2)) | J9: =IF($C9="","",IF($I$4="YES",ROUND(-$C9*AGENT_RATE,2),0)) | K9: =IF($C9="","",IF($I$4="YES",ROUND(-EVENT_COST/UNITS_PER_EVENT,2),0)) | L9: =IF($G9="","",ROUND($G9+$H9+$I9+$J9+$K9,2)) | M9: =IF(OR($L9="",$C9=""),"",$L9/$C9) | N9: =IF($L9="","",IF($L9<0,"LOSS",IF($M9<0.15,"THIN","OK"))) | P9: =IFERROR(INDEX(GATE!$G:$G,MATCH($A9,GATE!$A:$A,0)),"")
A10: UC-HOU-ROS-001 | B10: =IFERROR(INDEX(GATE!$B:$B,MATCH($A10,GATE!$A:$A,0)),"") | C10: =IFERROR(INDEX(GATE!$G:$G,MATCH($A10,GATE!$A:$A,0))*IF($B$4="RETAIL",1,IF($B$4="WHOLESALE",TIER_WHOLESALE,IF($B$4="CORPORATE",TIER_CORPORATE,TIER_INFLUENCER))),"") | D10: =IF($C10="","",IF(VAT_REGISTERED="YES",ROUND($C10-$C10/(1+VAT_RATE),2),0)) | E10: =IF($C10="","",$C10-$D10) | F10: =IFERROR(INDEX(GATE!$D:$D,MATCH($A10,GATE!$A:$A,0)),"") | G10: =IF(OR($E10="",$F10=""),"",$E10-$F10) | H10: =IF($F10="","",ROUND(-$F10*(IF($D$4="ACTUAL",SHRINK_ACTUAL,SHRINK_PLAN)/(1-IF($D$4="ACTUAL",SHRINK_ACTUAL,SHRINK_PLAN))),2)) | I10: =IF($C10="","",ROUND(-$C10*IF($F$4="BANK",FEE_BANK,IF($F$4="MPESA",FEE_MPESA,FEE_CASH)),2)) | J10: =IF($C10="","",IF($I$4="YES",ROUND(-$C10*AGENT_RATE,2),0)) | K10: =IF($C10="","",IF($I$4="YES",ROUND(-EVENT_COST/UNITS_PER_EVENT,2),0)) | L10: =IF($G10="","",ROUND($G10+$H10+$I10+$J10+$K10,2)) | M10: =IF(OR($L10="",$C10=""),"",$L10/$C10) | N10: =IF($L10="","",IF($L10<0,"LOSS",IF($M10<0.15,"THIN","OK"))) | P10: =IFERROR(INDEX(GATE!$G:$G,MATCH($A10,GATE!$A:$A,0)),"")
A11: UC-COM-ROS-002 | B11: =IFERROR(INDEX(GATE!$B:$B,MATCH($A11,GATE!$A:$A,0)),"") | C11: =IFERROR(INDEX(GATE!$G:$G,MATCH($A11,GATE!$A:$A,0))*IF($B$4="RETAIL",1,IF($B$4="WHOLESALE",TIER_WHOLESALE,IF($B$4="CORPORATE",TIER_CORPORATE,TIER_INFLUENCER))),"") | D11: =IF($C11="","",IF(VAT_REGISTERED="YES",ROUND($C11-$C11/(1+VAT_RATE),2),0)) | E11: =IF($C11="","",$C11-$D11) | F11: =IFERROR(INDEX(GATE!$D:$D,MATCH($A11,GATE!$A:$A,0)),"") | G11: =IF(OR($E11="",$F11=""),"",$E11-$F11) | H11: =IF($F11="","",ROUND(-$F11*(IF($D$4="ACTUAL",SHRINK_ACTUAL,SHRINK_PLAN)/(1-IF($D$4="ACTUAL",SHRINK_ACTUAL,SHRINK_PLAN))),2)) | I11: =IF($C11="","",ROUND(-$C11*IF($F$4="BANK",FEE_BANK,IF($F$4="MPESA",FEE_MPESA,FEE_CASH)),2)) | J11: =IF($C11="","",IF($I$4="YES",ROUND(-$C11*AGENT_RATE,2),0)) | K11: =IF($C11="","",IF($I$4="YES",ROUND(-EVENT_COST/UNITS_PER_EVENT,2),0)) | L11: =IF($G11="","",ROUND($G11+$H11+$I11+$J11+$K11,2)) | M11: =IF(OR($L11="",$C11=""),"",$L11/$C11) | N11: =IF($L11="","",IF($L11<0,"LOSS",IF($M11<0.15,"THIN","OK"))) | P11: =IFERROR(INDEX(GATE!$G:$G,MATCH($A11,GATE!$A:$A,0)),"")
A12: UC-HOU-WPF-003 | B12: =IFERROR(INDEX(GATE!$B:$B,MATCH($A12,GATE!$A:$A,0)),"") | C12: =IFERROR(INDEX(GATE!$G:$G,MATCH($A12,GATE!$A:$A,0))*IF($B$4="RETAIL",1,IF($B$4="WHOLESALE",TIER_WHOLESALE,IF($B$4="CORPORATE",TIER_CORPORATE,TIER_INFLUENCER))),"") | D12: =IF($C12="","",IF(VAT_REGISTERED="YES",ROUND($C12-$C12/(1+VAT_RATE),2),0)) | E12: =IF($C12="","",$C12-$D12) | F12: =IFERROR(INDEX(GATE!$D:$D,MATCH($A12,GATE!$A:$A,0)),"") | G12: =IF(OR($E12="",$F12=""),"",$E12-$F12) | H12: =IF($F12="","",ROUND(-$F12*(IF($D$4="ACTUAL",SHRINK_ACTUAL,SHRINK_PLAN)/(1-IF($D$4="ACTUAL",SHRINK_ACTUAL,SHRINK_PLAN))),2)) | I12: =IF($C12="","",ROUND(-$C12*IF($F$4="BANK",FEE_BANK,IF($F$4="MPESA",FEE_MPESA,FEE_CASH)),2)) | J12: =IF($C12="","",IF($I$4="YES",ROUND(-$C12*AGENT_RATE,2),0)) | K12: =IF($C12="","",IF($I$4="YES",ROUND(-EVENT_COST/UNITS_PER_EVENT,2),0)) | L12: =IF($G12="","",ROUND($G12+$H12+$I12+$J12+$K12,2)) | M12: =IF(OR($L12="",$C12=""),"",$L12/$C12) | N12: =IF($L12="","",IF($L12<0,"LOSS",IF($M12<0.15,"THIN","OK"))) | P12: =IFERROR(INDEX(GATE!$G:$G,MATCH($A12,GATE!$A:$A,0)),"")
A13: UC-HOU-USF-004 | B13: =IFERROR(INDEX(GATE!$B:$B,MATCH($A13,GATE!$A:$A,0)),"") | C13: =IFERROR(INDEX(GATE!$G:$G,MATCH($A13,GATE!$A:$A,0))*IF($B$4="RETAIL",1,IF($B$4="WHOLESALE",TIER_WHOLESALE,IF($B$4="CORPORATE",TIER_CORPORATE,TIER_INFLUENCER))),"") | D13: =IF($C13="","",IF(VAT_REGISTERED="YES",ROUND($C13-$C13/(1+VAT_RATE),2),0)) | E13: =IF($C13="","",$C13-$D13) | F13: =IFERROR(INDEX(GATE!$D:$D,MATCH($A13,GATE!$A:$A,0)),"") | G13: =IF(OR($E13="",$F13=""),"",$E13-$F13) | H13: =IF($F13="","",ROUND(-$F13*(IF($D$4="ACTUAL",SHRINK_ACTUAL,SHRINK_PLAN)/(1-IF($D$4="ACTUAL",SHRINK_ACTUAL,SHRINK_PLAN))),2)) | I13: =IF($C13="","",ROUND(-$C13*IF($F$4="BANK",FEE_BANK,IF($F$4="MPESA",FEE_MPESA,FEE_CASH)),2)) | J13: =IF($C13="","",IF($I$4="YES",ROUND(-$C13*AGENT_RATE,2),0)) | K13: =IF($C13="","",IF($I$4="YES",ROUND(-EVENT_COST/UNITS_PER_EVENT,2),0)) | L13: =IF($G13="","",ROUND($G13+$H13+$I13+$J13+$K13,2)) | M13: =IF(OR($L13="",$C13=""),"",$L13/$C13) | N13: =IF($L13="","",IF($L13<0,"LOSS",IF($M13<0.15,"THIN","OK"))) | P13: =IFERROR(INDEX(GATE!$G:$G,MATCH($A13,GATE!$A:$A,0)),"")
A14: UC-HOU-TAP-005 | B14: =IFERROR(INDEX(GATE!$B:$B,MATCH($A14,GATE!$A:$A,0)),"") | C14: =IFERROR(INDEX(GATE!$G:$G,MATCH($A14,GATE!$A:$A,0))*IF($B$4="RETAIL",1,IF($B$4="WHOLESALE",TIER_WHOLESALE,IF($B$4="CORPORATE",TIER_CORPORATE,TIER_INFLUENCER))),"") | D14: =IF($C14="","",IF(VAT_REGISTERED="YES",ROUND($C14-$C14/(1+VAT_RATE),2),0)) | E14: =IF($C14="","",$C14-$D14) | F14: =IFERROR(INDEX(GATE!$D:$D,MATCH($A14,GATE!$A:$A,0)),"") | G14: =IF(OR($E14="",$F14=""),"",$E14-$F14) | H14: =IF($F14="","",ROUND(-$F14*(IF($D$4="ACTUAL",SHRINK_ACTUAL,SHRINK_PLAN)/(1-IF($D$4="ACTUAL",SHRINK_ACTUAL,SHRINK_PLAN))),2)) | I14: =IF($C14="","",ROUND(-$C14*IF($F$4="BANK",FEE_BANK,IF($F$4="MPESA",FEE_MPESA,FEE_CASH)),2)) | J14: =IF($C14="","",IF($I$4="YES",ROUND(-$C14*AGENT_RATE,2),0)) | K14: =IF($C14="","",IF($I$4="YES",ROUND(-EVENT_COST/UNITS_PER_EVENT,2),0)) | L14: =IF($G14="","",ROUND($G14+$H14+$I14+$J14+$K14,2)) | M14: =IF(OR($L14="",$C14=""),"",$L14/$C14) | N14: =IF($L14="","",IF($L14<0,"LOSS",IF($M14<0.15,"THIN","OK"))) | P14: =IFERROR(INDEX(GATE!$G:$G,MATCH($A14,GATE!$A:$A,0)),"")
A15: UC-HOU-TAPF-006 | B15: =IFERROR(INDEX(GATE!$B:$B,MATCH($A15,GATE!$A:$A,0)),"") | C15: =IFERROR(INDEX(GATE!$G:$G,MATCH($A15,GATE!$A:$A,0))*IF($B$4="RETAIL",1,IF($B$4="WHOLESALE",TIER_WHOLESALE,IF($B$4="CORPORATE",TIER_CORPORATE,TIER_INFLUENCER))),"") | D15: =IF($C15="","",IF(VAT_REGISTERED="YES",ROUND($C15-$C15/(1+VAT_RATE),2),0)) | E15: =IF($C15="","",$C15-$D15) | F15: =IFERROR(INDEX(GATE!$D:$D,MATCH($A15,GATE!$A:$A,0)),"") | G15: =IF(OR($E15="",$F15=""),"",$E15-$F15) | H15: =IF($F15="","",ROUND(-$F15*(IF($D$4="ACTUAL",SHRINK_ACTUAL,SHRINK_PLAN)/(1-IF($D$4="ACTUAL",SHRINK_ACTUAL,SHRINK_PLAN))),2)) | I15: =IF($C15="","",ROUND(-$C15*IF($F$4="BANK",FEE_BANK,IF($F$4="MPESA",FEE_MPESA,FEE_CASH)),2)) | J15: =IF($C15="","",IF($I$4="YES",ROUND(-$C15*AGENT_RATE,2),0)) | K15: =IF($C15="","",IF($I$4="YES",ROUND(-EVENT_COST/UNITS_PER_EVENT,2),0)) | L15: =IF($G15="","",ROUND($G15+$H15+$I15+$J15+$K15,2)) | M15: =IF(OR($L15="",$C15=""),"",$L15/$C15) | N15: =IF($L15="","",IF($L15<0,"LOSS",IF($M15<0.15,"THIN","OK"))) | P15: =IFERROR(INDEX(GATE!$G:$G,MATCH($A15,GATE!$A:$A,0)),"")
A16: UC-HOU-WDFS-006 | B16: =IFERROR(INDEX(GATE!$B:$B,MATCH($A16,GATE!$A:$A,0)),"") | C16: =IFERROR(INDEX(GATE!$G:$G,MATCH($A16,GATE!$A:$A,0))*IF($B$4="RETAIL",1,IF($B$4="WHOLESALE",TIER_WHOLESALE,IF($B$4="CORPORATE",TIER_CORPORATE,TIER_INFLUENCER))),"") | D16: =IF($C16="","",IF(VAT_REGISTERED="YES",ROUND($C16-$C16/(1+VAT_RATE),2),0)) | E16: =IF($C16="","",$C16-$D16) | F16: =IFERROR(INDEX(GATE!$D:$D,MATCH($A16,GATE!$A:$A,0)),"") | G16: =IF(OR($E16="",$F16=""),"",$E16-$F16) | H16: =IF($F16="","",ROUND(-$F16*(IF($D$4="ACTUAL",SHRINK_ACTUAL,SHRINK_PLAN)/(1-IF($D$4="ACTUAL",SHRINK_ACTUAL,SHRINK_PLAN))),2)) | I16: =IF($C16="","",ROUND(-$C16*IF($F$4="BANK",FEE_BANK,IF($F$4="MPESA",FEE_MPESA,FEE_CASH)),2)) | J16: =IF($C16="","",IF($I$4="YES",ROUND(-$C16*AGENT_RATE,2),0)) | K16: =IF($C16="","",IF($I$4="YES",ROUND(-EVENT_COST/UNITS_PER_EVENT,2),0)) | L16: =IF($G16="","",ROUND($G16+$H16+$I16+$J16+$K16,2)) | M16: =IF(OR($L16="",$C16=""),"",$L16/$C16) | N16: =IF($L16="","",IF($L16<0,"LOSS",IF($M16<0.15,"THIN","OK"))) | P16: =IFERROR(INDEX(GATE!$G:$G,MATCH($A16,GATE!$A:$A,0)),"")
A17: UC-HOU-DF-007 | B17: =IFERROR(INDEX(GATE!$B:$B,MATCH($A17,GATE!$A:$A,0)),"") | C17: =IFERROR(INDEX(GATE!$G:$G,MATCH($A17,GATE!$A:$A,0))*IF($B$4="RETAIL",1,IF($B$4="WHOLESALE",TIER_WHOLESALE,IF($B$4="CORPORATE",TIER_CORPORATE,TIER_INFLUENCER))),"") | D17: =IF($C17="","",IF(VAT_REGISTERED="YES",ROUND($C17-$C17/(1+VAT_RATE),2),0)) | E17: =IF($C17="","",$C17-$D17) | F17: =IFERROR(INDEX(GATE!$D:$D,MATCH($A17,GATE!$A:$A,0)),"") | G17: =IF(OR($E17="",$F17=""),"",$E17-$F17) | H17: =IF($F17="","",ROUND(-$F17*(IF($D$4="ACTUAL",SHRINK_ACTUAL,SHRINK_PLAN)/(1-IF($D$4="ACTUAL",SHRINK_ACTUAL,SHRINK_PLAN))),2)) | I17: =IF($C17="","",ROUND(-$C17*IF($F$4="BANK",FEE_BANK,IF($F$4="MPESA",FEE_MPESA,FEE_CASH)),2)) | J17: =IF($C17="","",IF($I$4="YES",ROUND(-$C17*AGENT_RATE,2),0)) | K17: =IF($C17="","",IF($I$4="YES",ROUND(-EVENT_COST/UNITS_PER_EVENT,2),0)) | L17: =IF($G17="","",ROUND($G17+$H17+$I17+$J17+$K17,2)) | M17: =IF(OR($L17="",$C17=""),"",$L17/$C17) | N17: =IF($L17="","",IF($L17<0,"LOSS",IF($M17<0.15,"THIN","OK"))) | P17: =IFERROR(INDEX(GATE!$G:$G,MATCH($A17,GATE!$A:$A,0)),"")
A18: UC-BOG-SSB-008 | B18: =IFERROR(INDEX(GATE!$B:$B,MATCH($A18,GATE!$A:$A,0)),"") | C18: =IFERROR(INDEX(GATE!$G:$G,MATCH($A18,GATE!$A:$A,0))*IF($B$4="RETAIL",1,IF($B$4="WHOLESALE",TIER_WHOLESALE,IF($B$4="CORPORATE",TIER_CORPORATE,TIER_INFLUENCER))),"") | D18: =IF($C18="","",IF(VAT_REGISTERED="YES",ROUND($C18-$C18/(1+VAT_RATE),2),0)) | E18: =IF($C18="","",$C18-$D18) | F18: =IFERROR(INDEX(GATE!$D:$D,MATCH($A18,GATE!$A:$A,0)),"") | G18: =IF(OR($E18="",$F18=""),"",$E18-$F18) | H18: =IF($F18="","",ROUND(-$F18*(IF($D$4="ACTUAL",SHRINK_ACTUAL,SHRINK_PLAN)/(1-IF($D$4="ACTUAL",SHRINK_ACTUAL,SHRINK_PLAN))),2)) | I18: =IF($C18="","",ROUND(-$C18*IF($F$4="BANK",FEE_BANK,IF($F$4="MPESA",FEE_MPESA,FEE_CASH)),2)) | J18: =IF($C18="","",IF($I$4="YES",ROUND(-$C18*AGENT_RATE,2),0)) | K18: =IF($C18="","",IF($I$4="YES",ROUND(-EVENT_COST/UNITS_PER_EVENT,2),0)) | L18: =IF($G18="","",ROUND($G18+$H18+$I18+$J18+$K18,2)) | M18: =IF(OR($L18="",$C18=""),"",$L18/$C18) | N18: =IF($L18="","",IF($L18<0,"LOSS",IF($M18<0.15,"THIN","OK"))) | P18: =IFERROR(INDEX(GATE!$G:$G,MATCH($A18,GATE!$A:$A,0)),"")
... A37: UC-BOG-ECO-ECF1 | B37: =IFERROR(INDEX(GATE!$B:$B,MATCH($A37,GATE!$A:$A,0)),"") | C37: =IFERROR(INDEX(GATE!$G:$G,MATCH($A37,GATE!$A:$A,0))*IF($B$4="RETAIL",1,IF($B$4="WHOLESALE",TIER_WHOLESALE,IF($B$4="CORPORATE",TIER_CORPORATE,TIER_INFLUENCER))),"") | D37: =IF($C37="","",IF(VAT_REGISTERED="YES",ROUND($C37-$C37/(1+VAT_RATE),2),0)) | E37: =IF($C37="","",$C37-$D37) | F37: =IFERROR(INDEX(GATE!$D:$D,MATCH($A37,GATE!$A:$A,0)),"") | G37: =IF(OR($E37="",$F37=""),"",$E37-$F37) | H37: =IF($F37="","",ROUND(-$F37*(IF($D$4="ACTUAL",SHRINK_ACTUAL,SHRINK_PLAN)/(1-IF($D$4="ACTUAL",SHRINK_ACTUAL,SHRINK_PLAN))),2)) | I37: =IF($C37="","",ROUND(-$C37*IF($F$4="BANK",FEE_BANK,IF($F$4="MPESA",FEE_MPESA,FEE_CASH)),2)) | J37: =IF($C37="","",IF($I$4="YES",ROUND(-$C37*AGENT_RATE,2),0)) | K37: =IF($C37="","",IF($I$4="YES",ROUND(-EVENT_COST/UNITS_PER_EVENT,2),0)) | L37: =IF($G37="","",ROUND($G37+$H37+$I37+$J37+$K37,2)) | M37: =IF(OR($L37="",$C37=""),"",$L37/$C37) | N37: =IF($L37="","",IF($L37<0,"LOSS",IF($M37<0.15,"THIN","OK"))) | P37: =IFERROR(INDEX(GATE!$G:$G,MATCH($A37,GATE!$A:$A,0)),"")
B39: TOTALS / AVERAGE | C39: =SUM(C7:C37) | F39: =SUM(F7:F37) | G39: =SUM(G7:G37) | H39: =SUM(H7:H37) | I39: =SUM(I7:I37) | J39: =SUM(J7:J37) | K39: =SUM(K7:K37) | L39: =SUM(L7:L37) | M39: =IF($C39=0,"",$L39/$C39)
B41: LOSS | C41: =COUNTIF($N$7:$N$37,"LOSS")
B42: THIN | C42: =COUNTIF($N$7:$N$37,"THIN")
B43: OK | C43: =COUNTIF($N$7:$N$37,"OK")

Sheet CHANNEL_ECONOMICS
A1: CHANNEL ECONOMICS — the same basket sold five ways, at three shrinkage rates
A2: One unit of every publishable SKU (31 products). Live: change any parameter on GUARDRAILS and every cell below moves.
A4: CHANNEL | B4: SHRINKAGE | C4: REVENUE | D4: LANDED | E4: GROSS | F4: SHRINK LOSS | G4: PAY FEE | H4: AGENT | I4: EVENT | J4: CONTRIBUTION | K4: MARGIN | L4: VERDICT
A5: Retail walk-in | B5: historical 37.3% | C5: =SUM(UNIT_ECONOMICS!$P$7:$P$37)*1 | D5: =SUM(UNIT_ECONOMICS!$F$7:$F$37) | E5: =$C5-$D5 | F5: =-$D5*(SHRINK_ACTUAL/(1-SHRINK_ACTUAL)) | G5: =-$C5*FEE_MPESA | H5: =-$C5*AGENT_RATE*0 | I5: =-31*EVENT_COST/UNITS_PER_EVENT*0 | J5: =SUM($E5:$I5) | K5: =IF($C5=0,"",$J5/$C5) | L5: =IF($J5<0,"LOSS",IF($K5<0.15,"THIN","OK"))
B6: plan 10% | C6: =SUM(UNIT_ECONOMICS!$P$7:$P$37)*1 | D6: =SUM(UNIT_ECONOMICS!$F$7:$F$37) | E6: =$C6-$D6 | F6: =-$D6*(SHRINK_PLAN/(1-SHRINK_PLAN)) | G6: =-$C6*FEE_MPESA | H6: =-$C6*AGENT_RATE*0 | I6: =-31*EVENT_COST/UNITS_PER_EVENT*0 | J6: =SUM($E6:$I6) | K6: =IF($C6=0,"",$J6/$C6) | L6: =IF($J6<0,"LOSS",IF($K6<0.15,"THIN","OK"))
B7: best case 5% | C7: =SUM(UNIT_ECONOMICS!$P$7:$P$37)*1 | D7: =SUM(UNIT_ECONOMICS!$F$7:$F$37) | E7: =$C7-$D7 | F7: =-$D7*(0.05/(1-0.05)) | G7: =-$C7*FEE_MPESA | H7: =-$C7*AGENT_RATE*0 | I7: =-31*EVENT_COST/UNITS_PER_EVENT*0 | J7: =SUM($E7:$I7) | K7: =IF($C7=0,"",$J7/$C7) | L7: =IF($J7<0,"LOSS",IF($K7<0.15,"THIN","OK"))
A8: Activation (agent + event) | B8: historical 37.3% | C8: =SUM(UNIT_ECONOMICS!$P$7:$P$37)*1 | D8: =SUM(UNIT_ECONOMICS!$F$7:$F$37) | E8: =$C8-$D8 | F8: =-$D8*(SHRINK_ACTUAL/(1-SHRINK_ACTUAL)) | G8: =-$C8*FEE_MPESA | H8: =-$C8*AGENT_RATE*1 | I8: =-31*EVENT_COST/UNITS_PER_EVENT*1 | J8: =SUM($E8:$I8) | K8: =IF($C8=0,"",$J8/$C8) | L8: =IF($J8<0,"LOSS",IF($K8<0.15,"THIN","OK"))
B9: plan 10% | C9: =SUM(UNIT_ECONOMICS!$P$7:$P$37)*1 | D9: =SUM(UNIT_ECONOMICS!$F$7:$F$37) | E9: =$C9-$D9 | F9: =-$D9*(SHRINK_PLAN/(1-SHRINK_PLAN)) | G9: =-$C9*FEE_MPESA | H9: =-$C9*AGENT_RATE*1 | I9: =-31*EVENT_COST/UNITS_PER_EVENT*1 | J9: =SUM($E9:$I9) | K9: =IF($C9=0,"",$J9/$C9) | L9: =IF($J9<0,"LOSS",IF($K9<0.15,"THIN","OK"))
B10: best case 5% | C10: =SUM(UNIT_ECONOMICS!$P$7:$P$37)*1 | D10: =SUM(UNIT_ECONOMICS!$F$7:$F$37) | E10: =$C10-$D10 | F10: =-$D10*(0.05/(1-0.05)) | G10: =-$C10*FEE_MPESA | H10: =-$C10*AGENT_RATE*1 | I10: =-31*EVENT_COST/UNITS_PER_EVENT*1 | J10: =SUM($E10:$I10) | K10: =IF($C10=0,"",$J10/$C10) | L10: =IF($J10<0,"LOSS",IF($K10<0.15,"THIN","OK"))
A11: Wholesale | B11: historical 37.3% | C11: =SUM(UNIT_ECONOMICS!$P$7:$P$37)*TIER_WHOLESALE | D11: =SUM(UNIT_ECONOMICS!$F$7:$F$37) | E11: =$C11-$D11 | F11: =-$D11*(SHRINK_ACTUAL/(1-SHRINK_ACTUAL)) | G11: =-$C11*FEE_BANK | H11: =-$C11*AGENT_RATE*0 | I11: =-31*EVENT_COST/UNITS_PER_EVENT*0 | J11: =SUM($E11:$I11) | K11: =IF($C11=0,"",$J11/$C11) | L11: =IF($J11<0,"LOSS",IF($K11<0.15,"THIN","OK"))
B12: plan 10% | C12: =SUM(UNIT_ECONOMICS!$P$7:$P$37)*TIER_WHOLESALE | D12: =SUM(UNIT_ECONOMICS!$F$7:$F$37) | E12: =$C12-$D12 | F12: =-$D12*(SHRINK_PLAN/(1-SHRINK_PLAN)) | G12: =-$C12*FEE_BANK | H12: =-$C12*AGENT_RATE*0 | I12: =-31*EVENT_COST/UNITS_PER_EVENT*0 | J12: =SUM($E12:$I12) | K12: =IF($C12=0,"",$J12/$C12) | L12: =IF($J12<0,"LOSS",IF($K12<0.15,"THIN","OK"))
B13: best case 5% | C13: =SUM(UNIT_ECONOMICS!$P$7:$P$37)*TIER_WHOLESALE | D13: =SUM(UNIT_ECONOMICS!$F$7:$F$37) | E13: =$C13-$D13 | F13: =-$D13*(0.05/(1-0.05)) | G13: =-$C13*FEE_BANK | H13: =-$C13*AGENT_RATE*0 | I13: =-31*EVENT_COST/UNITS_PER_EVENT*0 | J13: =SUM($E13:$I13) | K13: =IF($C13=0,"",$J13/$C13) | L13: =IF($J13<0,"LOSS",IF($K13<0.15,"THIN","OK"))
A14: Corporate | B14: historical 37.3% | C14: =SUM(UNIT_ECONOMICS!$P$7:$P$37)*TIER_CORPORATE | D14: =SUM(UNIT_ECONOMICS!$F$7:$F$37) | E14: =$C14-$D14 | F14: =-$D14*(SHRINK_ACTUAL/(1-SHRINK_ACTUAL)) | G14: =-$C14*FEE_BANK | H14: =-$C14*AGENT_RATE*0 | I14: =-31*EVENT_COST/UNITS_PER_EVENT*0 | J14: =SUM($E14:$I14) | K14: =IF($C14=0,"",$J14/$C14) | L14: =IF($J14<0,"LOSS",IF($K14<0.15,"THIN","OK"))
B15: plan 10% | C15: =SUM(UNIT_ECONOMICS!$P$7:$P$37)*TIER_CORPORATE | D15: =SUM(UNIT_ECONOMICS!$F$7:$F$37) | E15: =$C15-$D15 | F15: =-$D15*(SHRINK_PLAN/(1-SHRINK_PLAN)) | G15: =-$C15*FEE_BANK | H15: =-$C15*AGENT_RATE*0 | I15: =-31*EVENT_COST/UNITS_PER_EVENT*0 | J15: =SUM($E15:$I15) | K15: =IF($C15=0,"",$J15/$C15) | L15: =IF($J15<0,"LOSS",IF($K15<0.15,"THIN","OK"))
B16: best case 5% | C16: =SUM(UNIT_ECONOMICS!$P$7:$P$37)*TIER_CORPORATE | D16: =SUM(UNIT_ECONOMICS!$F$7:$F$37) | E16: =$C16-$D16 | F16: =-$D16*(0.05/(1-0.05)) | G16: =-$C16*FEE_BANK | H16: =-$C16*AGENT_RATE*0 | I16: =-31*EVENT_COST/UNITS_PER_EVENT*0 | J16: =SUM($E16:$I16) | K16: =IF($C16=0,"",$J16/$C16) | L16: =IF($J16<0,"LOSS",IF($K16<0.15,"THIN","OK"))
A17: Influencer | B17: historical 37.3% | C17: =SUM(UNIT_ECONOMICS!$P$7:$P$37)*TIER_INFLUENCER | D17: =SUM(UNIT_ECONOMICS!$F$7:$F$37) | E17: =$C17-$D17 | F17: =-$D17*(SHRINK_ACTUAL/(1-SHRINK_ACTUAL)) | G17: =-$C17*FEE_MPESA | H17: =-$C17*AGENT_RATE*0 | I17: =-31*EVENT_COST/UNITS_PER_EVENT*0 | J17: =SUM($E17:$I17) | K17: =IF($C17=0,"",$J17/$C17) | L17: =IF($J17<0,"LOSS",IF($K17<0.15,"THIN","OK"))
B18: plan 10% | C18: =SUM(UNIT_ECONOMICS!$P$7:$P$37)*TIER_INFLUENCER | D18: =SUM(UNIT_ECONOMICS!$F$7:$F$37) | E18: =$C18-$D18 | F18: =-$D18*(SHRINK_PLAN/(1-SHRINK_PLAN)) | G18: =-$C18*FEE_MPESA | H18: =-$C18*AGENT_RATE*0 | I18: =-31*EVENT_COST/UNITS_PER_EVENT*0 | J18: =SUM($E18:$I18) | K18: =IF($C18=0,"",$J18/$C18) | L18: =IF($J18<0,"LOSS",IF($K18<0.15,"THIN","OK"))
B19: best case 5% | C19: =SUM(UNIT_ECONOMICS!$P$7:$P$37)*TIER_INFLUENCER | D19: =SUM(UNIT_ECONOMICS!$F$7:$F$37) | E19: =$C19-$D19 | F19: =-$D19*(0.05/(1-0.05)) | G19: =-$C19*FEE_MPESA | H19: =-$C19*AGENT_RATE*0 | I19: =-31*EVENT_COST/UNITS_PER_EVENT*0 | J19: =SUM($E19:$I19) | K19: =IF($C19=0,"",$J19/$C19) | L19: =IF($J19<0,"LOSS",IF($K19<0.15,"THIN","OK"))
A21: ACTIVATION BREAK-EVEN
A22: Units that must sell at one event before the KES 7,000 of venue and staff is covered.
A23: SHRINKAGE | B23: AVG PRICE/UNIT | C23: CONTRIBUTION/UNIT before event | D23: UNITS NEEDED | E23: RUNNING AT | F23: GAP
A24: historical 37.3% | B24: =SUM(UNIT_ECONOMICS!$P$7:$P$37)/31 | C24: =(SUM(UNIT_ECONOMICS!$P$7:$P$37)-SUM(UNIT_ECONOMICS!$F$7:$F$37)-SUM(UNIT_ECONOMICS!$F$7:$F$37)*(SHRINK_ACTUAL/(1-SHRINK_ACTUAL))-SUM(UNIT_ECONOMICS!$P$7:$P$37)*FEE_MPESA-SUM(UNIT_ECONOMICS!$P$7:$P$37)*AGENT_RATE)/31 | D24: =IF($C24<=0,"never — negative before the event cost",ROUND(EVENT_COST/$C24,1)) | E24: =UNITS_PER_EVENT | F24: =IF(ISNUMBER($D24),ROUND($D24-$E24,1),"—")
A25: plan 10% | B25: =SUM(UNIT_ECONOMICS!$P$7:$P$37)/31 | C25: =(SUM(UNIT_ECONOMICS!$P$7:$P$37)-SUM(UNIT_ECONOMICS!$F$7:$F$37)-SUM(UNIT_ECONOMICS!$F$7:$F$37)*(SHRINK_PLAN/(1-SHRINK_PLAN))-SUM(UNIT_ECONOMICS!$P$7:$P$37)*FEE_MPESA-SUM(UNIT_ECONOMICS!$P$7:$P$37)*AGENT_RATE)/31 | D25: =IF($C25<=0,"never — negative before the event cost",ROUND(EVENT_COST/$C25,1)) | E25: =UNITS_PER_EVENT | F25: =IF(ISNUMBER($D25),ROUND($D25-$E25,1),"—")
A26: best case 5% | B26: =SUM(UNIT_ECONOMICS!$P$7:$P$37)/31 | C26: =(SUM(UNIT_ECONOMICS!$P$7:$P$37)-SUM(UNIT_ECONOMICS!$F$7:$F$37)-SUM(UNIT_ECONOMICS!$F$7:$F$37)*(0.05/(1-0.05))-SUM(UNIT_ECONOMICS!$P$7:$P$37)*FEE_MPESA-SUM(UNIT_ECONOMICS!$P$7:$P$37)*AGENT_RATE)/31 | D26: =IF($C26<=0,"never — negative before the event cost",ROUND(EVENT_COST/$C26,1)) | E26: =UNITS_PER_EVENT | F26: =IF(ISNUMBER($D26),ROUND($D26-$E26,1),"—")
A28: The activation programme is not a pricing problem.
A29: At the historical shrinkage rate a unit is already loss-making before anyone pays for a venue. At a 10% rate it needs about ten units an event; it is running at three. Either the basket triples, the event cost falls, or the channel is for lead generation and should be funded from a marketing budget rather than expected to pay for itself on unit margin.

Sheet CLOSURE_PLAN
B1: CLOSING THE SKU AND PRICE CHAPTER
B2: Six items. Each has one decision, one owner and one test that proves it closed. Nothing here needs new analysis.
A4: No. | B4: ITEM | C4: TYPE | D4: DECIDED BY | E4: THE DECISION, AND WHAT CLOSES IT | F4: GATE TEST
A5: 1 | B5: Tax status — registered or not | C5: PARAMETER | D5: Accountant | E5: F-9 settles it: bears VAT, does not charge it. GUARDRAILS now carries VAT_REGISTERED = NO and the whole book re-prices from it. CLOSED the moment the accountant confirms in writing; the switch is already built so confirmation changes one cell, not the analysis. | F5: MULT_RETAIL
A6: 2 | B6: Ratify UC-BOG-FCB-028 | C6: ISSUE | D6: Master / CEO | E6: Two physically different cartridges share UC-BOG-FCA-015. Say yes to the proposed number and the split is done. Closes when SKU_REGISTRY shows ISSUED instead of PROPOSED. | F6: G2
A7: 3 | B7: Five impossible cost rows | C7: DATA | D7: Procurement | E7: FLB-012, SQB-013, SQB-014, FCS-017, DFS-024 record landed cost BELOW ex-works. One of the two numbers on each row is wrong — check the supplier invoice, correct whichever is wrong. Five lookups. | F7: G6
A8: 4 | B8: Four SKUs with no landed cost | C8: DATA | D8: Procurement | E8: UF-100, DFS-025, DFS-026, ROT-029. Get carton dimensions and ex-works from the supplier; freight then derives itself. Until then the gate correctly holds them out of the catalogue. | F8: G5
A9: 5 | B9: Aqua Stream carton dimensions | C9: DATA | D9: Supplier | E9: Currently on a comparable carton, BASIS = ESTIMATE. Real dimensions move it to DERIVED and will RAISE the freight, because a 1200GPD twin-membrane unit is larger than the 800G it was compared to. | F9: BASIS
A10: 6 | B10: Beauty Faucet Filter | C10: RULING | D10: CEO | E10: Same parent as UC-SKW-DFS-024, or a separate product? One sentence either way. | F10: G4
B12: WHAT "CLOSED" MEANS
B13: The chapter is closed when GATE shows zero BLOCKED rows and SKU_REGISTRY shows zero PROPOSED rows. Not when a meeting agrees — when the file says so. Everything above is a data errand or a one-line ruling; none of it needs further analysis, and none of it blocks the unit-economics work.
B15: AND ONE CORRECTION I OWE
B16: The guardrail shipped on 17 Sep derived MULT_RETAIL = 2.00 from a 1.5660 floor. F-9 (FINAL, 9 Sep 2026) had already settled the floor at 1.35 — the 31 Aug recut had counted VAT twice. MULT_RETAIL is now 1.73 and every price in this file has moved down accordingly, by 13.5%. The method was right; the input was stale, because I did not re-read the development record before building. That is the same failure this project keeps finding: one value living in two places.

Sheet GATE
A1: GATE — every parent, every rule, live. A product reaches the catalogue only when PUBLISH says GO.
A2: PRICE_ACTUAL is yours to set. PRICE_MIN is the FLOOR-BINDING minimum (cost x R4_FLOOR / deepest tier). The gate only checks that actual is not BELOW it - judgement may price above it freely. MULT_RETAIL (2.00) is the engine default that lands safely above PRICE_MIN.
A4: PARENT_SKU | B4: MODEL | C4: STOCK_STATUS | D4: COST_KES | E4: COST_BASIS | F4: PRICE_MIN (floor-binding) | G4: PRICE_ACTUAL | H4: HEADROOM | I4: MAX_DISC | J4: WHSL_PUB | K4: CORP_PUB | L4: INFL_PUB | M4: G1 | N4: G2 | O4: G5 | P4: G6 | Q4: G7 | R4: G8 | S4: PUBLISH | T4: WHY NOT
A5: UC-HOU-PHRO-001 | B5: =IFERROR(INDEX(LANDED_COST_BUILD!$B:$B,MATCH($A5,LANDED_COST_BUILD!$A:$A,0)),"") | C5: =IFERROR(INDEX(LANDED_COST_BUILD!$C:$C,MATCH($A5,LANDED_COST_BUILD!$A:$A,0)),"") | D5: =IFERROR(IF(INDEX(LANDED_COST_BUILD!$O:$O,MATCH($A5,LANDED_COST_BUILD!$A:$A,0))="","",INDEX(LANDED_COST_BUILD!$O:$O,MATCH($A5,LANDED_COST_BUILD!$A:$A,0))*FX_USD_KES),"") | E5: =IFERROR(LEFT(INDEX(LANDED_COST_BUILD!$P:$P,MATCH($A5,LANDED_COST_BUILD!$A:$A,0)),FIND(" ",INDEX(LANDED_COST_BUILD!$P:$P,MATCH($A5,LANDED_COST_BUILD!$A:$A,0))&" ")-1),"") | F5: =IF($D5="","",ROUNDUP($D5*R4_FLOOR/MIN_TIER_RATE,0)) | G5: =IFERROR(INDEX('SKU with PRICES'!$M:$M,MATCH($A5,'SKU with PRICES'!$H:$H,0)),"") | H5: =IF(OR($D5="",$G5=""),"",ROUND($G5/($D5*R4_FLOOR)-1,4)) | I5: =IF(OR($D5="",$G5=""),"",MAX(0,1-($D5*R4_FLOOR/$G5))) | J5: =IFERROR(INDEX('SKU with PRICES'!$O:$O,MATCH($A5,'SKU with PRICES'!$H:$H,0)),"") | K5: =IFERROR(INDEX('SKU with PRICES'!$Q:$Q,MATCH($A5,'SKU with PRICES'!$H:$H,0)),"") | L5: =IFERROR(INDEX('SKU with PRICES'!$S:$S,MATCH($A5,'SKU with PRICES'!$H:$H,0)),"") | M5: =IF(AND(LEFT($A5,3)="UC-",LEN($A5)>=13),"PASS","FAIL") | N5: =IF(COUNTIF($A$5:$A$99,$A5)=1,"PASS","FAIL") | O5: =IF($E5="NONE","FAIL",IF($E5="RECORDED","WARN","PASS")) | P5: =IFERROR(IF(INDEX(LANDED_COST_BUILD!$O:$O,MATCH($A5,LANDED_COST_BUILD!$A:$A,0))="","n/a",IF(INDEX(LANDED_COST_BUILD!$O:$O,MATCH($A5,LANDED_COST_BUILD!$A:$A,0))<INDEX(LANDED_COST_BUILD!$G:$G,MATCH($A5,LANDED_COST_BUILD!$A:$A,0)),"FAIL","PASS")),"n/a") | Q5: =IF(OR($F5="",$G5=""),"n/a",IF($G5>=$F5,"PASS","FAIL")) | R5: =IF($D5="","n/a",IF(AND(N($J5)>=$D5*R4_FLOOR,N($K5)>=$D5*R4_FLOOR,N($L5)>=$D5*R4_FLOOR),"PASS","FAIL")) | S5: =IF(COUNTIF($M5:$R5,"FAIL")>0,"BLOCKED",IF($D5="","HOLD - no cost","GO")) | T5: =IF($S5="GO","",IF($M5="FAIL","SKU format. ","")&IF($N5="FAIL","Duplicate SKU. ","")&IF($P5="FAIL","Landed cost is below ex-works - impossible. ","")&IF($Q5="FAIL","Retail is below the floor-binding minimum. ","")&IF($R5="FAIL","A published discount tier breaches the floor. ","")&IF($D5="","No cost recorded - cannot be gated or published. ",""))
A6: UC-HOU-URO-001 | B6: =IFERROR(INDEX(LANDED_COST_BUILD!$B:$B,MATCH($A6,LANDED_COST_BUILD!$A:$A,0)),"") | C6: =IFERROR(INDEX(LANDED_COST_BUILD!$C:$C,MATCH($A6,LANDED_COST_BUILD!$A:$A,0)),"") | D6: =IFERROR(IF(INDEX(LANDED_COST_BUILD!$O:$O,MATCH($A6,LANDED_COST_BUILD!$A:$A,0))="","",INDEX(LANDED_COST_BUILD!$O:$O,MATCH($A6,LANDED_COST_BUILD!$A:$A,0))*FX_USD_KES),"") | E6: =IFERROR(LEFT(INDEX(LANDED_COST_BUILD!$P:$P,MATCH($A6,LANDED_COST_BUILD!$A:$A,0)),FIND(" ",INDEX(LANDED_COST_BUILD!$P:$P,MATCH($A6,LANDED_COST_BUILD!$A:$A,0))&" ")-1),"") | F6: =IF($D6="","",ROUNDUP($D6*R4_FLOOR/MIN_TIER_RATE,0)) | G6: =IFERROR(INDEX('SKU with PRICES'!$M:$M,MATCH($A6,'SKU with PRICES'!$H:$H,0)),"") | H6: =IF(OR($D6="",$G6=""),"",ROUND($G6/($D6*R4_FLOOR)-1,4)) | I6: =IF(OR($D6="",$G6=""),"",MAX(0,1-($D6*R4_FLOOR/$G6))) | J6: =IFERROR(INDEX('SKU with PRICES'!$O:$O,MATCH($A6,'SKU with PRICES'!$H:$H,0)),"") | K6: =IFERROR(INDEX('SKU with PRICES'!$Q:$Q,MATCH($A6,'SKU with PRICES'!$H:$H,0)),"") | L6: =IFERROR(INDEX('SKU with PRICES'!$S:$S,MATCH($A6,'SKU with PRICES'!$H:$H,0)),"") | M6: =IF(AND(LEFT($A6,3)="UC-",LEN($A6)>=13),"PASS","FAIL") | N6: =IF(COUNTIF($A$5:$A$99,$A6)=1,"PASS","FAIL") | O6: =IF($E6="NONE","FAIL",IF($E6="RECORDED","WARN","PASS")) | P6: =IFERROR(IF(INDEX(LANDED_COST_BUILD!$O:$O,MATCH($A6,LANDED_COST_BUILD!$A:$A,0))="","n/a",IF(INDEX(LANDED_COST_BUILD!$O:$O,MATCH($A6,LANDED_COST_BUILD!$A:$A,0))<INDEX(LANDED_COST_BUILD!$G:$G,MATCH($A6,LANDED_COST_BUILD!$A:$A,0)),"FAIL","PASS")),"n/a") | Q6: =IF(OR($F6="",$G6=""),"n/a",IF($G6>=$F6,"PASS","FAIL")) | R6: =IF($D6="","n/a",IF(AND(N($J6)>=$D6*R4_FLOOR,N($K6)>=$D6*R4_FLOOR,N($L6)>=$D6*R4_FLOOR),"PASS","FAIL")) | S6: =IF(COUNTIF($M6:$R6,"FAIL")>0,"BLOCKED",IF($D6="","HOLD - no cost","GO")) | T6: =IF($S6="GO","",IF($M6="FAIL","SKU format. ","")&IF($N6="FAIL","Duplicate SKU. ","")&IF($P6="FAIL","Landed cost is below ex-works - impossible. ","")&IF($Q6="FAIL","Retail is below the floor-binding minimum. ","")&IF($R6="FAIL","A published discount tier breaches the floor. ","")&IF($D6="","No cost recorded - cannot be gated or published. ",""))
A7: UC-HOU-URO-002 | B7: =IFERROR(INDEX(LANDED_COST_BUILD!$B:$B,MATCH($A7,LANDED_COST_BUILD!$A:$A,0)),"") | C7: =IFERROR(INDEX(LANDED_COST_BUILD!$C:$C,MATCH($A7,LANDED_COST_BUILD!$A:$A,0)),"") | D7: =IFERROR(IF(INDEX(LANDED_COST_BUILD!$O:$O,MATCH($A7,LANDED_COST_BUILD!$A:$A,0))="","",INDEX(LANDED_COST_BUILD!$O:$O,MATCH($A7,LANDED_COST_BUILD!$A:$A,0))*FX_USD_KES),"") | E7: =IFERROR(LEFT(INDEX(LANDED_COST_BUILD!$P:$P,MATCH($A7,LANDED_COST_BUILD!$A:$A,0)),FIND(" ",INDEX(LANDED_COST_BUILD!$P:$P,MATCH($A7,LANDED_COST_BUILD!$A:$A,0))&" ")-1),"") | F7: =IF($D7="","",ROUNDUP($D7*R4_FLOOR/MIN_TIER_RATE,0)) | G7: =IFERROR(INDEX('SKU with PRICES'!$M:$M,MATCH($A7,'SKU with PRICES'!$H:$H,0)),"") | H7: =IF(OR($D7="",$G7=""),"",ROUND($G7/($D7*R4_FLOOR)-1,4)) | I7: =IF(OR($D7="",$G7=""),"",MAX(0,1-($D7*R4_FLOOR/$G7))) | J7: =IFERROR(INDEX('SKU with PRICES'!$O:$O,MATCH($A7,'SKU with PRICES'!$H:$H,0)),"") | K7: =IFERROR(INDEX('SKU with PRICES'!$Q:$Q,MATCH($A7,'SKU with PRICES'!$H:$H,0)),"") | L7: =IFERROR(INDEX('SKU with PRICES'!$S:$S,MATCH($A7,'SKU with PRICES'!$H:$H,0)),"") | M7: =IF(AND(LEFT($A7,3)="UC-",LEN($A7)>=13),"PASS","FAIL") | N7: =IF(COUNTIF($A$5:$A$99,$A7)=1,"PASS","FAIL") | O7: =IF($E7="NONE","FAIL",IF($E7="RECORDED","WARN","PASS")) | P7: =IFERROR(IF(INDEX(LANDED_COST_BUILD!$O:$O,MATCH($A7,LANDED_COST_BUILD!$A:$A,0))="","n/a",IF(INDEX(LANDED_COST_BUILD!$O:$O,MATCH($A7,LANDED_COST_BUILD!$A:$A,0))<INDEX(LANDED_COST_BUILD!$G:$G,MATCH($A7,LANDED_COST_BUILD!$A:$A,0)),"FAIL","PASS")),"n/a") | Q7: =IF(OR($F7="",$G7=""),"n/a",IF($G7>=$F7,"PASS","FAIL")) | R7: =IF($D7="","n/a",IF(AND(N($J7)>=$D7*R4_FLOOR,N($K7)>=$D7*R4_FLOOR,N($L7)>=$D7*R4_FLOOR),"PASS","FAIL")) | S7: =IF(COUNTIF($M7:$R7,"FAIL")>0,"BLOCKED",IF($D7="","HOLD - no cost","GO")) | T7: =IF($S7="GO","",IF($M7="FAIL","SKU format. ","")&IF($N7="FAIL","Duplicate SKU. ","")&IF($P7="FAIL","Landed cost is below ex-works - impossible. ","")&IF($Q7="FAIL","Retail is below the floor-binding minimum. ","")&IF($R7="FAIL","A published discount tier breaches the floor. ","")&IF($D7="","No cost recorded - cannot be gated or published. ",""))
A8: UC-HOU-ROS-001 | B8: =IFERROR(INDEX(LANDED_COST_BUILD!$B:$B,MATCH($A8,LANDED_COST_BUILD!$A:$A,0)),"") | C8: =IFERROR(INDEX(LANDED_COST_BUILD!$C:$C,MATCH($A8,LANDED_COST_BUILD!$A:$A,0)),"") | D8: =IFERROR(IF(INDEX(LANDED_COST_BUILD!$O:$O,MATCH($A8,LANDED_COST_BUILD!$A:$A,0))="","",INDEX(LANDED_COST_BUILD!$O:$O,MATCH($A8,LANDED_COST_BUILD!$A:$A,0))*FX_USD_KES),"") | E8: =IFERROR(LEFT(INDEX(LANDED_COST_BUILD!$P:$P,MATCH($A8,LANDED_COST_BUILD!$A:$A,0)),FIND(" ",INDEX(LANDED_COST_BUILD!$P:$P,MATCH($A8,LANDED_COST_BUILD!$A:$A,0))&" ")-1),"") | F8: =IF($D8="","",ROUNDUP($D8*R4_FLOOR/MIN_TIER_RATE,0)) | G8: =IFERROR(INDEX('SKU with PRICES'!$M:$M,MATCH($A8,'SKU with PRICES'!$H:$H,0)),"") | H8: =IF(OR($D8="",$G8=""),"",ROUND($G8/($D8*R4_FLOOR)-1,4)) | I8: =IF(OR($D8="",$G8=""),"",MAX(0,1-($D8*R4_FLOOR/$G8))) | J8: =IFERROR(INDEX('SKU with PRICES'!$O:$O,MATCH($A8,'SKU with PRICES'!$H:$H,0)),"") | K8: =IFERROR(INDEX('SKU with PRICES'!$Q:$Q,MATCH($A8,'SKU with PRICES'!$H:$H,0)),"") | L8: =IFERROR(INDEX('SKU with PRICES'!$S:$S,MATCH($A8,'SKU with PRICES'!$H:$H,0)),"") | M8: =IF(AND(LEFT($A8,3)="UC-",LEN($A8)>=13),"PASS","FAIL") | N8: =IF(COUNTIF($A$5:$A$99,$A8)=1,"PASS","FAIL") | O8: =IF($E8="NONE","FAIL",IF($E8="RECORDED","WARN","PASS")) | P8: =IFERROR(IF(INDEX(LANDED_COST_BUILD!$O:$O,MATCH($A8,LANDED_COST_BUILD!$A:$A,0))="","n/a",IF(INDEX(LANDED_COST_BUILD!$O:$O,MATCH($A8,LANDED_COST_BUILD!$A:$A,0))<INDEX(LANDED_COST_BUILD!$G:$G,MATCH($A8,LANDED_COST_BUILD!$A:$A,0)),"FAIL","PASS")),"n/a") | Q8: =IF(OR($F8="",$G8=""),"n/a",IF($G8>=$F8,"PASS","FAIL")) | R8: =IF($D8="","n/a",IF(AND(N($J8)>=$D8*R4_FLOOR,N($K8)>=$D8*R4_FLOOR,N($L8)>=$D8*R4_FLOOR),"PASS","FAIL")) | S8: =IF(COUNTIF($M8:$R8,"FAIL")>0,"BLOCKED",IF($D8="","HOLD - no cost","GO")) | T8: =IF($S8="GO","",IF($M8="FAIL","SKU format. ","")&IF($N8="FAIL","Duplicate SKU. ","")&IF($P8="FAIL","Landed cost is below ex-works - impossible. ","")&IF($Q8="FAIL","Retail is below the floor-binding minimum. ","")&IF($R8="FAIL","A published discount tier breaches the floor. ","")&IF($D8="","No cost recorded - cannot be gated or published. ",""))
A9: UC-COM-ROS-002 | B9: =IFERROR(INDEX(LANDED_COST_BUILD!$B:$B,MATCH($A9,LANDED_COST_BUILD!$A:$A,0)),"") | C9: =IFERROR(INDEX(LANDED_COST_BUILD!$C:$C,MATCH($A9,LANDED_COST_BUILD!$A:$A,0)),"") | D9: =IFERROR(IF(INDEX(LANDED_COST_BUILD!$O:$O,MATCH($A9,LANDED_COST_BUILD!$A:$A,0))="","",INDEX(LANDED_COST_BUILD!$O:$O,MATCH($A9,LANDED_COST_BUILD!$A:$A,0))*FX_USD_KES),"") | E9: =IFERROR(LEFT(INDEX(LANDED_COST_BUILD!$P:$P,MATCH($A9,LANDED_COST_BUILD!$A:$A,0)),FIND(" ",INDEX(LANDED_COST_BUILD!$P:$P,MATCH($A9,LANDED_COST_BUILD!$A:$A,0))&" ")-1),"") | F9: =IF($D9="","",ROUNDUP($D9*R4_FLOOR/MIN_TIER_RATE,0)) | G9: =IFERROR(INDEX('SKU with PRICES'!$M:$M,MATCH($A9,'SKU with PRICES'!$H:$H,0)),"") | H9: =IF(OR($D9="",$G9=""),"",ROUND($G9/($D9*R4_FLOOR)-1,4)) | I9: =IF(OR($D9="",$G9=""),"",MAX(0,1-($D9*R4_FLOOR/$G9))) | J9: =IFERROR(INDEX('SKU with PRICES'!$O:$O,MATCH($A9,'SKU with PRICES'!$H:$H,0)),"") | K9: =IFERROR(INDEX('SKU with PRICES'!$Q:$Q,MATCH($A9,'SKU with PRICES'!$H:$H,0)),"") | L9: =IFERROR(INDEX('SKU with PRICES'!$S:$S,MATCH($A9,'SKU with PRICES'!$H:$H,0)),"") | M9: =IF(AND(LEFT($A9,3)="UC-",LEN($A9)>=13),"PASS","FAIL") | N9: =IF(COUNTIF($A$5:$A$99,$A9)=1,"PASS","FAIL") | O9: =IF($E9="NONE","FAIL",IF($E9="RECORDED","WARN","PASS")) | P9: =IFERROR(IF(INDEX(LANDED_COST_BUILD!$O:$O,MATCH($A9,LANDED_COST_BUILD!$A:$A,0))="","n/a",IF(INDEX(LANDED_COST_BUILD!$O:$O,MATCH($A9,LANDED_COST_BUILD!$A:$A,0))<INDEX(LANDED_COST_BUILD!$G:$G,MATCH($A9,LANDED_COST_BUILD!$A:$A,0)),"FAIL","PASS")),"n/a") | Q9: =IF(OR($F9="",$G9=""),"n/a",IF($G9>=$F9,"PASS","FAIL")) | R9: =IF($D9="","n/a",IF(AND(N($J9)>=$D9*R4_FLOOR,N($K9)>=$D9*R4_FLOOR,N($L9)>=$D9*R4_FLOOR),"PASS","FAIL")) | S9: =IF(COUNTIF($M9:$R9,"FAIL")>0,"BLOCKED",IF($D9="","HOLD - no cost","GO")) | T9: =IF($S9="GO","",IF($M9="FAIL","SKU format. ","")&IF($N9="FAIL","Duplicate SKU. ","")&IF($P9="FAIL","Landed cost is below ex-works - impossible. ","")&IF($Q9="FAIL","Retail is below the floor-binding minimum. ","")&IF($R9="FAIL","A published discount tier breaches the floor. ","")&IF($D9="","No cost recorded - cannot be gated or published. ",""))
A10: UC-HOU-WPF-003 | B10: =IFERROR(INDEX(LANDED_COST_BUILD!$B:$B,MATCH($A10,LANDED_COST_BUILD!$A:$A,0)),"") | C10: =IFERROR(INDEX(LANDED_COST_BUILD!$C:$C,MATCH($A10,LANDED_COST_BUILD!$A:$A,0)),"") | D10: =IFERROR(IF(INDEX(LANDED_COST_BUILD!$O:$O,MATCH($A10,LANDED_COST_BUILD!$A:$A,0))="","",INDEX(LANDED_COST_BUILD!$O:$O,MATCH($A10,LANDED_COST_BUILD!$A:$A,0))*FX_USD_KES),"") | E10: =IFERROR(LEFT(INDEX(LANDED_COST_BUILD!$P:$P,MATCH($A10,LANDED_COST_BUILD!$A:$A,0)),FIND(" ",INDEX(LANDED_COST_BUILD!$P:$P,MATCH($A10,LANDED_COST_BUILD!$A:$A,0))&" ")-1),"") | F10: =IF($D10="","",ROUNDUP($D10*R4_FLOOR/MIN_TIER_RATE,0)) | G10: =IFERROR(INDEX('SKU with PRICES'!$M:$M,MATCH($A10,'SKU with PRICES'!$H:$H,0)),"") | H10: =IF(OR($D10="",$G10=""),"",ROUND($G10/($D10*R4_FLOOR)-1,4)) | I10: =IF(OR($D10="",$G10=""),"",MAX(0,1-($D10*R4_FLOOR/$G10))) | J10: =IFERROR(INDEX('SKU with PRICES'!$O:$O,MATCH($A10,'SKU with PRICES'!$H:$H,0)),"") | K10: =IFERROR(INDEX('SKU with PRICES'!$Q:$Q,MATCH($A10,'SKU with PRICES'!$H:$H,0)),"") | L10: =IFERROR(INDEX('SKU with PRICES'!$S:$S,MATCH($A10,'SKU with PRICES'!$H:$H,0)),"") | M10: =IF(AND(LEFT($A10,3)="UC-",LEN($A10)>=13),"PASS","FAIL") | N10: =IF(COUNTIF($A$5:$A$99,$A10)=1,"PASS","FAIL") | O10: =IF($E10="NONE","FAIL",IF($E10="RECORDED","WARN","PASS")) | P10: =IFERROR(IF(INDEX(LANDED_COST_BUILD!$O:$O,MATCH($A10,LANDED_COST_BUILD!$A:$A,0))="","n/a",IF(INDEX(LANDED_COST_BUILD!$O:$O,MATCH($A10,LANDED_COST_BUILD!$A:$A,0))<INDEX(LANDED_COST_BUILD!$G:$G,MATCH($A10,LANDED_COST_BUILD!$A:$A,0)),"FAIL","PASS")),"n/a") | Q10: =IF(OR($F10="",$G10=""),"n/a",IF($G10>=$F10,"PASS","FAIL")) | R10: =IF($D10="","n/a",IF(AND(N($J10)>=$D10*R4_FLOOR,N($K10)>=$D10*R4_FLOOR,N($L10)>=$D10*R4_FLOOR),"PASS","FAIL")) | S10: =IF(COUNTIF($M10:$R10,"FAIL")>0,"BLOCKED",IF($D10="","HOLD - no cost","GO")) | T10: =IF($S10="GO","",IF($M10="FAIL","SKU format. ","")&IF($N10="FAIL","Duplicate SKU. ","")&IF($P10="FAIL","Landed cost is below ex-works - impossible. ","")&IF($Q10="FAIL","Retail is below the floor-binding minimum. ","")&IF($R10="FAIL","A published discount tier breaches the floor. ","")&IF($D10="","No cost recorded - cannot be gated or published. ",""))
A11: UC-HOU-USF-004 | B11: =IFERROR(INDEX(LANDED_COST_BUILD!$B:$B,MATCH($A11,LANDED_COST_BUILD!$A:$A,0)),"") | C11: =IFERROR(INDEX(LANDED_COST_BUILD!$C:$C,MATCH($A11,LANDED_COST_BUILD!$A:$A,0)),"") | D11: =IFERROR(IF(INDEX(LANDED_COST_BUILD!$O:$O,MATCH($A11,LANDED_COST_BUILD!$A:$A,0))="","",INDEX(LANDED_COST_BUILD!$O:$O,MATCH($A11,LANDED_COST_BUILD!$A:$A,0))*FX_USD_KES),"") | E11: =IFERROR(LEFT(INDEX(LANDED_COST_BUILD!$P:$P,MATCH($A11,LANDED_COST_BUILD!$A:$A,0)),FIND(" ",INDEX(LANDED_COST_BUILD!$P:$P,MATCH($A11,LANDED_COST_BUILD!$A:$A,0))&" ")-1),"") | F11: =IF($D11="","",ROUNDUP($D11*R4_FLOOR/MIN_TIER_RATE,0)) | G11: =IFERROR(INDEX('SKU with PRICES'!$M:$M,MATCH($A11,'SKU with PRICES'!$H:$H,0)),"") | H11: =IF(OR($D11="",$G11=""),"",ROUND($G11/($D11*R4_FLOOR)-1,4)) | I11: =IF(OR($D11="",$G11=""),"",MAX(0,1-($D11*R4_FLOOR/$G11))) | J11: =IFERROR(INDEX('SKU with PRICES'!$O:$O,MATCH($A11,'SKU with PRICES'!$H:$H,0)),"") | K11: =IFERROR(INDEX('SKU with PRICES'!$Q:$Q,MATCH($A11,'SKU with PRICES'!$H:$H,0)),"") | L11: =IFERROR(INDEX('SKU with PRICES'!$S:$S,MATCH($A11,'SKU with PRICES'!$H:$H,0)),"") | M11: =IF(AND(LEFT($A11,3)="UC-",LEN($A11)>=13),"PASS","FAIL") | N11: =IF(COUNTIF($A$5:$A$99,$A11)=1,"PASS","FAIL") | O11: =IF($E11="NONE","FAIL",IF($E11="RECORDED","WARN","PASS")) | P11: =IFERROR(IF(INDEX(LANDED_COST_BUILD!$O:$O,MATCH($A11,LANDED_COST_BUILD!$A:$A,0))="","n/a",IF(INDEX(LANDED_COST_BUILD!$O:$O,MATCH($A11,LANDED_COST_BUILD!$A:$A,0))<INDEX(LANDED_COST_BUILD!$G:$G,MATCH($A11,LANDED_COST_BUILD!$A:$A,0)),"FAIL","PASS")),"n/a") | Q11: =IF(OR($F11="",$G11=""),"n/a",IF($G11>=$F11,"PASS","FAIL")) | R11: =IF($D11="","n/a",IF(AND(N($J11)>=$D11*R4_FLOOR,N($K11)>=$D11*R4_FLOOR,N($L11)>=$D11*R4_FLOOR),"PASS","FAIL")) | S11: =IF(COUNTIF($M11:$R11,"FAIL")>0,"BLOCKED",IF($D11="","HOLD - no cost","GO")) | T11: =IF($S11="GO","",IF($M11="FAIL","SKU format. ","")&IF($N11="FAIL","Duplicate SKU. ","")&IF($P11="FAIL","Landed cost is below ex-works - impossible. ","")&IF($Q11="FAIL","Retail is below the floor-binding minimum. ","")&IF($R11="FAIL","A published discount tier breaches the floor. ","")&IF($D11="","No cost recorded - cannot be gated or published. ",""))
A12: UC-HOU-TAP-005 | B12: =IFERROR(INDEX(LANDED_COST_BUILD!$B:$B,MATCH($A12,LANDED_COST_BUILD!$A:$A,0)),"") | C12: =IFERROR(INDEX(LANDED_COST_BUILD!$C:$C,MATCH($A12,LANDED_COST_BUILD!$A:$A,0)),"") | D12: =IFERROR(IF(INDEX(LANDED_COST_BUILD!$O:$O,MATCH($A12,LANDED_COST_BUILD!$A:$A,0))="","",INDEX(LANDED_COST_BUILD!$O:$O,MATCH($A12,LANDED_COST_BUILD!$A:$A,0))*FX_USD_KES),"") | E12: =IFERROR(LEFT(INDEX(LANDED_COST_BUILD!$P:$P,MATCH($A12,LANDED_COST_BUILD!$A:$A,0)),FIND(" ",INDEX(LANDED_COST_BUILD!$P:$P,MATCH($A12,LANDED_COST_BUILD!$A:$A,0))&" ")-1),"") | F12: =IF($D12="","",ROUNDUP($D12*R4_FLOOR/MIN_TIER_RATE,0)) | G12: =IFERROR(INDEX('SKU with PRICES'!$M:$M,MATCH($A12,'SKU with PRICES'!$H:$H,0)),"") | H12: =IF(OR($D12="",$G12=""),"",ROUND($G12/($D12*R4_FLOOR)-1,4)) | I12: =IF(OR($D12="",$G12=""),"",MAX(0,1-($D12*R4_FLOOR/$G12))) | J12: =IFERROR(INDEX('SKU with PRICES'!$O:$O,MATCH($A12,'SKU with PRICES'!$H:$H,0)),"") | K12: =IFERROR(INDEX('SKU with PRICES'!$Q:$Q,MATCH($A12,'SKU with PRICES'!$H:$H,0)),"") | L12: =IFERROR(INDEX('SKU with PRICES'!$S:$S,MATCH($A12,'SKU with PRICES'!$H:$H,0)),"") | M12: =IF(AND(LEFT($A12,3)="UC-",LEN($A12)>=13),"PASS","FAIL") | N12: =IF(COUNTIF($A$5:$A$99,$A12)=1,"PASS","FAIL") | O12: =IF($E12="NONE","FAIL",IF($E12="RECORDED","WARN","PASS")) | P12: =IFERROR(IF(INDEX(LANDED_COST_BUILD!$O:$O,MATCH($A12,LANDED_COST_BUILD!$A:$A,0))="","n/a",IF(INDEX(LANDED_COST_BUILD!$O:$O,MATCH($A12,LANDED_COST_BUILD!$A:$A,0))<INDEX(LANDED_COST_BUILD!$G:$G,MATCH($A12,LANDED_COST_BUILD!$A:$A,0)),"FAIL","PASS")),"n/a") | Q12: =IF(OR($F12="",$G12=""),"n/a",IF($G12>=$F12,"PASS","FAIL")) | R12: =IF($D12="","n/a",IF(AND(N($J12)>=$D12*R4_FLOOR,N($K12)>=$D12*R4_FLOOR,N($L12)>=$D12*R4_FLOOR),"PASS","FAIL")) | S12: =IF(COUNTIF($M12:$R12,"FAIL")>0,"BLOCKED",IF($D12="","HOLD - no cost","GO")) | T12: =IF($S12="GO","",IF($M12="FAIL","SKU format. ","")&IF($N12="FAIL","Duplicate SKU. ","")&IF($P12="FAIL","Landed cost is below ex-works - impossible. ","")&IF($Q12="FAIL","Retail is below the floor-binding minimum. ","")&IF($R12="FAIL","A published discount tier breaches the floor. ","")&IF($D12="","No cost recorded - cannot be gated or published. ",""))
A13: UC-HOU-TAPF-006 | B13: =IFERROR(INDEX(LANDED_COST_BUILD!$B:$B,MATCH($A13,LANDED_COST_BUILD!$A:$A,0)),"") | C13: =IFERROR(INDEX(LANDED_COST_BUILD!$C:$C,MATCH($A13,LANDED_COST_BUILD!$A:$A,0)),"") | D13: =IFERROR(IF(INDEX(LANDED_COST_BUILD!$O:$O,MATCH($A13,LANDED_COST_BUILD!$A:$A,0))="","",INDEX(LANDED_COST_BUILD!$O:$O,MATCH($A13,LANDED_COST_BUILD!$A:$A,0))*FX_USD_KES),"") | E13: =IFERROR(LEFT(INDEX(LANDED_COST_BUILD!$P:$P,MATCH($A13,LANDED_COST_BUILD!$A:$A,0)),FIND(" ",INDEX(LANDED_COST_BUILD!$P:$P,MATCH($A13,LANDED_COST_BUILD!$A:$A,0))&" ")-1),"") | F13: =IF($D13="","",ROUNDUP($D13*R4_FLOOR/MIN_TIER_RATE,0)) | G13: =IFERROR(INDEX('SKU with PRICES'!$M:$M,MATCH($A13,'SKU with PRICES'!$H:$H,0)),"") | H13: =IF(OR($D13="",$G13=""),"",ROUND($G13/($D13*R4_FLOOR)-1,4)) | I13: =IF(OR($D13="",$G13=""),"",MAX(0,1-($D13*R4_FLOOR/$G13))) | J13: =IFERROR(INDEX('SKU with PRICES'!$O:$O,MATCH($A13,'SKU with PRICES'!$H:$H,0)),"") | K13: =IFERROR(INDEX('SKU with PRICES'!$Q:$Q,MATCH($A13,'SKU with PRICES'!$H:$H,0)),"") | L13: =IFERROR(INDEX('SKU with PRICES'!$S:$S,MATCH($A13,'SKU with PRICES'!$H:$H,0)),"") | M13: =IF(AND(LEFT($A13,3)="UC-",LEN($A13)>=13),"PASS","FAIL") | N13: =IF(COUNTIF($A$5:$A$99,$A13)=1,"PASS","FAIL") | O13: =IF($E13="NONE","FAIL",IF($E13="RECORDED","WARN","PASS")) | P13: =IFERROR(IF(INDEX(LANDED_COST_BUILD!$O:$O,MATCH($A13,LANDED_COST_BUILD!$A:$A,0))="","n/a",IF(INDEX(LANDED_COST_BUILD!$O:$O,MATCH($A13,LANDED_COST_BUILD!$A:$A,0))<INDEX(LANDED_COST_BUILD!$G:$G,MATCH($A13,LANDED_COST_BUILD!$A:$A,0)),"FAIL","PASS")),"n/a") | Q13: =IF(OR($F13="",$G13=""),"n/a",IF($G13>=$F13,"PASS","FAIL")) | R13: =IF($D13="","n/a",IF(AND(N($J13)>=$D13*R4_FLOOR,N($K13)>=$D13*R4_FLOOR,N($L13)>=$D13*R4_FLOOR),"PASS","FAIL")) | S13: =IF(COUNTIF($M13:$R13,"FAIL")>0,"BLOCKED",IF($D13="","HOLD - no cost","GO")) | T13: =IF($S13="GO","",IF($M13="FAIL","SKU format. ","")&IF($N13="FAIL","Duplicate SKU. ","")&IF($P13="FAIL","Landed cost is below ex-works - impossible. ","")&IF($Q13="FAIL","Retail is below the floor-binding minimum. ","")&IF($R13="FAIL","A published discount tier breaches the floor. ","")&IF($D13="","No cost recorded - cannot be gated or published. ",""))
A14: UC-HOU-WDFS-006 | B14: =IFERROR(INDEX(LANDED_COST_BUILD!$B:$B,MATCH($A14,LANDED_COST_BUILD!$A:$A,0)),"") | C14: =IFERROR(INDEX(LANDED_COST_BUILD!$C:$C,MATCH($A14,LANDED_COST_BUILD!$A:$A,0)),"") | D14: =IFERROR(IF(INDEX(LANDED_COST_BUILD!$O:$O,MATCH($A14,LANDED_COST_BUILD!$A:$A,0))="","",INDEX(LANDED_COST_BUILD!$O:$O,MATCH($A14,LANDED_COST_BUILD!$A:$A,0))*FX_USD_KES),"") | E14: =IFERROR(LEFT(INDEX(LANDED_COST_BUILD!$P:$P,MATCH($A14,LANDED_COST_BUILD!$A:$A,0)),FIND(" ",INDEX(LANDED_COST_BUILD!$P:$P,MATCH($A14,LANDED_COST_BUILD!$A:$A,0))&" ")-1),"") | F14: =IF($D14="","",ROUNDUP($D14*R4_FLOOR/MIN_TIER_RATE,0)) | G14: =IFERROR(INDEX('SKU with PRICES'!$M:$M,MATCH($A14,'SKU with PRICES'!$H:$H,0)),"") | H14: =IF(OR($D14="",$G14=""),"",ROUND($G14/($D14*R4_FLOOR)-1,4)) | I14: =IF(OR($D14="",$G14=""),"",MAX(0,1-($D14*R4_FLOOR/$G14))) | J14: =IFERROR(INDEX('SKU with PRICES'!$O:$O,MATCH($A14,'SKU with PRICES'!$H:$H,0)),"") | K14: =IFERROR(INDEX('SKU with PRICES'!$Q:$Q,MATCH($A14,'SKU with PRICES'!$H:$H,0)),"") | L14: =IFERROR(INDEX('SKU with PRICES'!$S:$S,MATCH($A14,'SKU with PRICES'!$H:$H,0)),"") | M14: =IF(AND(LEFT($A14,3)="UC-",LEN($A14)>=13),"PASS","FAIL") | N14: =IF(COUNTIF($A$5:$A$99,$A14)=1,"PASS","FAIL") | O14: =IF($E14="NONE","FAIL",IF($E14="RECORDED","WARN","PASS")) | P14: =IFERROR(IF(INDEX(LANDED_COST_BUILD!$O:$O,MATCH($A14,LANDED_COST_BUILD!$A:$A,0))="","n/a",IF(INDEX(LANDED_COST_BUILD!$O:$O,MATCH($A14,LANDED_COST_BUILD!$A:$A,0))<INDEX(LANDED_COST_BUILD!$G:$G,MATCH($A14,LANDED_COST_BUILD!$A:$A,0)),"FAIL","PASS")),"n/a") | Q14: =IF(OR($F14="",$G14=""),"n/a",IF($G14>=$F14,"PASS","FAIL")) | R14: =IF($D14="","n/a",IF(AND(N($J14)>=$D14*R4_FLOOR,N($K14)>=$D14*R4_FLOOR,N($L14)>=$D14*R4_FLOOR),"PASS","FAIL")) | S14: =IF(COUNTIF($M14:$R14,"FAIL")>0,"BLOCKED",IF($D14="","HOLD - no cost","GO")) | T14: =IF($S14="GO","",IF($M14="FAIL","SKU format. ","")&IF($N14="FAIL","Duplicate SKU. ","")&IF($P14="FAIL","Landed cost is below ex-works - impossible. ","")&IF($Q14="FAIL","Retail is below the floor-binding minimum. ","")&IF($R14="FAIL","A published discount tier breaches the floor. ","")&IF($D14="","No cost recorded - cannot be gated or published. ",""))
A15: UC-HOU-DF-007 | B15: =IFERROR(INDEX(LANDED_COST_BUILD!$B:$B,MATCH($A15,LANDED_COST_BUILD!$A:$A,0)),"") | C15: =IFERROR(INDEX(LANDED_COST_BUILD!$C:$C,MATCH($A15,LANDED_COST_BUILD!$A:$A,0)),"") | D15: =IFERROR(IF(INDEX(LANDED_COST_BUILD!$O:$O,MATCH($A15,LANDED_COST_BUILD!$A:$A,0))="","",INDEX(LANDED_COST_BUILD!$O:$O,MATCH($A15,LANDED_COST_BUILD!$A:$A,0))*FX_USD_KES),"") | E15: =IFERROR(LEFT(INDEX(LANDED_COST_BUILD!$P:$P,MATCH($A15,LANDED_COST_BUILD!$A:$A,0)),FIND(" ",INDEX(LANDED_COST_BUILD!$P:$P,MATCH($A15,LANDED_COST_BUILD!$A:$A,0))&" ")-1),"") | F15: =IF($D15="","",ROUNDUP($D15*R4_FLOOR/MIN_TIER_RATE,0)) | G15: =IFERROR(INDEX('SKU with PRICES'!$M:$M,MATCH($A15,'SKU with PRICES'!$H:$H,0)),"") | H15: =IF(OR($D15="",$G15=""),"",ROUND($G15/($D15*R4_FLOOR)-1,4)) | I15: =IF(OR($D15="",$G15=""),"",MAX(0,1-($D15*R4_FLOOR/$G15))) | J15: =IFERROR(INDEX('SKU with PRICES'!$O:$O,MATCH($A15,'SKU with PRICES'!$H:$H,0)),"") | K15: =IFERROR(INDEX('SKU with PRICES'!$Q:$Q,MATCH($A15,'SKU with PRICES'!$H:$H,0)),"") | L15: =IFERROR(INDEX('SKU with PRICES'!$S:$S,MATCH($A15,'SKU with PRICES'!$H:$H,0)),"") | M15: =IF(AND(LEFT($A15,3)="UC-",LEN($A15)>=13),"PASS","FAIL") | N15: =IF(COUNTIF($A$5:$A$99,$A15)=1,"PASS","FAIL") | O15: =IF($E15="NONE","FAIL",IF($E15="RECORDED","WARN","PASS")) | P15: =IFERROR(IF(INDEX(LANDED_COST_BUILD!$O:$O,MATCH($A15,LANDED_COST_BUILD!$A:$A,0))="","n/a",IF(INDEX(LANDED_COST_BUILD!$O:$O,MATCH($A15,LANDED_COST_BUILD!$A:$A,0))<INDEX(LANDED_COST_BUILD!$G:$G,MATCH($A15,LANDED_COST_BUILD!$A:$A,0)),"FAIL","PASS")),"n/a") | Q15: =IF(OR($F15="",$G15=""),"n/a",IF($G15>=$F15,"PASS","FAIL")) | R15: =IF($D15="","n/a",IF(AND(N($J15)>=$D15*R4_FLOOR,N($K15)>=$D15*R4_FLOOR,N($L15)>=$D15*R4_FLOOR),"PASS","FAIL")) | S15: =IF(COUNTIF($M15:$R15,"FAIL")>0,"BLOCKED",IF($D15="","HOLD - no cost","GO")) | T15: =IF($S15="GO","",IF($M15="FAIL","SKU format. ","")&IF($N15="FAIL","Duplicate SKU. ","")&IF($P15="FAIL","Landed cost is below ex-works - impossible. ","")&IF($Q15="FAIL","Retail is below the floor-binding minimum. ","")&IF($R15="FAIL","A published discount tier breaches the floor. ","")&IF($D15="","No cost recorded - cannot be gated or published. ",""))
A16: UC-BOG-SSB-008 | B16: =IFERROR(INDEX(LANDED_COST_BUILD!$B:$B,MATCH($A16,LANDED_COST_BUILD!$A:$A,0)),"") | C16: =IFERROR(INDEX(LANDED_COST_BUILD!$C:$C,MATCH($A16,LANDED_COST_BUILD!$A:$A,0)),"") | D16: =IFERROR(IF(INDEX(LANDED_COST_BUILD!$O:$O,MATCH($A16,LANDED_COST_BUILD!$A:$A,0))="","",INDEX(LANDED_COST_BUILD!$O:$O,MATCH($A16,LANDED_COST_BUILD!$A:$A,0))*FX_USD_KES),"") | E16: =IFERROR(LEFT(INDEX(LANDED_COST_BUILD!$P:$P,MATCH($A16,LANDED_COST_BUILD!$A:$A,0)),FIND(" ",INDEX(LANDED_COST_BUILD!$P:$P,MATCH($A16,LANDED_COST_BUILD!$A:$A,0))&" ")-1),"") | F16: =IF($D16="","",ROUNDUP($D16*R4_FLOOR/MIN_TIER_RATE,0)) | G16: =IFERROR(INDEX('SKU with PRICES'!$M:$M,MATCH($A16,'SKU with PRICES'!$H:$H,0)),"") | H16: =IF(OR($D16="",$G16=""),"",ROUND($G16/($D16*R4_FLOOR)-1,4)) | I16: =IF(OR($D16="",$G16=""),"",MAX(0,1-($D16*R4_FLOOR/$G16))) | J16: =IFERROR(INDEX('SKU with PRICES'!$O:$O,MATCH($A16,'SKU with PRICES'!$H:$H,0)),"") | K16: =IFERROR(INDEX('SKU with PRICES'!$Q:$Q,MATCH($A16,'SKU with PRICES'!$H:$H,0)),"") | L16: =IFERROR(INDEX('SKU with PRICES'!$S:$S,MATCH($A16,'SKU with PRICES'!$H:$H,0)),"") | M16: =IF(AND(LEFT($A16,3)="UC-",LEN($A16)>=13),"PASS","FAIL") | N16: =IF(COUNTIF($A$5:$A$99,$A16)=1,"PASS","FAIL") | O16: =IF($E16="NONE","FAIL",IF($E16="RECORDED","WARN","PASS")) | P16: =IFERROR(IF(INDEX(LANDED_COST_BUILD!$O:$O,MATCH($A16,LANDED_COST_BUILD!$A:$A,0))="","n/a",IF(INDEX(LANDED_COST_BUILD!$O:$O,MATCH($A16,LANDED_COST_BUILD!$A:$A,0))<INDEX(LANDED_COST_BUILD!$G:$G,MATCH($A16,LANDED_COST_BUILD!$A:$A,0)),"FAIL","PASS")),"n/a") | Q16: =IF(OR($F16="",$G16=""),"n/a",IF($G16>=$F16,"PASS","FAIL")) | R16: =IF($D16="","n/a",IF(AND(N($J16)>=$D16*R4_FLOOR,N($K16)>=$D16*R4_FLOOR,N($L16)>=$D16*R4_FLOOR),"PASS","FAIL")) | S16: =IF(COUNTIF($M16:$R16,"FAIL")>0,"BLOCKED",IF($D16="","HOLD - no cost","GO")) | T16: =IF($S16="GO","",IF($M16="FAIL","SKU format. ","")&IF($N16="FAIL","Duplicate SKU. ","")&IF($P16="FAIL","Landed cost is below ex-works - impossible. ","")&IF($Q16="FAIL","Retail is below the floor-binding minimum. ","")&IF($R16="FAIL","A published discount tier breaches the floor. ","")&IF($D16="","No cost recorded - cannot be gated or published. ",""))
... A44: UC-HOU-ROT-029 | B44: =IFERROR(INDEX(LANDED_COST_BUILD!$B:$B,MATCH($A44,LANDED_COST_BUILD!$A:$A,0)),"") | C44: =IFERROR(INDEX(LANDED_COST_BUILD!$C:$C,MATCH($A44,LANDED_COST_BUILD!$A:$A,0)),"") | D44: =IFERROR(IF(INDEX(LANDED_COST_BUILD!$O:$O,MATCH($A44,LANDED_COST_BUILD!$A:$A,0))="","",INDEX(LANDED_COST_BUILD!$O:$O,MATCH($A44,LANDED_COST_BUILD!$A:$A,0))*FX_USD_KES),"") | E44: =IFERROR(LEFT(INDEX(LANDED_COST_BUILD!$P:$P,MATCH($A44,LANDED_COST_BUILD!$A:$A,0)),FIND(" ",INDEX(LANDED_COST_BUILD!$P:$P,MATCH($A44,LANDED_COST_BUILD!$A:$A,0))&" ")-1),"") | F44: =IF($D44="","",ROUNDUP($D44*R4_FLOOR/MIN_TIER_RATE,0)) | G44: =IFERROR(INDEX('SKU with PRICES'!$M:$M,MATCH($A44,'SKU with PRICES'!$H:$H,0)),"") | H44: =IF(OR($D44="",$G44=""),"",ROUND($G44/($D44*R4_FLOOR)-1,4)) | I44: =IF(OR($D44="",$G44=""),"",MAX(0,1-($D44*R4_FLOOR/$G44))) | J44: =IFERROR(INDEX('SKU with PRICES'!$O:$O,MATCH($A44,'SKU with PRICES'!$H:$H,0)),"") | K44: =IFERROR(INDEX('SKU with PRICES'!$Q:$Q,MATCH($A44,'SKU with PRICES'!$H:$H,0)),"") | L44: =IFERROR(INDEX('SKU with PRICES'!$S:$S,MATCH($A44,'SKU with PRICES'!$H:$H,0)),"") | M44: =IF(AND(LEFT($A44,3)="UC-",LEN($A44)>=13),"PASS","FAIL") | N44: =IF(COUNTIF($A$5:$A$99,$A44)=1,"PASS","FAIL") | O44: =IF($E44="NONE","FAIL",IF($E44="RECORDED","WARN","PASS")) | P44: =IFERROR(IF(INDEX(LANDED_COST_BUILD!$O:$O,MATCH($A44,LANDED_COST_BUILD!$A:$A,0))="","n/a",IF(INDEX(LANDED_COST_BUILD!$O:$O,MATCH($A44,LANDED_COST_BUILD!$A:$A,0))<INDEX(LANDED_COST_BUILD!$G:$G,MATCH($A44,LANDED_COST_BUILD!$A:$A,0)),"FAIL","PASS")),"n/a") | Q44: =IF(OR($F44="",$G44=""),"n/a",IF($G44>=$F44,"PASS","FAIL")) | R44: =IF($D44="","n/a",IF(AND(N($J44)>=$D44*R4_FLOOR,N($K44)>=$D44*R4_FLOOR,N($L44)>=$D44*R4_FLOOR),"PASS","FAIL")) | S44: =IF(COUNTIF($M44:$R44,"FAIL")>0,"BLOCKED",IF($D44="","HOLD - no cost","GO")) | T44: =IF($S44="GO","",IF($M44="FAIL","SKU format. ","")&IF($N44="FAIL","Duplicate SKU. ","")&IF($P44="FAIL","Landed cost is below ex-works - impossible. ","")&IF($Q44="FAIL","Retail is below the floor-binding minimum. ","")&IF($R44="FAIL","A published discount tier breaches the floor. ","")&IF($D44="","No cost recorded - cannot be gated or published. ",""))
A46: SUMMARY
A47: GO | B47: =COUNTIF($S$5:$S$44,"GO")
A48: BLOCKED | B48: =COUNTIF($S$5:$S$44,"BLOCKED")
A49: HOLD - no cost | B49: =COUNTIF($S$5:$S$44,"HOLD - no cost")

Sheet PL 
A1: Guangzhou Begreat Smart Life Co., Ltd.
A2: Room 2104, No. 3 Jinhuan Street, Nansha Street, Nansha District, Guangzhou, Guangdong, China.
A3: Contact: Jack Tel: +86 136 8221 8884 E-mail: jack@begreat001.com
A4: Packing List
A5: Buyer | B5: J&I ULTRAL SUPPLIES Jerry Royce C/o Nii Ashe Bruce #49 THB Estate . Kijitonyama,Dar es Salam,Tanzania (+255) 746635555,0686791479 Sales@ucfilters.com
B6: Model | C6: Modeel Sku | D6: Total Q'ty(pcs) | E6: N.W/Ctn (Kgs) | F6: G.W/Ctn (Kgs) | G6: Q'ty/Ctn (pcs) | H6: Carton Dimension (CM) | K6: Total Cartons | L6: Total G.W. (Kgs) | M6: Total CBM
A7: 1 | B7: 740ml stainless steel water filter bottle BG-B01 | C7: UC-BOG-SSB-008 | D7: 84 | E7: 10.6 | F7: 11.5 | G7: 21 | H7: 53.5 | I7: 46 | J7: 30.5 | K7: 4 | L7: =F7*K7 | M7: =H7*I7*J7*K7/1000000
A8: 2 | B8: 769ml tritan water filter bottle BG-B02 | C8: UC-BOG-TRB-009 | D8: 90 | E8: 9.1 | F8: 10 | G8: 30 | H8: 53.5 | I8: 46 | J8: 30.5 | K8: 3 | L8: =F8*K8 | M8: =H8*I8*J8*K8/1000000
D9: 60 | E9: 6.1 | F9: 7 | G9: 20 | H9: 54.5 | I9: 44 | J9: 31 | K9: 3 | L9: =F9*K9 | M9: =H9*I9*J9*K9/1000000
A10: 3 | B10: 500ml tritan water filter bottle(black) BG-B06 | C10: UC-BOG-TRB-010 | D10: 84 | E10: 10.3 | F10: 11.3 | G10: 42 | H10: 51.5 | I10: 57.5 | J10: 25 | K10: 2 | L10: =F10*K10 | M10: =H10*I10*J10*K10/1000000
D11: 6 | E11: 1.4 | F11: 2 | G11: 6 | H11: 36 | I11: 36 | J11: 17 | K11: 1 | L11: =F11*K11 | M11: =H11*I11*J11*K11/1000000
D12: 60 | E12: 7.4 | F12: 8.4 | G12: 30 | H12: 50 | I12: 42.5 | J12: 24.5 | K12: 2 | L12: =F12*K12 | M12: =H12*I12*J12*K12/1000000
A13: 4 | B13: 1000ml tritan water filter bottle BG-B09 | C13: UC-BOG-TRB-011 | D13: 100 | E13: 16.8 | F13: 17.8 | G13: 50 | H13: 50 | I13: 42.5 | J13: 24.5 | K13: 2 | L13: =F13*K13 | M13: =H13*I13*J13*K13/1000000
D14: 20 | E14: 3.4 | F14: 4 | G14: 10 | H14: 55 | I14: 23.5 | J14: 37.5 | K14: 2 | L14: =F14*K14 | M14: =H14*I14*J14*K14/1000000
A15: 5 | B15: 350ml collapsible water filter bottle BG-B04 | C15: UC-BOG-FLB-012 | D15: 40 | E15: 10.3 | F15: 11.3 | G15: 40 | H15: 57 | I15: 39.5 | J15: 29.5 | K15: 1 | L15: =F15*K15 | M15: =H15*I15*J15*K15/1000000
A16: 6 | B16: 1000ml squeeze water filter bottle BG-B07 | C16: UC-BOG-SQB-014 | D16: 72 | E16: 10.2 | F16: 11.2 | G16: 36 | H16: 57.5 | I16: 57.5 | J16: 44.5 | K16: 2 | L16: =F16*K16 | M16: =H16*I16*J16*K16/1000000
D17: 28 | E17: 4.1 | F17: 5.1 | G17: 14 | H17: 54 | I17: 45.5 | J17: 31 | K17: 2 | L17: =F17*K17 | M17: =H17*I17*J17*K17/1000000
A18: 7 | B18: straw bottle's filters+squeeze bottle's actived fiber filter BG-F06A | C18: UC-BOG-FCA-015 | D18: 360 | E18: 2.6 | F18: 3 | G18: 120 | H18: 29 | I18: 32 | J18: 14 | K18: 3 | L18: =F18*K18 | M18: =H18*I18*J18*K18/1000000
C19: UC-BOG-FCA-015 | D19: 100 | E19: 2.2 | F19: 2.5 | G19: 100 | H19: 29 | I19: 32 | J19: 14 | K19: 1 | L19: =F19*K19 | M19: =H19*I19*J19*K19/1000000
A20: 8 | B20: 740ml stainless steel water filter bottle' s straw only NIL | C20: UC-BOG-SHL-018 | D20: 50 | E20: 1.5 | F20: 1.7 | G20: 50 | H20: 36.5 | I20: 20 | J20: 19 | K20: 1 | L20: =F20*K20 | M20: =H20*I20*J20*K20/1000000
A21: 9 | B21: pump filter cartridge BG-F04A | C21: UC-HOU-WDFS-006 | D21: 120 | E21: 9.3 | F21: 10.3 | G21: 60 | H21: 50.5 | I21: 41.5 | J21: 26 | K21: 2 | L21: =F21*K21 | M21: =H21*I21*J21*K21/1000000
D22: 80 | E22: 6 | F22: 7 | G22: 40 | H22: 42 | I22: 41 | J22: 25 | K22: 2 | L22: =F22*K22 | M22: =H22*I22*J22*K22/1000000
A23: 10 | B23: ultra filter faucet BG-T01U | C23: UC-HOU-TAP-005 | D23: 180 | E23: 14.5 | F23: 15.5 | G23: 30 | H23: 42.5 | I23: 38 | J23: 39.5 | K23: 6 | L23: =F23*K23 | M23: =H23*I23*J23*K23/1000000
D24: 20 | E24: 9.5 | F24: 10.5 | G24: 20 | H24: 42.5 | I24: 38 | J24: 39.5 | K24: 1 | L24: =F24*K24 | M24: =H24*I24*J24*K24/1000000
A25: 11 | B25: faucet filter cartridge BG-F01U | C25: UC-HOU-TAPF-006 | D25: 120 | E25: 7 | F25: 7.6 | G25: 120 | H25: 48.5 | I25: 30.5 | J25: 20 | K25: 1 | L25: =F25*K25 | M25: =H25*I25*J25*K25/1000000
A26: 12 | B26: diamond shower filter BG-S01 | C26: UC-SKW-SHF-020 | D26: 60 | E26: 10 | F26: 11 | G26: 30 | H26: 49.5 | I26: 43 | J26: 24.5 | K26: 2 | L26: =F26*K26 | M26: =H26*I26*J26*K26/1000000
A27: 13 | B27: round shower filter BG-S02 | C27: UC-SKW-SHF-019 | D27: 90 | E27: 12 | F27: 12.5 | G27: 30 | H27: 45.5 | I27: 42 | J27: 24 | K27: 3 | L27: =F27*K27 | M27: =H27*I27*J27*K27/1000000
A28: 14 | B28: shower filter with window BG-S04 | C28: UC-SKW-SHF-022 | D28: 20 | E28: 4.3 | F28: 4.8 | G28: 20 | H28: 37 | I28: 28 | J28: 31.5 | K28: 1 | L28: =F28*K28 | M28: =H28*I28*J28*K28/1000000
A29: 15 | B29: aluminum alloy shower filter BG-S06 | C29: UC-SKW-SHF-021 | D29: 120 | E29: 15.1 | F29: 15.8 | G29: 30 | H29: 49.5 | I29: 40.5 | J29: 26 | K29: 4 | L29: =F29*K29 | M29: =H29*I29*J29*K29/1000000
A30: 16 | B30: shower filter cartridge BG-F02 | C30: UC-SKW-SHC-023 | D30: 120 | E30: 16.9 | F30: 17.5 | G30: 120 | H30: 54.5 | I30: 23 | J30: 37 | K30: 1 | L30: =F30*K30 | M30: =H30*I30*J30*K30/1000000
A31: 17 | B31: new straw filter BG-B12 | C31: UC-BOG-FST-016 | D31: 50 | E31: 6 | F31: 7 | G31: 50 | H31: 48 | I31: 33 | J31: 23.5 | K31: 1 | L31: =F31*K31 | M31: =H31*I31*J31*K31/1000000
D33: =SUM(D7:D31) | K33: =SUM(K7:K31) | L33: =SUM(L7:L31) | M33: =SUM(M7:M31)

Sheet FIX_LOG
A1: SKU Prices — formula repair log
A2: Source: D:\Users\OneDrive\WEB\OFFICIAL DOCUMENTS\...\SKU with Prices\SKU Prices.xlsx
A3: Repaired 16 Sep 2026. Errors before: 24 x #VALUE! + 22 x #DIV/0! = 46. Errors after: 0.
A5: PHASE | B5: CELL / OBJECT | C5: WAS | D5: NOW | E5: WHY IT WAS WRONG
A6: P1 | B6: Y11 | C6: '1.6' | D6: 1.6 | E6: multiplier stored as TEXT; coerces in * but fails in lookups/array maths
A7: P1 | B7: Z11 | C7: '1.45' | D7: 1.45 | E7: multiplier stored as TEXT; coerces in * but fails in lookups/array maths
A8: P2 | B8: FX_USD_KES | C8: -> | D8: 'SKU with PRICES'!$W$8 | E8: named anchor added (cannot drift on row insert/delete)
A9: P2 | B9: MULT_RETAIL_CORE | C9: -> | D9: 'SKU with PRICES'!$Y$11 | E9: named anchor added (cannot drift on row insert/delete)
A10: P2 | B10: RATE_WHOLESALE | C10: -> | D10: 'SKU with PRICES'!$Y$12 | E10: named anchor added (cannot drift on row insert/delete)
A11: P2 | B11: RATE_CORPORATE | C11: -> | D11: 'SKU with PRICES'!$Y$13 | E11: named anchor added (cannot drift on row insert/delete)
A12: P2 | B12: RATE_INFLUENCER | C12: -> | D12: 'SKU with PRICES'!$Y$14 | E12: named anchor added (cannot drift on row insert/delete)
A13: P2 | B13: MULT_RETAIL_CONS | C13: -> | D13: 'SKU with PRICES'!$Z$11 | E13: named anchor added (cannot drift on row insert/delete)
A14: P2 | B14: RATE_WHOLESALE_CONS | C14: -> | D14: 'SKU with PRICES'!$Z$12 | E14: named anchor added (cannot drift on row insert/delete)
A15: P2 | B15: RATE_CORPORATE_CONS | C15: -> | D15: 'SKU with PRICES'!$Z$13 | E15: named anchor added (cannot drift on row insert/delete)
A16: P2 | B16: RATE_INFLUENCER_CONS | C16: -> | D16: 'SKU with PRICES'!$Z$14 | E16: named anchor added (cannot drift on row insert/delete)
... A376: P3 | B376: T41 | C376: $W$6 | D376: -> named anchors | E376: formula reference drift
A377: P3 | B377: TOTAL | E377: 440 data-row formulas rewritten from one canonical template
A378: P4 | B378: Table1 column template [Cost_KES] | C378: $W$6 | D378: -> named anchors | E378: master template was broken: every NEW row inherited it
A379: P4 | B379: Table1 column template [Retail_KES] | C379: $Y$9 | D379: -> named anchors | E379: master template was broken: every NEW row inherited it
A380: P4 | B380: Table1 column template [Pychological Pricing] | C380: (none) | D380: -> named anchors | E380: master template was broken: every NEW row inherited it
A381: P4 | B381: Table1 column template [Retail_USD] | C381: /135 | D381: -> named anchors | E381: master template was broken: every NEW row inherited it
A382: P4 | B382: Table1 column template [Wholesale_KES] | C382: $Y$10 | D382: -> named anchors | E382: master template was broken: every NEW row inherited it
A383: P4 | B383: Table1 column template [Wholesale_USD] | C383: $W$6 | D383: -> named anchors | E383: master template was broken: every NEW row inherited it
A384: P4 | B384: Table1 column template [Corporate_KES] | C384: $Y$11 | D384: -> named anchors | E384: master template was broken: every NEW row inherited it
A385: P4 | B385: Table1 column template [Corporate_USD] | C385: $W$6 | D385: -> named anchors | E385: master template was broken: every NEW row inherited it
A386: P4 | B386: Table1 column template [Influencer_KES] | C386: $Y$12 | D386: -> named anchors | E386: master template was broken: every NEW row inherited it
A387: P4 | B387: Table1 column template [Influencer_USD] | C387: $W$6 | D387: -> named anchors | E387: master template was broken: every NEW row inherited it
A388: P4 | B388: Table1 column template [REVENUE] | C388: (none) | D388: -> named anchors | E388: master template was broken: every NEW row inherited it
A389: P5 | B389: Table1.ref | C389: A1:V42 | D389: A1:V41 | E389: "Total" was a DATA ROW inside the product table and was being priced as if it were a product
A390: P5 | B390: I42 | C390: =SUM(I2:I40) | D390: =SUM(I2:I41) | E390: production-cost total omitted row 41
A391: P5 | B391: J42 | C391: =SUM(J2:J34) | D391: =SUM(J2:J41) | E391: landing-cost total omitted rows 35-41 (7 SKUs)

Sheet ROOT_CAUSE
A1: Root cause: the parameter block sits 2 rows BELOW where every pricing formula points
A2: One defect, two symptoms: cells that point at an EMPTY cell throw an error (loud); cells that point at the WRONG LIVE NUMBER return a plausible but wrong price (silent). The silent half is the expensive half.
A4: No. | B4: FORMULA POINTED AT | C4: THAT CELL HELD | D4: SHOULD BE | E4: WHICH HOLDS | F4: RESULT
A5: 1 | B5: $W$6 (forex) | C5: (empty) | D5: $W$8 | E5: 135 | F5: DIV/0 error in Wholesale_USD / Corporate_USD / Influencer_USD - 22 cells
A6: 2 | B6: $Y$9 (retail multiplier) | C6: (empty) | D6: $Y$11 | E6: 1.6 | F6: Retail_KES = 0 on rows 20, 32, 33
A7: 3 | B7: $Y$10 (wholesale rate) | C7: "Core Product Discounts" (text) | D7: $Y$12 | E7: 0.8 | F7: VALUE error in Wholesale_KES / Wholesale_USD - 24 cells
A8: 4 | B8: $Y$11 (used as CORPORATE rate) | C8: 1.6 — the RETAIL multiplier | D8: $Y$13 | E8: 0.85 | F8: SILENT: corporate price = retail x 1.6, i.e. 60-64% ABOVE retail. 8 SKUs.
A9: 5 | B9: $Y$12 (used as INFLUENCER rate) | C9: 0.8 — the WHOLESALE rate | D9: $Y$14 | E9: 0.9 | F9: SILENT: influencer discounted 20% instead of 10%. 8 SKUs.
A10: 6 | B10: /135 hard-typed in Retail_USD | C10: literal | D10: FX_USD_KES | E10: 135 | F10: forex change silently ignored in one column only
A11: 7 | B11: P2 contained the formula W8/W8 (Wholesale_USD) | C11: self-division | D11: FX_USD_KES | E11: 135 | F11: returned literally 1.00 USD
A12: 8 | B12: Y11 and Z11 stored as TEXT "1.6" / "1.45" | C12: text | D12: number | E12: 1.6 / 1.45 | F12: coerces under * but fails under SUMPRODUCT/XLOOKUP — latent
A13: 9 | B13: rows 2-3 used UNANCHORED W8/Y11..Y14 | C13: relative | D13: absolute | E13: — | F13: any fill-down re-drifts the whole ladder
B15: PROPAGATING DEFECT — the most important line on this sheet
B16: Table1's own column templates (calculatedColumnFormula) carried the drifted references. Excel applies that template to EVERY new row. So the file was not merely damaged — it was manufacturing the damage. Any SKU added tomorrow would have inherited #VALUE!, #DIV/0! and the inverted corporate price. All 11 templates have been rewritten.

Sheet R4_FLOOR_GATE
A1: R4 hard floor — VAT-inclusive. Floor = Cost_KES x 1.35 x 1.16 = Cost_KES x 1.5660
A2: Cost base = "Landing Cost" (USD) x 135 as carried in this file. Retail multiplier is 1.600, so headroom above the floor is 1.600/1.566 = 2.13%. Any discount deeper than 2.13% breaches by arithmetic, before any judgement is applied.
A4: ROW | B4: SKU | C4: MODEL | D4: Cost_KES | E4: FLOOR | F4: RETAIL | G4: WHSL | H4: CORP | I4: INFL | J4: MAX DISCOUNT | K4: VERDICT
A5: 2 | B5: UC-HOU-PHRO-001 | C5: Pure Home | D5: 18900 | E5: 29597.4 | F5: 30990 | G5: 24990 | H5: 25990 | I5: 27990 | J5: 0.0449 | K5: BREACH: Whsl, Corp, Infl
A6: 3 | B6: UC-HOU-URO-001 | C6: Ultra Pure | D6: 8100 | E6: 12684.6 | F6: 12990 | G6: 10990 | H6: 11990 | I6: 11990 | J6: 0.0235 | K6: BREACH: Whsl, Corp, Infl
A7: 4 | B7: UC-HOU-URO-002 | C7: Ultra Pure 2 | D7: 8775 | E7: 13741.65 | F7: 14990 | G7: 11990 | H7: 11990 | I7: 12990 | J7: 0.0833 | K7: BREACH: Whsl, Corp, Infl
A8: 5 | B8: UC-HOU-ROS-001 | C8: Pure Blue | D8: 13732.2 | E8: 21504.63 | F8: 21990 | G8: 17990 | H8: 18990 | I8: 19990 | J8: 0.0221 | K8: BREACH: Whsl, Corp, Infl
A9: 6 | B9: UC-HOU-ROS-002 | C9: Aqua Stream 1200D | D9: 33750 | E9: 52852.5 | F9: 53990 | G9: 43990 | H9: 45990 | I9: 48990 | J9: 0.0211 | K9: BREACH: Whsl, Corp, Infl
A10: 7 | B10: UC-HOU-WPF-003 | C10: Pure Shield | D10: 7425 | E10: 11627.55 | F10: 11990 | G10: 9990 | H10: 10990 | I10: 10990 | J10: 0.0302 | K10: BREACH: Whsl, Corp, Infl
A11: 8 | B11: UC-HOU-USF-004 | C11: Aqua Drop | D11: 6793.2 | E11: 10638.15 | F11: 10990 | G11: 8990 | H11: 9990 | I11: 9990 | J11: 0.032 | K11: BREACH: Whsl, Corp, Infl
A12: 9 | B12: UC-HOU-TAP-005 | C12: Home sweet Home Filter set | D12: 1620 | E12: 2536.92 | F12: 2599.99 | G12: 2079.99 | H12: 2209.99 | I12: 2339.99 | J12: 0.0243 | K12: BREACH: Whsl, Corp, Infl
A13: 10 | B13: UC-HOU-TAPF-006 | C13: Home sweet Home Filter | D13: 742.5 | E13: 1162.76 | F13: 1189.99 | G13: 959.99 | H13: 1009.99 | I13: 1069.99 | J13: 0.0229 | K13: BREACH: Whsl, Corp, Infl
A14: 11 | B14: UC-HOU-WDFS-006 | C14: Wireless Dispenser Filter Set | D14: 1620 | E14: 2536.92 | F14: 2599.99 | G14: 2079.99 | H14: 2209.99 | I14: 2339.99 | J14: 0.0243 | K14: BREACH: Whsl, Corp, Infl
A15: 12 | B15: UC-HOU-DF-007 | C15: Dispenser Filter | D15: 945 | E15: 1479.87 | F15: 1519.99 | G15: 1209.99 | H15: 1289.99 | I15: 1369.99 | J15: 0.0264 | K15: BREACH: Whsl, Corp, Infl
A16: 13 | B16: UC-BOG-SSB-008 | C16: Hydra Flux | D16: 2160 | E16: 3382.56 | F16: 3499 | G16: 2799 | H16: 2999 | I16: 3199 | J16: 0.0333 | K16: BREACH: Whsl, Corp, Infl
... A22: 19 | B22: UC-BOG-SQB-014 | C22: Flex | D22: 938.25 | E22: 1469.3 | F22: 1509.99 | G22: 1209.99 | H22: 1279.99 | I22: 1359.99 | J22: 0.0269 | K22: BREACH: Whsl, Corp, Infl
A23: 20 | B23: UC-BOG-UF-100 | C23: Ultra Fold | D23: (no cost) | K23: NO COST ROW — cannot be gated. Blocks publish.
A24: 21 | B24: UC-BOG-FCA-015 | C24: Filter Squeeze Ahlstrom | D24: 540 | E24: 845.64 | F24: 869.99 | G24: 699.99 | H24: 739.99 | I24: 779.99 | J24: 0.028 | K24: BREACH: Whsl, Corp, Infl
A25: 22 | B25: UC-BOG-FCA-015 | C25: Filter Squeeze Ahlstrom | D25: 540 | E25: 845.64 | F25: 869.99 | G25: 699.99 | H25: 739.99 | I25: 779.99 | J25: 0.028 | K25: BREACH: Whsl, Corp, Infl
A26: 23 | B26: UC-BOG-FST-016 | C26: Survivor | D26: 810 | E26: 1268.46 | F26: 1299.99 | G26: 1039.99 | H26: 1109.99 | I26: 1169.99 | J26: 0.0243 | K26: BREACH: Whsl, Corp, Infl
A27: 24 | B27: UC-BOG-FCS-017 | C27: Survivor filter | D27: 270 | E27: 422.82 | F27: 439.99 | G27: 349.99 | H27: 369.99 | I27: 389.99 | J27: 0.039 | K27: BREACH: Whsl, Corp, Infl
A28: 25 | B28: UC-BOG-SHL-018 | C28: Shell | D28: 202.5 | E28: 317.12 | F28: 329.99 | G28: 259.99 | H28: 279.99 | I28: 299.99 | J28: 0.039 | K28: BREACH: Whsl, Corp, Infl
A29: 26 | B29: UC-SKW-SHF-019 | C29: Chanel | D29: 1620 | E29: 2536.92 | F29: 2599.99 | G29: 2079.99 | H29: 2209.99 | I29: 2339.99 | J29: 0.0243 | K29: BREACH: Whsl, Corp, Infl
A30: 27 | B30: UC-SKW-SHF-020 | C30: Derma Care | D30: 1282.5 | E30: 2008.39 | F30: 2059.99 | G30: 1649.99 | H30: 1749.99 | I30: 1849.99 | J30: 0.025 | K30: BREACH: Whsl, Corp, Infl
A31: 28 | B31: UC-SKW-SHF-021 | C31: J'adore | D31: 2025 | E31: 3171.15 | F31: 3299 | G31: 2599 | H31: 2799 | I31: 2999 | J31: 0.0388 | K31: BREACH: Whsl, Corp, Infl
A32: 29 | B32: UC-SKW-SHF-022 | C32: Pure Drop | D32: 1215 | E32: 1902.69 | F32: 1949.99 | G32: 1559.99 | H32: 1659.99 | I32: 1749.99 | J32: 0.0243 | K32: BREACH: Whsl, Corp, Infl
A33: 30 | B33: UC-SKW-SHC-023 | C33: Shower Filter | D33: 877.5 | E33: 1374.16 | F33: 1409.99 | G33: 1129.99 | H33: 1199.99 | I33: 1269.99 | J33: 0.0254 | K33: BREACH: Whsl, Corp, Infl
A34: 31 | B34: UC-SKW-DFS-024 | C34: Derma Flux | D34: 4050 | E34: 6342.3 | F34: 6499 | G34: 5199 | H34: 5599 | I34: 5899 | J34: 0.0241 | K34: BREACH: Whsl, Corp, Infl
A35: 32 | B35: UC-SKW-DFS-025 | C35: Derma Flux | D35: (no cost) | K35: NO COST ROW — cannot be gated. Blocks publish.
A36: 33 | B36: UC-SKW-DFS-026 | C36: Derma Flux | D36: (no cost) | K36: NO COST ROW — cannot be gated. Blocks publish.
A37: 34 | B37: UC-SKW-DFO-027 | C37: Derma Flux Fiiter | D37: 945 | E37: 1479.87 | F37: 1519.99 | G37: 1209.99 | H37: 1289.99 | I37: 1369.99 | J37: 0.0264 | K37: BREACH: Whsl, Corp, Infl
A38: 35 | B38: UC-HOU-ROP-PP | C38: RO Replacement | D38: 47.25 | E38: 73.99 | F38: 79.99 | G38: 69.99 | H38: 69.99 | I38: 69.99 | J38: 0.075 | K38: BREACH: Whsl, Corp, Infl
A39: 36 | B39: UC-HOU-ROP-UDF | C39: RO Replacement | D39: 405 | E39: 634.23 | F39: 649.99 | G39: 519.99 | H39: 559.99 | I39: 589.99 | J39: 0.0242 | K39: BREACH: Whsl, Corp, Infl
A40: 37 | B40: UC-HOU-ROP-CTO | C40: RO Replacement | D40: 405 | E40: 634.23 | F40: 649.99 | G40: 519.99 | H40: 559.99 | I40: 589.99 | J40: 0.0242 | K40: BREACH: Whsl, Corp, Infl
A41: 38 | B41: UC-HOU-ROM-100g | C41: RO Replacement | D41: 607.5 | E41: 951.35 | F41: 979.99 | G41: 779.99 | H41: 829.99 | I41: 879.99 | J41: 0.0292 | K41: BREACH: Whsl, Corp, Infl
A42: 39 | B42: UC-HOU-RO-YMT33 | C42: RO Replacement | D42: 162 | E42: 253.69 | F42: 259.99 | G42: 209.99 | H42: 229.99 | I42: 239.99 | J42: 0.0242 | K42: BREACH: Whsl, Corp, Infl
A43: 40 | B43: UC-HOU-RO-CBT33 | C43: RO Replacement | D43: 270 | E43: 422.82 | F43: 439.99 | G43: 349.99 | H43: 369.99 | I43: 389.99 | J43: 0.039 | K43: BREACH: Whsl, Corp, Infl
A44: 41 | B44: UC-BOG-ECO-ECF1 | C44: Ecosmart Filter | D44: 5805 | E44: 9090.63 | F44: 9299 | G44: 7499 | H44: 7899 | I44: 8399 | J44: 0.0224 | K44: BREACH: Whsl, Corp, Infl
B46: SUMMARY
B47: Retail | C47: 0 of 37 breach
B48: Wholesale | C48: 37 of 37 breach
B49: Corporate | C49: 37 of 37 breach
B50: Influencer | C50: 37 of 37 breach
B52: The ladder cannot clear the floor
B53: Retail = cost x 1.600 (passes, 2.13% headroom). Wholesale = cost x 1.280. Corporate = cost x 1.360. Influencer = cost x 1.440. The floor is cost x 1.566. Every discounted tier is below cost-plus-margin on every SKU — 111 of 111 tier/SKU combinations. This is not a data problem; the 20/15/10 discount schedule is arithmetically impossible at a 1.60 retail multiplier. Either the retail multiplier rises to at least 1.96 (to fund a 20% wholesale discount) or the discount schedule is cut to 2.13%.

Sheet OPEN_ITEMS
A1: Open items this file raises — owner ruling required
A3: No. | B3: SEVERITY | C3: ITEM | D3: FINDING / EVIDENCE | E3: DECISION
A4: 1 | B4: BLOCKING | C4: Retail multiplier 1.60 vs floor 1.566 | D4: Only 2.13% of discount capacity exists. The 20/15/10 wholesale/corporate/influencer schedule breaches the R4 floor on 100% of priced SKUs. Withdraw the schedule or raise the multiplier.
A5: 2 | B5: BLOCKING | C5: 3 SKUs with no Landing Cost | D5: UC-BOG-UF-100 (Ultra Fold), UC-SKW-DFS-025 and UC-SKW-DFS-026 (Derma Flux SF-N2 / SF-N3). Ex-works cost exists (6 / 47 / 45 USD) but landed does not, so no price and no floor test. They cannot be published.
A6: 3 | B6: HIGH | C6: Aqua Stream now carries a THIRD price | D6: This file: UC-HOU-ROS-002, retail 53,990. Live site: 69,990. Official 2026: 75,990. All three clear the floor (52,852), so the gate no longer blocks — but the identity does. D10 is now a naming/authority dispute, not a costing gap.
A7: 4 | B7: HIGH | C7: Aqua Stream SKU contradicts its own category | D7: Column A says "Commercial"; the SKU segment says HOU (Home & Utility); the catalogue calls it UC-COM-UP-027. One product, three identities. Nothing joins on a name — this must be resolved by ruling, not by matching text.
A8: 5 | B8: HIGH | C8: Duplicate SKU UC-BOG-FCA-015 | D8: Rows 21 and 22 both carry UC-BOG-FCA-015 but are different products: "Cartridge - squeeze Ahlstrom" (BG-F06A) and "Cartridge - bottle Ahlstrom" (Tritan Bottle Filter Cap). The master is sole issuer; one of these needs a new child SKU.
A9: 6 | B9: HIGH | C9: Consumables ladder defined but unused | D9: Z11:Z14 (1.45 / 0.5 / 0.6 / 0.65) exists and 15 rows are tagged "consumables" in column B, yet only row 12 ever referenced it. The repair standardised every row on the Core ladder, which moved UC-HOU-DF-007 from 1,370.25 to 1,512.00 (+10.3%). If consumables should use the Z ladder, say so and it will be switched by rule, not by hand.
A10: 7 | B10: MEDIUM | C10: 7 SKUs where landed cost = ex-works cost | D10: UC-HOU-ROP-PP/UDF/CTO, ROM-100g, RO-YMT33, RO-CBT33, and UC-SKW-DFO-027 carry landed = ex-works exactly. Freight, duty and clearing were never applied. Their cost is understated, so their floor is understated and their true breach is worse than shown.
A11: 8 | B11: MEDIUM | C11: 5 SKUs where landed cost is BELOW ex-works | D11: UC-BOG-FLB-012 (0.83x), SQB-013 (0.92x), SQB-014 (0.99x), FCS-017 (0.80x), SKW-DFS-024 (0.60x). Landing cannot be cheaper than the factory. Either the ex-works figure is stale or the landed figure is a negotiated price, not a cost.
A12: 9 | B12: MEDIUM | C12: Packing list is not joined | D12: The PL sheet and the AD column list manufacturer model codes as TEXT. No formula anywhere links a SKU to a packing-list line. The linkage you intend for this file does not exist yet — it is a visual adjacency, not a join.
A13: 10 | B13: LOW | C13: Tier ladder is based on raw Retail_KES, not the published psychological price | D13: Retail_USD is derived from the psychological price; the three discount tiers are derived from the unrounded retail. The two bases differ. Effect is small (under 1%) but the rule should be one or the other.

Sheet 00_READ_ME
B1: UC SKU MASTER v2 — variant, stock and landed-cost architecture
B3: THE ONE RULE | C3: A SKU is an identifier, not a description. It must be unique, stable and never re-issued. Every attribute — colour, size, media, filter life, carton size — lives in its own COLUMN. You never read a SKU to learn what something is; you look it up. Seven different SKU grammars exist today because each time a new attribute appeared, someone lengthened the string. Colour was about to be the eighth.
B5: CHILD SKU FORMAT | C5: CHILD_SKU = <PARENT_SKU>-<VV> where VV is a two-letter variant code, or XX where the product has no variants. Example: UC-BOG-TRB-010-GN. The parent is literally inside the child, so the parent-child join can never break and needs no crosswalk.
B7: WHY NOT LONGER | C7: The old format UC-EA-BOT-VDR-GN-500ML-25 embeds size and year. The packing list says that bottle is 500ml; the variation file says 500ML; Hydra Flux is 740ml on the packing list and 750ML in the variation file; Gym Buddy is 1000ml to the factory and 1200ml to us. Every contradiction lives in a segment that duplicates a column. Shortening the string deletes the whole class of error.
B9: WHAT IS A PARENT | C9: Different price, different cost or different carton = different PARENT. A 500ml and a 1000ml bottle are two parents. Different colour only = same parent, different CHILD.
B11: WHAT IS COUNTABLE | C11: Only CHILD_SKU is pickable, countable and sellable (ruling D38). Stock, orders and picks attach to the child. Price, cost, policy and evidence attach to the parent.
B13: STOCK vs FUTURE | C13: STOCK_STATUS is IN_STOCK only where a physical count recorded units. Everything else is FUTURE — not yet purchased — or INCOMING — on an open shipment. QTY_ON_HAND is meaningless without COUNT_DATE beside it: the current anchor is 12 Mar 2026 and a recount was due 7 Sep 2026.
B15: LANDED COST | C15: Landed cost is DERIVED, never typed. Landed = EXW + freight/unit + one-time fees/unit + duty & clearing. Freight/unit = (L x W x H x cartons / 1,000,000) / units x rate. BASIS records which method produced each number, so a typed figure can never masquerade as a measured one.
B17: FREIGHT RATE | C17: Two rates are in play: USD 400/CBM for the Tanzania stock already landed, USD 500/CBM for new stock. The rate is a named parameter (FREIGHT_RATE) on LANDED_COST_BUILD, not a constant inside formulas.
B19: RULING — CAPACITY | C19: Storefront capacity is the published figure and the only one used anywhere. Factory capacity is kept in a separate reference column, never published, so nobody "corrects" the storefront value back to the packing-list value. Hydra Flux 750 ml, Truva Go 750 ml, Gym Buddy 1200 ml.
B21: RULING — BLANK COST | C21: A missing landed cost is allowed. It is not allowed to be invisible. BASIS = NONE, and the gate holds the product out of the catalogue until a cost exists. Nothing is guessed to fill a gap.
B23: RULING — PRICE | C23: No price is fixed. The file computes a MINIMUM, never a price. PRICE_MIN = cost x R4_FLOOR / deepest tier. Judgement sets the actual price anywhere at or above it. The gate only ever tests the floor.
B25: THE GUARDRAIL | C25: MULT_RETAIL is DERIVED, not typed: ROUNDUP(R4_FLOOR / MIN_TIER_RATE x (1 + SAFETY_BUFFER), 2) = 2.00. At the old typed 1.60 the deepest discount landed at cost x 1.28, below the 1.566 floor — one typed number caused every tier breach in the catalogue. Deepen wholesale to 25% and MULT_RETAIL rises to 2.13 on its own. The rule now enforces itself.
B27: D10 — CLOSED | C27: UC-HOU-ROS-002 is RETIRED and never re-issued; it had pointed at two different products. The Commercial RO System is UC-COM-ROS-002, landed USD 200. Uniqueness is tested on the FULL string and the numeric segment carries no meaning, so reusing "002" creates no conflict. See SKU_REGISTRY.

Sheet CHILD_SKU
A1: CHILD_SKU — the only countable, pickable, sellable unit. RULING: storefront capacity is the published figure; factory capacity is reference only.
A3: CHILD_SKU | B3: PARENT_SKU | C3: MODEL NAME | D3: VARIANT_CODE | E3: VARIANT_AXIS | F3: COLOUR | G3: FINISH | H3: RELEASE | I3: CAPACITY_STOREFRONT | J3: CAPACITY_FACTORY (ref only) | K3: FILTER_LIFE | L3: FILTER_MEDIA | M3: LIFECYCLE | N3: STOCK_STATUS | O3: QTY_ON_HAND | P3: COUNT_DATE | Q3: SHIPMENT_ID | R3: ETA | S3: CHANNEL_PUBLISH | T3: LEGACY_SKU | U3: SOURCE | V3: FLAG
A4: UC-HOU-PHRO-001-XX | B4: UC-HOU-PHRO-001 | C4: Pure Home | D4: XX | E4: NONE | M4: ACTIVE | N4: FUTURE | O4: 0 | Q4: SHP-NEXT | R4: TBC | S4: HOLD | U4: derived from parent
A5: UC-HOU-URO-001-XX | B5: UC-HOU-URO-001 | C5: Ultra Pure | D5: XX | E5: NONE | M5: ACTIVE | N5: FUTURE | O5: 0 | Q5: SHP-NEXT | R5: TBC | S5: HOLD | U5: derived from parent
A6: UC-HOU-URO-002-XX | B6: UC-HOU-URO-002 | C6: Ultra Pure 2 | D6: XX | E6: NONE | M6: ACTIVE | N6: FUTURE | O6: 0 | Q6: SHP-NEXT | R6: TBC | S6: HOLD | U6: derived from parent
A7: UC-HOU-ROS-001-XX | B7: UC-HOU-ROS-001 | C7: Pure Blue | D7: XX | E7: NONE | M7: ACTIVE | N7: FUTURE | O7: 0 | Q7: SHP-NEXT | R7: TBC | S7: HOLD | U7: derived from parent
A8: UC-COM-ROS-002-XX | B8: UC-COM-ROS-002 | C8: Aqua Stream 1200D | D8: XX | E8: NONE | M8: ACTIVE | N8: FUTURE | O8: 0 | Q8: SHP-NEXT | R8: TBC | S8: HOLD | U8: derived from parent
A9: UC-HOU-WPF-003-XX | B9: UC-HOU-WPF-003 | C9: Pure Shield | D9: XX | E9: NONE | M9: ACTIVE | N9: FUTURE | O9: 0 | Q9: SHP-NEXT | R9: TBC | S9: HOLD | U9: derived from parent
A10: UC-HOU-USF-004-XX | B10: UC-HOU-USF-004 | C10: Aqua Drop | D10: XX | E10: NONE | M10: ACTIVE | N10: FUTURE | O10: 0 | Q10: SHP-NEXT | R10: TBC | S10: HOLD | U10: derived from parent
A11: UC-HOU-TAP-005-WH | B11: UC-HOU-TAP-005 | C11: Home sweet Home Filter set | D11: WH | E11: COLOUR | F11: White | I11: 8 L/min | K11: 1500 L | L11: Ahlstrom + carbon | M11: ACTIVE | N11: FUTURE | O11: 0 | Q11: SHP-NEXT | R11: TBC | S11: HOLD | T11: UC-EA-KCH-SHF-FAUCET-WH-25 | U11: SKU variation.csv
A12: UC-HOU-TAPF-006-WH | B12: UC-HOU-TAPF-006 | C12: Home sweet Home Filter | D12: WH | E12: COLOUR | F12: White | K12: 1500 L | L12: Ahlstrom + carbon | M12: ACTIVE | N12: IN_STOCK | O12: 93 | P12: 2026-03-12 | S12: PUBLISH | T12: UC-EA-KCH-CRT-SHF-WH-25 | U12: SKU variation.csv
A13: UC-HOU-WDFS-006-WH | B13: UC-HOU-WDFS-006 | C13: Wireless Dispenser Filter Set | D13: WH | E13: COLOUR | F13: White | K13: 400 L | L13: UF origami | M13: ACTIVE | N13: IN_STOCK | O13: 58 | P13: 2026-03-12 | S13: PUBLISH | T13: UC-EA-DSP-WDS-WIRELESS-WH-25 | U13: SKU variation.csv
A14: UC-HOU-DF-007-XX | B14: UC-HOU-DF-007 | C14: Dispenser Filter | D14: XX | E14: NONE | M14: ACTIVE | N14: IN_STOCK | O14: 41 | P14: 2026-03-12 | S14: PUBLISH | U14: derived from parent
A15: UC-BOG-SSB-008-DG | B15: UC-BOG-SSB-008 | C15: Hydra Flux | D15: DG | E15: COLOUR | F15: Dark Grey | H15: LIMITED | I15: 750 ml | J15: 740 ml (BG-B01) | K15: 150 L | L15: Ahlstrom + ACF | M15: ACTIVE | N15: IN_STOCK | O15: 5 | P15: 2026-03-12 | S15: PUBLISH | T15: UC-EA-BOT-HYF-LTD-DG-750ML-25 | U15: SKU variation.csv | V15: Limited colour. QTY split evenly across variants — NOT a counted figure. Recount by variant required.
A16: UC-BOG-SSB-008-BL | B16: UC-BOG-SSB-008 | C16: Hydra Flux | D16: BL | E16: COLOUR | F16: Blue | I16: 750 ml | J16: 740 ml (BG-B01) | K16: 150 L | L16: Ahlstrom + ACF | M16: ACTIVE | N16: IN_STOCK | O16: 5 | P16: 2026-03-12 | S16: PUBLISH | T16: UC-EA-BOT-HYF-BL-750ML-25 | U16: SKU variation.csv | V16: QTY split evenly across variants — NOT a counted figure. Recount by variant required.
A17: UC-BOG-SSB-008-PK | B17: UC-BOG-SSB-008 | C17: Hydra Flux | D17: PK | E17: COLOUR | F17: Pink | I17: 750 ml | J17: 740 ml (BG-B01) | K17: 150 L | L17: Ahlstrom + ACF | M17: ACTIVE | N17: IN_STOCK | O17: 5 | P17: 2026-03-12 | S17: PUBLISH | T17: UC-EA-BOT-HYF-PK-750ML-25 | U17: SKU variation.csv | V17: QTY split evenly across variants — NOT a counted figure. Recount by variant required.
A18: UC-BOG-SSB-008-GY | B18: UC-BOG-SSB-008 | C18: Hydra Flux | D18: GY | E18: COLOUR | F18: Grey | I18: 750 ml | J18: 740 ml (BG-B01) | K18: 150 L | L18: Ahlstrom + ACF | M18: ACTIVE | N18: IN_STOCK | O18: 5 | P18: 2026-03-12 | S18: PUBLISH | T18: UC-EA-BOT-HYF-GY-750ML-25 | U18: SKU variation.csv | V18: QTY split evenly across variants — NOT a counted figure. Recount by variant required.
A19: UC-BOG-TRB-009-GY | B19: UC-BOG-TRB-009 | C19: Truva Go | D19: GY | E19: COLOUR | F19: Grey | I19: 750 ml | J19: 769 ml (BG-B02) | K19: 150 L | L19: Ahlstrom + ACF | M19: ACTIVE | N19: IN_STOCK | O19: 12 | P19: 2026-03-12 | S19: PUBLISH | T19: UC-EA-BOT-TRG-GY-750ML-25 | U19: SKU variation.csv | V19: QTY split evenly across variants — NOT a counted figure. Recount by variant required.
A20: UC-BOG-TRB-009-PK | B20: UC-BOG-TRB-009 | C20: Truva Go | D20: PK | E20: COLOUR | F20: Pink | I20: 750 ml | J20: 769 ml (BG-B02) | K20: 150 L | L20: Ahlstrom + ACF | M20: ACTIVE | N20: IN_STOCK | O20: 12 | P20: 2026-03-12 | S20: PUBLISH | T20: UC-EA-BOT-TRG-PK-750ML-25 | U20: SKU variation.csv | V20: QTY split evenly across variants — NOT a counted figure. Recount by variant required.
A21: UC-BOG-TRB-009-BL | B21: UC-BOG-TRB-009 | C21: Truva Go | D21: BL | E21: COLOUR | F21: Blue | I21: 750 ml | J21: 769 ml (BG-B02) | K21: 150 L | L21: Ahlstrom + ACF | M21: ACTIVE | N21: IN_STOCK | O21: 12 | P21: 2026-03-12 | S21: PUBLISH | T21: UC-EA-BOT-TRG-BL-750ML-25 | U21: SKU variation.csv | V21: QTY split evenly across variants — NOT a counted figure. Recount by variant required.
A22: UC-BOG-TRB-010-GN | B22: UC-BOG-TRB-010 | C22: Viva Drop | D22: GN | E22: COLOUR | F22: Green | I22: 500 ml | K22: 150 L | L22: Ahlstrom + ACF | M22: ACTIVE | N22: IN_STOCK | O22: 35 | P22: 2026-03-12 | S22: PUBLISH | T22: UC-EA-BOT-VDR-GN-500ML-25 | U22: SKU variation.csv | V22: QTY split evenly across variants — NOT a counted figure. Recount by variant required.
A23: UC-BOG-TRB-010-BK | B23: UC-BOG-TRB-010 | C23: Viva Drop | D23: BK | E23: COLOUR | F23: Black | I23: 500 ml | K23: 150 L | L23: Ahlstrom + ACF | M23: ACTIVE | N23: IN_STOCK | O23: 35 | P23: 2026-03-12 | S23: PUBLISH | T23: UC-EA-BOT-VDR-BK-500ML-25 | U23: SKU variation.csv | V23: QTY split evenly across variants — NOT a counted figure. Recount by variant required.
A24: UC-BOG-TRB-011-BK | B24: UC-BOG-TRB-011 | C24: Gym Buddy | D24: BK | E24: COLOUR | F24: Black | I24: 1200 ml | J24: 1000 ml (BG-B09) | K24: 150 L | L24: Ahlstrom + ACF | M24: ACTIVE | N24: IN_STOCK | O24: 12 | P24: 2026-03-12 | S24: PUBLISH | T24: UC-EA-BOT-GYM-BK-1200ML-25 | U24: SKU variation.csv | V24: QTY split evenly across variants — NOT a counted figure. Recount by variant required.
A25: UC-BOG-TRB-011-GN | B25: UC-BOG-TRB-011 | C25: Gym Buddy | D25: GN | E25: COLOUR | F25: Green | I25: 1200 ml | J25: 1000 ml (BG-B09) | K25: 150 L | L25: Ahlstrom + ACF | M25: ACTIVE | N25: IN_STOCK | O25: 12 | P25: 2026-03-12 | S25: PUBLISH | T25: UC-EA-BOT-GYM-GN-1200ML-25 | U25: SKU variation.csv | V25: QTY split evenly across variants — NOT a counted figure. Recount by variant required.
A26: UC-BOG-FLB-012-XX | B26: UC-BOG-FLB-012 | C26: Timbo | D26: XX | E26: NONE | I26: 350 ml | M26: ACTIVE | N26: IN_STOCK | O26: 3 | P26: 2026-03-12 | S26: PUBLISH | U26: derived from parent
A27: UC-BOG-SQB-013-XX | B27: UC-BOG-SQB-013 | C27: Breeze | D27: XX | E27: NONE | I27: 600 ml | M27: ACTIVE | N27: FUTURE | O27: 0 | Q27: SHP-NEXT | R27: TBC | S27: HOLD | U27: derived from parent
A28: UC-BOG-SQB-014-PK | B28: UC-BOG-SQB-014 | C28: Flex | D28: PK | E28: COLOUR | F28: Pink | I28: 1000 ml | K28: 150 L | L28: Ahlstrom + ACF | M28: ACTIVE | N28: IN_STOCK | O28: 38 | P28: 2026-03-12 | S28: PUBLISH | T28: UC-EA-BOT-FLX-PK-1000ML-25 | U28: SKU variation.csv | V28: QTY split evenly across variants — NOT a counted figure. Recount by variant required.
A29: UC-BOG-SQB-014-GY | B29: UC-BOG-SQB-014 | C29: Flex | D29: GY | E29: COLOUR | F29: Grey | I29: 1000 ml | K29: 150 L | L29: Ahlstrom + ACF | M29: ACTIVE | N29: IN_STOCK | O29: 38 | P29: 2026-03-12 | S29: PUBLISH | T29: UC-EA-BOT-FLX-GY-1000ML-25 | U29: SKU variation.csv | V29: QTY split evenly across variants — NOT a counted figure. Recount by variant required.
A30: UC-BOG-UF-100-XX | B30: UC-BOG-UF-100 | C30: Ultra Fold | D30: XX | E30: NONE | M30: ACTIVE | N30: FUTURE | O30: 0 | Q30: SHP-NEXT | R30: TBC | S30: HOLD | U30: derived from parent
A31: UC-BOG-FCA-015-XX | B31: UC-BOG-FCA-015 | C31: Filter Squeeze Ahlstrom | D31: XX | E31: NONE | M31: ACTIVE | N31: IN_STOCK | O31: 351 | P31: 2026-03-12 | S31: PUBLISH | U31: derived from parent
A32: UC-BOG-FST-016-BL | B32: UC-BOG-FST-016 | C32: Survivor | D32: BL | E32: COLOUR | F32: Blue | K32: 300 L | L32: UF membrane | M32: ACTIVE | N32: IN_STOCK | O32: 17 | P32: 2026-03-12 | S32: PUBLISH | T32: UC-EA-BOT-SVS-BL-25 | U32: SKU variation.csv | V32: QTY split evenly across variants — NOT a counted figure. Recount by variant required.
A33: UC-BOG-FST-016-OR | B33: UC-BOG-FST-016 | C33: Survivor | D33: OR | E33: COLOUR | F33: Orange | K33: 300 L | L33: UF membrane | M33: ACTIVE | N33: IN_STOCK | O33: 17 | P33: 2026-03-12 | S33: PUBLISH | T33: UC-EA-BOT-SVS-OR-25 | U33: SKU variation.csv | V33: QTY split evenly across variants — NOT a counted figure. Recount by variant required.
A34: UC-BOG-FCS-017-XX | B34: UC-BOG-FCS-017 | C34: Survivor filter | D34: XX | E34: NONE | M34: ACTIVE | N34: FUTURE | O34: 0 | Q34: SHP-NEXT | R34: TBC | S34: HOLD | U34: derived from parent
A35: UC-BOG-SHL-018-XX | B35: UC-BOG-SHL-018 | C35: Shell | D35: XX | E35: NONE | M35: ACTIVE | N35: IN_STOCK | O35: 50 | P35: 2026-03-12 | S35: PUBLISH | U35: derived from parent
A36: UC-SKW-SHF-019-WH | B36: UC-SKW-SHF-019 | C36: Chanel | D36: WH | E36: COLOUR | F36: White | G36: Ceramic | I36: 8 L/min | K36: 20000 L | L36: PP+ACF+carbon+KDF+Vit C | M36: ACTIVE | N36: IN_STOCK | O36: 60 | P36: 2026-03-12 | S36: PUBLISH | T36: UC-EA-SHW-CHN-CERAMIC-WH-25 | U36: SKU variation.csv | V36: Manual start-date dial on Chanel.
A37: UC-SKW-SHF-020-WH | B37: UC-SKW-SHF-020 | C37: Derma Care | D37: WH | E37: COLOUR | F37: White | G37: Tritan | I37: 8 L/min | K37: 20000 L | L37: PP+ACF+carbon+KDF+Vit C | M37: ACTIVE | N37: IN_STOCK | O37: 50 | P37: 2026-03-12 | S37: PUBLISH | T37: UC-EA-SHW-DRC-TRITAN-WH-25 | U37: SKU variation.csv
A38: UC-SKW-SHF-021-SS | B38: UC-SKW-SHF-021 | C38: J'adore | D38: SS | E38: FINISH | G38: Stainless | I38: 8 L/min | K38: 20000 L | L38: PP+ACF+carbon+KDF+Vit C | M38: ACTIVE | N38: IN_STOCK | O38: 65 | P38: 2026-03-12 | S38: PUBLISH | T38: UC-EA-SHW-JAD-STAINLESS-SS-25 | U38: SKU variation.csv
A39: UC-SKW-SHF-022-WH | B39: UC-SKW-SHF-022 | C39: Pure Drop | D39: WH | E39: COLOUR | F39: White | I39: 8 L/min | K39: 20000 L | L39: PP+ACF+carbon+KDF+Vit C | M39: ACTIVE | N39: IN_STOCK | O39: 10 | P39: 2026-03-12 | S39: PUBLISH | T39: UC-EA-SHW-PRD-FIXED-WH-25 | U39: SKU variation.csv
A40: UC-SKW-SHC-023-XX | B40: UC-SKW-SHC-023 | C40: Shower Filter | D40: XX | E40: NONE | K40: 20000 L | L40: ACF+carbon+KDF+Vit C | M40: ACTIVE | N40: IN_STOCK | O40: 94 | P40: 2026-03-12 | S40: PUBLISH | T40: UC-EA-SHW-CRT-JAD-WH-25 / -CHN- / -DRC- (all three) | U40: SKU variation.csv | V40: RULED 21 Sep 2026: one cartridge fits all replaceable shower types. Legacy keys UC-EA-SHW-CRT-JAD / -CHN / -DRC all map here.
A41: UC-SKW-DFS-024-WH | B41: UC-SKW-DFS-024 | C41: Derma Flux | D41: WH | E41: COLOUR | F41: White | M41: ACTIVE | N41: IN_STOCK | O41: 2 | P41: 2026-03-12 | S41: PUBLISH | T41: UC-EA-FAC-DFX-FACIAL-WH-25 | U41: SKU variation.csv | V41: UNRESOLVED: variation file also has UC-EA-FAC-BFF-FAUCET-CR-25 "Beauty Faucet Filter" (chrome). Is that this parent or a separate product?
A42: UC-SKW-DFS-025-XX | B42: UC-SKW-DFS-025 | C42: Derma Flux | D42: XX | E42: NONE | M42: ACTIVE | N42: FUTURE | O42: 0 | Q42: SHP-NEXT | R42: TBC | S42: HOLD | U42: derived from parent
A43: UC-SKW-DFS-026-XX | B43: UC-SKW-DFS-026 | C43: Derma Flux | D43: XX | E43: NONE | M43: ACTIVE | N43: FUTURE | O43: 0 | Q43: SHP-NEXT | R43: TBC | S43: HOLD | U43: derived from parent
A44: UC-SKW-DFO-027-XX | B44: UC-SKW-DFO-027 | C44: Derma Flux Fiiter | D44: XX | E44: NONE | M44: ACTIVE | N44: IN_STOCK | O44: 2 | P44: 2026-03-12 | S44: PUBLISH | U44: derived from parent
A45: UC-HOU-ROP-PP-XX | B45: UC-HOU-ROP-PP | C45: RO Replacement | D45: XX | E45: NONE | M45: ACTIVE | N45: FUTURE | O45: 0 | Q45: SHP-NEXT | R45: TBC | S45: HOLD | U45: derived from parent
A46: UC-HOU-ROP-UDF-XX | B46: UC-HOU-ROP-UDF | C46: RO Replacement | D46: XX | E46: NONE | M46: ACTIVE | N46: FUTURE | O46: 0 | Q46: SHP-NEXT | R46: TBC | S46: HOLD | U46: derived from parent
A47: UC-HOU-ROP-CTO-XX | B47: UC-HOU-ROP-CTO | C47: RO Replacement | D47: XX | E47: NONE | M47: ACTIVE | N47: FUTURE | O47: 0 | Q47: SHP-NEXT | R47: TBC | S47: HOLD | U47: derived from parent
A48: UC-HOU-ROM-100g-XX | B48: UC-HOU-ROM-100g | C48: RO Replacement | D48: XX | E48: NONE | M48: ACTIVE | N48: FUTURE | O48: 0 | Q48: SHP-NEXT | R48: TBC | S48: HOLD | U48: derived from parent
A49: UC-HOU-RO-YMT33-XX | B49: UC-HOU-RO-YMT33 | C49: RO Replacement | D49: XX | E49: NONE | M49: ACTIVE | N49: FUTURE | O49: 0 | Q49: SHP-NEXT | R49: TBC | S49: HOLD | U49: derived from parent
A50: UC-HOU-RO-CBT33-XX | B50: UC-HOU-RO-CBT33 | C50: RO Replacement | D50: XX | E50: NONE | M50: ACTIVE | N50: FUTURE | O50: 0 | Q50: SHP-NEXT | R50: TBC | S50: HOLD | U50: derived from parent
A51: UC-BOG-ECO-ECF1-XX | B51: UC-BOG-ECO-ECF1 | C51: Ecosmart Filter | D51: XX | E51: NONE | M51: ACTIVE | N51: FUTURE | O51: 0 | Q51: SHP-NEXT | R51: TBC | S51: HOLD | U51: derived from parent
A52: UC-HOU-ROT-029-XX | B52: UC-HOU-ROT-029 | C52: RO Mini Tank | D52: XX | E52: NONE | I52: 0.5 gal | M52: ACTIVE | N52: FUTURE | O52: 0 | Q52: SHP-NEXT | R52: TBC | S52: HOLD | U52: registry 21 Sep 2026 | V52: Issued 21 Sep 2026. No landed cost yet — gate holds it.

Sheet LOGISTICS_PL
A1: LOGISTICS — one row per packing-list carton line. Freight is DERIVED here and nowhere else.
A2: Unit CBM = L x W x H x cartons / 1,000,000 / units. Freight/unit = Unit CBM x FREIGHT_RATE.
A4: PL_LINE | B4: SHIPMENT_ID | C4: PARENT_SKU | D4: MFR_MODEL | E4: UNITS | F4: PCS/CTN | G4: CARTONS | H4: L (cm) | I4: W (cm) | J4: H (cm) | K4: NW/CTN | L4: GW/CTN | M4: TOTAL_GW | N4: TOTAL_CBM | O4: UNIT_CBM | P4: FREIGHT/UNIT | Q4: FREIGHT_LINE | R4: DIMS_SOURCE | S4: NOTE
A5: PL-007 | B5: SHP-BG-2024-01 | C5: UC-BOG-SSB-008 | D5: 740ml stainless steel water filter bottle BG-B01 | E5: 84 | F5: 21 | G5: 4 | H5: 53.5 | I5: 46 | J5: 30.5 | K5: 10.6 | L5: 11.5 | M5: =IF(L5="","",L5*G5) | N5: =IF(OR(H5="",G5=""),"",ROUND(H5*I5*J5*G5/1000000,6)) | O5: =IF(OR(N5="",E5=0),"",ROUND(N5/E5,6)) | P5: =IF(O5="","",ROUND(O5*FREIGHT_RATE,4)) | Q5: =IF(P5="","",ROUND(P5*E5,2)) | R5: MEASURED
A6: PL-008 | B6: SHP-BG-2024-01 | C6: UC-BOG-TRB-009 | D6: 769ml tritan water filter bottle BG-B02 | E6: 90 | F6: 30 | G6: 3 | H6: 53.5 | I6: 46 | J6: 30.5 | K6: 9.1 | L6: 10 | M6: =IF(L6="","",L6*G6) | N6: =IF(OR(H6="",G6=""),"",ROUND(H6*I6*J6*G6/1000000,6)) | O6: =IF(OR(N6="",E6=0),"",ROUND(N6/E6,6)) | P6: =IF(O6="","",ROUND(O6*FREIGHT_RATE,4)) | Q6: =IF(P6="","",ROUND(P6*E6,2)) | R6: MEASURED
A7: PL-009 | B7: SHP-BG-2024-01 | C7: UC-BOG-TRB-009 | E7: 60 | F7: 20 | G7: 3 | H7: 54.5 | I7: 44 | J7: 31 | K7: 6.1 | L7: 7 | M7: =IF(L7="","",L7*G7) | N7: =IF(OR(H7="",G7=""),"",ROUND(H7*I7*J7*G7/1000000,6)) | O7: =IF(OR(N7="",E7=0),"",ROUND(N7/E7,6)) | P7: =IF(O7="","",ROUND(O7*FREIGHT_RATE,4)) | Q7: =IF(P7="","",ROUND(P7*E7,2)) | R7: MEASURED | S7: continuation of the line above — packing list left the SKU blank
A8: PL-010 | B8: SHP-BG-2024-01 | C8: UC-BOG-TRB-010 | D8: 500ml tritan water filter bottle(black) BG-B06 | E8: 84 | F8: 42 | G8: 2 | H8: 51.5 | I8: 57.5 | J8: 25 | K8: 10.3 | L8: 11.3 | M8: =IF(L8="","",L8*G8) | N8: =IF(OR(H8="",G8=""),"",ROUND(H8*I8*J8*G8/1000000,6)) | O8: =IF(OR(N8="",E8=0),"",ROUND(N8/E8,6)) | P8: =IF(O8="","",ROUND(O8*FREIGHT_RATE,4)) | Q8: =IF(P8="","",ROUND(P8*E8,2)) | R8: MEASURED
A9: PL-011 | B9: SHP-BG-2024-01 | C9: UC-BOG-TRB-010 | E9: 6 | F9: 6 | G9: 1 | H9: 36 | I9: 36 | J9: 17 | K9: 1.4 | L9: 2 | M9: =IF(L9="","",L9*G9) | N9: =IF(OR(H9="",G9=""),"",ROUND(H9*I9*J9*G9/1000000,6)) | O9: =IF(OR(N9="",E9=0),"",ROUND(N9/E9,6)) | P9: =IF(O9="","",ROUND(O9*FREIGHT_RATE,4)) | Q9: =IF(P9="","",ROUND(P9*E9,2)) | R9: MEASURED | S9: continuation of the line above — packing list left the SKU blank
A10: PL-012 | B10: SHP-BG-2024-01 | C10: UC-BOG-TRB-010 | E10: 60 | F10: 30 | G10: 2 | H10: 50 | I10: 42.5 | J10: 24.5 | K10: 7.4 | L10: 8.4 | M10: =IF(L10="","",L10*G10) | N10: =IF(OR(H10="",G10=""),"",ROUND(H10*I10*J10*G10/1000000,6)) | O10: =IF(OR(N10="",E10=0),"",ROUND(N10/E10,6)) | P10: =IF(O10="","",ROUND(O10*FREIGHT_RATE,4)) | Q10: =IF(P10="","",ROUND(P10*E10,2)) | R10: MEASURED | S10: continuation of the line above — packing list left the SKU blank
A11: PL-013 | B11: SHP-BG-2024-01 | C11: UC-BOG-TRB-011 | D11: 1000ml tritan water filter bottle BG-B09 | E11: 100 | F11: 50 | G11: 2 | H11: 50 | I11: 42.5 | J11: 24.5 | K11: 16.8 | L11: 17.8 | M11: =IF(L11="","",L11*G11) | N11: =IF(OR(H11="",G11=""),"",ROUND(H11*I11*J11*G11/1000000,6)) | O11: =IF(OR(N11="",E11=0),"",ROUND(N11/E11,6)) | P11: =IF(O11="","",ROUND(O11*FREIGHT_RATE,4)) | Q11: =IF(P11="","",ROUND(P11*E11,2)) | R11: MEASURED
A12: PL-014 | B12: SHP-BG-2024-01 | C12: UC-BOG-TRB-011 | E12: 20 | F12: 10 | G12: 2 | H12: 55 | I12: 23.5 | J12: 37.5 | K12: 3.4 | L12: 4 | M12: =IF(L12="","",L12*G12) | N12: =IF(OR(H12="",G12=""),"",ROUND(H12*I12*J12*G12/1000000,6)) | O12: =IF(OR(N12="",E12=0),"",ROUND(N12/E12,6)) | P12: =IF(O12="","",ROUND(O12*FREIGHT_RATE,4)) | Q12: =IF(P12="","",ROUND(P12*E12,2)) | R12: MEASURED | S12: continuation of the line above — packing list left the SKU blank
A13: PL-015 | B13: SHP-BG-2024-01 | C13: UC-BOG-FLB-012 | D13: 350ml collapsible water filter bottle BG-B04 | E13: 40 | F13: 40 | G13: 1 | H13: 57 | I13: 39.5 | J13: 29.5 | K13: 10.3 | L13: 11.3 | M13: =IF(L13="","",L13*G13) | N13: =IF(OR(H13="",G13=""),"",ROUND(H13*I13*J13*G13/1000000,6)) | O13: =IF(OR(N13="",E13=0),"",ROUND(N13/E13,6)) | P13: =IF(O13="","",ROUND(O13*FREIGHT_RATE,4)) | Q13: =IF(P13="","",ROUND(P13*E13,2)) | R13: MEASURED
A14: PL-016 | B14: SHP-BG-2024-01 | C14: UC-BOG-SQB-014 | D14: 1000ml squeeze water filter bottle BG-B07 | E14: 72 | F14: 36 | G14: 2 | H14: 57.5 | I14: 57.5 | J14: 44.5 | K14: 10.2 | L14: 11.2 | M14: =IF(L14="","",L14*G14) | N14: =IF(OR(H14="",G14=""),"",ROUND(H14*I14*J14*G14/1000000,6)) | O14: =IF(OR(N14="",E14=0),"",ROUND(N14/E14,6)) | P14: =IF(O14="","",ROUND(O14*FREIGHT_RATE,4)) | Q14: =IF(P14="","",ROUND(P14*E14,2)) | R14: MEASURED
A15: PL-017 | B15: SHP-BG-2024-01 | C15: UC-BOG-SQB-014 | E15: 28 | F15: 14 | G15: 2 | H15: 54 | I15: 45.5 | J15: 31 | K15: 4.1 | L15: 5.1 | M15: =IF(L15="","",L15*G15) | N15: =IF(OR(H15="",G15=""),"",ROUND(H15*I15*J15*G15/1000000,6)) | O15: =IF(OR(N15="",E15=0),"",ROUND(N15/E15,6)) | P15: =IF(O15="","",ROUND(O15*FREIGHT_RATE,4)) | Q15: =IF(P15="","",ROUND(P15*E15,2)) | R15: MEASURED | S15: continuation of the line above — packing list left the SKU blank
A16: PL-018 | B16: SHP-BG-2024-01 | C16: UC-BOG-FCA-015 | D16: straw bottle's filters+squeeze bottle's actived fiber filter | E16: 360 | F16: 120 | G16: 3 | H16: 29 | I16: 32 | J16: 14 | K16: 2.6 | L16: 3 | M16: =IF(L16="","",L16*G16) | N16: =IF(OR(H16="",G16=""),"",ROUND(H16*I16*J16*G16/1000000,6)) | O16: =IF(OR(N16="",E16=0),"",ROUND(N16/E16,6)) | P16: =IF(O16="","",ROUND(O16*FREIGHT_RATE,4)) | Q16: =IF(P16="","",ROUND(P16*E16,2)) | R16: MEASURED
A17: PL-019 | B17: SHP-BG-2024-01 | C17: UC-BOG-FCA-015 | E17: 100 | F17: 100 | G17: 1 | H17: 29 | I17: 32 | J17: 14 | K17: 2.2 | L17: 2.5 | M17: =IF(L17="","",L17*G17) | N17: =IF(OR(H17="",G17=""),"",ROUND(H17*I17*J17*G17/1000000,6)) | O17: =IF(OR(N17="",E17=0),"",ROUND(N17/E17,6)) | P17: =IF(O17="","",ROUND(O17*FREIGHT_RATE,4)) | Q17: =IF(P17="","",ROUND(P17*E17,2)) | R17: MEASURED
A18: PL-020 | B18: SHP-BG-2024-01 | C18: UC-BOG-SHL-018 | D18: 740ml stainless steel water filter bottle' s straw only NIL | E18: 50 | F18: 50 | G18: 1 | H18: 36.5 | I18: 20 | J18: 19 | K18: 1.5 | L18: 1.7 | M18: =IF(L18="","",L18*G18) | N18: =IF(OR(H18="",G18=""),"",ROUND(H18*I18*J18*G18/1000000,6)) | O18: =IF(OR(N18="",E18=0),"",ROUND(N18/E18,6)) | P18: =IF(O18="","",ROUND(O18*FREIGHT_RATE,4)) | Q18: =IF(P18="","",ROUND(P18*E18,2)) | R18: MEASURED
A19: PL-021 | B19: SHP-BG-2024-01 | C19: UC-HOU-DF-007 | D19: pump filter cartridge BG-F04A | E19: 120 | F19: 60 | G19: 2 | H19: 50.5 | I19: 41.5 | J19: 26 | K19: 9.3 | L19: 10.3 | M19: =IF(L19="","",L19*G19) | N19: =IF(OR(H19="",G19=""),"",ROUND(H19*I19*J19*G19/1000000,6)) | O19: =IF(OR(N19="",E19=0),"",ROUND(N19/E19,6)) | P19: =IF(O19="","",ROUND(O19*FREIGHT_RATE,4)) | Q19: =IF(P19="","",ROUND(P19*E19,2)) | R19: MEASURED | S19: CORRECTED: packing list said UC-HOU-WDFS-006, but BG-F04A is the pump cartridge = UC-HOU-DF-007. The shipping estimate inherited this error and put USD 97.54 of freight on the wrong SKU.
A20: PL-022 | B20: SHP-BG-2024-01 | C20: UC-HOU-DF-007 | E20: 80 | F20: 40 | G20: 2 | H20: 42 | I20: 41 | J20: 25 | K20: 6 | L20: 7 | M20: =IF(L20="","",L20*G20) | N20: =IF(OR(H20="",G20=""),"",ROUND(H20*I20*J20*G20/1000000,6)) | O20: =IF(OR(N20="",E20=0),"",ROUND(N20/E20,6)) | P20: =IF(O20="","",ROUND(O20*FREIGHT_RATE,4)) | Q20: =IF(P20="","",ROUND(P20*E20,2)) | R20: MEASURED | S20: continuation of the line above — packing list left the SKU blank
A21: PL-023 | B21: SHP-BG-2024-01 | C21: UC-HOU-TAP-005 | D21: ultra filter faucet BG-T01U | E21: 180 | F21: 30 | G21: 6 | H21: 42.5 | I21: 38 | J21: 39.5 | K21: 14.5 | L21: 15.5 | M21: =IF(L21="","",L21*G21) | N21: =IF(OR(H21="",G21=""),"",ROUND(H21*I21*J21*G21/1000000,6)) | O21: =IF(OR(N21="",E21=0),"",ROUND(N21/E21,6)) | P21: =IF(O21="","",ROUND(O21*FREIGHT_RATE,4)) | Q21: =IF(P21="","",ROUND(P21*E21,2)) | R21: MEASURED
A22: PL-024 | B22: SHP-BG-2024-01 | C22: UC-HOU-TAP-005 | E22: 20 | F22: 20 | G22: 1 | H22: 42.5 | I22: 38 | J22: 39.5 | K22: 9.5 | L22: 10.5 | M22: =IF(L22="","",L22*G22) | N22: =IF(OR(H22="",G22=""),"",ROUND(H22*I22*J22*G22/1000000,6)) | O22: =IF(OR(N22="",E22=0),"",ROUND(N22/E22,6)) | P22: =IF(O22="","",ROUND(O22*FREIGHT_RATE,4)) | Q22: =IF(P22="","",ROUND(P22*E22,2)) | R22: MEASURED | S22: continuation of the line above — packing list left the SKU blank
A23: PL-025 | B23: SHP-BG-2024-01 | C23: UC-HOU-TAPF-006 | D23: faucet filter cartridge BG-F01U | E23: 120 | F23: 120 | G23: 1 | H23: 48.5 | I23: 30.5 | J23: 20 | K23: 7 | L23: 7.6 | M23: =IF(L23="","",L23*G23) | N23: =IF(OR(H23="",G23=""),"",ROUND(H23*I23*J23*G23/1000000,6)) | O23: =IF(OR(N23="",E23=0),"",ROUND(N23/E23,6)) | P23: =IF(O23="","",ROUND(O23*FREIGHT_RATE,4)) | Q23: =IF(P23="","",ROUND(P23*E23,2)) | R23: MEASURED
A24: PL-026 | B24: SHP-BG-2024-01 | C24: UC-SKW-SHF-020 | D24: diamond shower filter BG-S01 | E24: 60 | F24: 30 | G24: 2 | H24: 49.5 | I24: 43 | J24: 24.5 | K24: 10 | L24: 11 | M24: =IF(L24="","",L24*G24) | N24: =IF(OR(H24="",G24=""),"",ROUND(H24*I24*J24*G24/1000000,6)) | O24: =IF(OR(N24="",E24=0),"",ROUND(N24/E24,6)) | P24: =IF(O24="","",ROUND(O24*FREIGHT_RATE,4)) | Q24: =IF(P24="","",ROUND(P24*E24,2)) | R24: MEASURED
A25: PL-027 | B25: SHP-BG-2024-01 | C25: UC-SKW-SHF-019 | D25: round shower filter BG-S02 | E25: 90 | F25: 30 | G25: 3 | H25: 45.5 | I25: 42 | J25: 24 | K25: 12 | L25: 12.5 | M25: =IF(L25="","",L25*G25) | N25: =IF(OR(H25="",G25=""),"",ROUND(H25*I25*J25*G25/1000000,6)) | O25: =IF(OR(N25="",E25=0),"",ROUND(N25/E25,6)) | P25: =IF(O25="","",ROUND(O25*FREIGHT_RATE,4)) | Q25: =IF(P25="","",ROUND(P25*E25,2)) | R25: MEASURED
A26: PL-028 | B26: SHP-BG-2024-01 | C26: UC-SKW-SHF-022 | D26: shower filter with window BG-S04 | E26: 20 | F26: 20 | G26: 1 | H26: 37 | I26: 28 | J26: 31.5 | K26: 4.3 | L26: 4.8 | M26: =IF(L26="","",L26*G26) | N26: =IF(OR(H26="",G26=""),"",ROUND(H26*I26*J26*G26/1000000,6)) | O26: =IF(OR(N26="",E26=0),"",ROUND(N26/E26,6)) | P26: =IF(O26="","",ROUND(O26*FREIGHT_RATE,4)) | Q26: =IF(P26="","",ROUND(P26*E26,2)) | R26: MEASURED
A27: PL-029 | B27: SHP-BG-2024-01 | C27: UC-SKW-SHF-021 | D27: aluminum alloy shower filter BG-S06 | E27: 120 | F27: 30 | G27: 4 | H27: 49.5 | I27: 40.5 | J27: 26 | K27: 15.1 | L27: 15.8 | M27: =IF(L27="","",L27*G27) | N27: =IF(OR(H27="",G27=""),"",ROUND(H27*I27*J27*G27/1000000,6)) | O27: =IF(OR(N27="",E27=0),"",ROUND(N27/E27,6)) | P27: =IF(O27="","",ROUND(O27*FREIGHT_RATE,4)) | Q27: =IF(P27="","",ROUND(P27*E27,2)) | R27: MEASURED
A28: PL-030 | B28: SHP-BG-2024-01 | C28: UC-SKW-SHC-023 | D28: shower filter cartridge BG-F02 | E28: 120 | F28: 120 | G28: 1 | H28: 54.5 | I28: 23 | J28: 37 | K28: 16.9 | L28: 17.5 | M28: =IF(L28="","",L28*G28) | N28: =IF(OR(H28="",G28=""),"",ROUND(H28*I28*J28*G28/1000000,6)) | O28: =IF(OR(N28="",E28=0),"",ROUND(N28/E28,6)) | P28: =IF(O28="","",ROUND(O28*FREIGHT_RATE,4)) | Q28: =IF(P28="","",ROUND(P28*E28,2)) | R28: MEASURED
A29: PL-031 | B29: SHP-BG-2024-01 | C29: UC-BOG-FST-016 | D29: new straw filter BG-B12 | E29: 50 | F29: 50 | G29: 1 | H29: 48 | I29: 33 | J29: 23.5 | K29: 6 | L29: 7 | M29: =IF(L29="","",L29*G29) | N29: =IF(OR(H29="",G29=""),"",ROUND(H29*I29*J29*G29/1000000,6)) | O29: =IF(OR(N29="",E29=0),"",ROUND(N29/E29,6)) | P29: =IF(O29="","",ROUND(O29*FREIGHT_RATE,4)) | Q29: =IF(P29="","",ROUND(P29*E29,2)) | R29: MEASURED
A31: PL-E01 | B31: SHP-NEXT | C31: UC-COM-ROS-002 | D31: Commercial RO 1200GPD (carton estimated) | E31: 1 | F31: 1 | G31: 1 | H31: 41 | I31: 25 | J31: 81 | M31: =IF(L31="","",L31*G31) | N31: =IF(OR(H31="",G31=""),"",ROUND(H31*I31*J31*G31/1000000,6)) | O31: =IF(OR(N31="",E31=0),"",ROUND(N31/E31,6)) | P31: =IF(O31="","",ROUND(O31*FREIGHT_RATE,4)) | Q31: =IF(P31="","",ROUND(P31*E31,2)) | R31: COMPARABLE | S31: ESTIMATE. No carton data exists for the 1200GPD unit. Dimensions taken from the RO213 800GPD comparable in the shipping estimate, 1 unit per carton. A twin-pump twin-membrane 1200GPD unit is PHYSICALLY LARGER than an 800G tankless, so 41.51/unit is a FLOOR on freight, not the answer. Replace with real cartons when the supplier confirms.
D32: TOTAL | E32: =SUM(E5:E31) | M32: =SUM(M5:M31) | N32: =SUM(N5:N31) | Q32: =SUM(Q5:Q31)
C34: Coverage | D34: 17 of the 39 parents appear on this packing list. The other 22 have no carton data, so their freight cannot be derived — see BASIS on LANDED_COST_BUILD.

Sheet LANDED_COST_BUILD
A1: LANDED COST BUILD — one row per parent. Landed cost is derived here, never typed into the price sheet.
A2: EXW_USD and LANDED_RECORDED are LOOKUPS into "SKU with PRICES" — one source of truth. Never type a cost here.
A3: FREIGHT_RATE (USD/CBM) | C3: 500 | D3: 400 = Tanzania stock already landed | 500 = new stock inbound
A5: PARENT_SKU | B5: MODEL | C5: STOCK_STATUS | D5: QTY_ON_HAND | E5: COUNT_DATE | F5: VARIANTS | G5: EXW_USD | H5: UNIT_CBM | I5: FREIGHT_USD | J5: ONE_TIME_FEE | K5: ONE_TIME_QTY | L5: ONE_TIME/UNIT | M5: DUTY_CLEAR | N5: LANDED_DERIVED | O5: LANDED_RECORDED | P5: BASIS / WHY
A6: UC-HOU-PHRO-001 | B6: Pure Home | C6: FUTURE | D6: 0 | F6: 1 | G6: =IFERROR(INDEX('SKU with PRICES'!$I:$I,MATCH($A6,'SKU with PRICES'!$H:$H,0)),"") | H6: =IFERROR(SUMIF(LOGISTICS_PL!$C:$C,$A6,LOGISTICS_PL!$N:$N)/SUMIF(LOGISTICS_PL!$C:$C,$A6,LOGISTICS_PL!$E:$E),"") | I6: =IF($H6="","",ROUND($H6*FREIGHT_RATE,2)) | J6: 440 | K6: 30 | L6: =IF(OR($J6="",$K6=""),"",ROUND($J6/$K6,2)) | N6: =IF($G6="","",ROUND($G6+IF($I6="",0,$I6)+IF($L6="",0,$L6)+IF($M6="",0,$M6),2)) | O6: =IFERROR(INDEX('SKU with PRICES'!$J:$J,MATCH($A6,'SKU with PRICES'!$H:$H,0)),"") | P6: =IF($H6="",IF($O6<>"","RECORDED — landed cost typed, no carton data to verify it","NONE — no cost at all; cannot be priced or gated"),IF(COUNTIFS(LOGISTICS_PL!$C:$C,$A6,LOGISTICS_PL!$R:$R,"COMPARABLE")>0,"ESTIMATE — freight from a comparable carton, not this product's own","DERIVED — freight measured from cartons"))
A7: UC-HOU-URO-001 | B7: Ultra Pure | C7: FUTURE | D7: 0 | F7: 1 | G7: =IFERROR(INDEX('SKU with PRICES'!$I:$I,MATCH($A7,'SKU with PRICES'!$H:$H,0)),"") | H7: =IFERROR(SUMIF(LOGISTICS_PL!$C:$C,$A7,LOGISTICS_PL!$N:$N)/SUMIF(LOGISTICS_PL!$C:$C,$A7,LOGISTICS_PL!$E:$E),"") | I7: =IF($H7="","",ROUND($H7*FREIGHT_RATE,2)) | L7: =IF(OR($J7="",$K7=""),"",ROUND($J7/$K7,2)) | N7: =IF($G7="","",ROUND($G7+IF($I7="",0,$I7)+IF($L7="",0,$L7)+IF($M7="",0,$M7),2)) | O7: =IFERROR(INDEX('SKU with PRICES'!$J:$J,MATCH($A7,'SKU with PRICES'!$H:$H,0)),"") | P7: =IF($H7="",IF($O7<>"","RECORDED — landed cost typed, no carton data to verify it","NONE — no cost at all; cannot be priced or gated"),IF(COUNTIFS(LOGISTICS_PL!$C:$C,$A7,LOGISTICS_PL!$R:$R,"COMPARABLE")>0,"ESTIMATE — freight from a comparable carton, not this product's own","DERIVED — freight measured from cartons"))
A8: UC-HOU-URO-002 | B8: Ultra Pure 2 | C8: FUTURE | D8: 0 | F8: 1 | G8: =IFERROR(INDEX('SKU with PRICES'!$I:$I,MATCH($A8,'SKU with PRICES'!$H:$H,0)),"") | H8: =IFERROR(SUMIF(LOGISTICS_PL!$C:$C,$A8,LOGISTICS_PL!$N:$N)/SUMIF(LOGISTICS_PL!$C:$C,$A8,LOGISTICS_PL!$E:$E),"") | I8: =IF($H8="","",ROUND($H8*FREIGHT_RATE,2)) | L8: =IF(OR($J8="",$K8=""),"",ROUND($J8/$K8,2)) | N8: =IF($G8="","",ROUND($G8+IF($I8="",0,$I8)+IF($L8="",0,$L8)+IF($M8="",0,$M8),2)) | O8: =IFERROR(INDEX('SKU with PRICES'!$J:$J,MATCH($A8,'SKU with PRICES'!$H:$H,0)),"") | P8: =IF($H8="",IF($O8<>"","RECORDED — landed cost typed, no carton data to verify it","NONE — no cost at all; cannot be priced or gated"),IF(COUNTIFS(LOGISTICS_PL!$C:$C,$A8,LOGISTICS_PL!$R:$R,"COMPARABLE")>0,"ESTIMATE — freight from a comparable carton, not this product's own","DERIVED — freight measured from cartons"))
A9: UC-HOU-ROS-001 | B9: Pure Blue | C9: FUTURE | D9: 0 | F9: 1 | G9: =IFERROR(INDEX('SKU with PRICES'!$I:$I,MATCH($A9,'SKU with PRICES'!$H:$H,0)),"") | H9: =IFERROR(SUMIF(LOGISTICS_PL!$C:$C,$A9,LOGISTICS_PL!$N:$N)/SUMIF(LOGISTICS_PL!$C:$C,$A9,LOGISTICS_PL!$E:$E),"") | I9: =IF($H9="","",ROUND($H9*FREIGHT_RATE,2)) | L9: =IF(OR($J9="",$K9=""),"",ROUND($J9/$K9,2)) | N9: =IF($G9="","",ROUND($G9+IF($I9="",0,$I9)+IF($L9="",0,$L9)+IF($M9="",0,$M9),2)) | O9: =IFERROR(INDEX('SKU with PRICES'!$J:$J,MATCH($A9,'SKU with PRICES'!$H:$H,0)),"") | P9: =IF($H9="",IF($O9<>"","RECORDED — landed cost typed, no carton data to verify it","NONE — no cost at all; cannot be priced or gated"),IF(COUNTIFS(LOGISTICS_PL!$C:$C,$A9,LOGISTICS_PL!$R:$R,"COMPARABLE")>0,"ESTIMATE — freight from a comparable carton, not this product's own","DERIVED — freight measured from cartons"))
A10: UC-COM-ROS-002 | B10: Aqua Stream 1200D | C10: FUTURE | D10: 0 | F10: 1 | G10: =IFERROR(INDEX('SKU with PRICES'!$I:$I,MATCH($A10,'SKU with PRICES'!$H:$H,0)),"") | H10: =IFERROR(SUMIF(LOGISTICS_PL!$C:$C,$A10,LOGISTICS_PL!$N:$N)/SUMIF(LOGISTICS_PL!$C:$C,$A10,LOGISTICS_PL!$E:$E),"") | I10: =IF($H10="","",ROUND($H10*FREIGHT_RATE,2)) | L10: =IF(OR($J10="",$K10=""),"",ROUND($J10/$K10,2)) | N10: =IF($G10="","",ROUND($G10+IF($I10="",0,$I10)+IF($L10="",0,$L10)+IF($M10="",0,$M10),2)) | O10: =IFERROR(INDEX('SKU with PRICES'!$J:$J,MATCH($A10,'SKU with PRICES'!$H:$H,0)),"") | P10: =IF($H10="",IF($O10<>"","RECORDED — landed cost typed, no carton data to verify it","NONE — no cost at all; cannot be priced or gated"),IF(COUNTIFS(LOGISTICS_PL!$C:$C,$A10,LOGISTICS_PL!$R:$R,"COMPARABLE")>0,"ESTIMATE — freight from a comparable carton, not this product's own","DERIVED — freight measured from cartons"))
A11: UC-HOU-WPF-003 | B11: Pure Shield | C11: FUTURE | D11: 0 | F11: 1 | G11: =IFERROR(INDEX('SKU with PRICES'!$I:$I,MATCH($A11,'SKU with PRICES'!$H:$H,0)),"") | H11: =IFERROR(SUMIF(LOGISTICS_PL!$C:$C,$A11,LOGISTICS_PL!$N:$N)/SUMIF(LOGISTICS_PL!$C:$C,$A11,LOGISTICS_PL!$E:$E),"") | I11: =IF($H11="","",ROUND($H11*FREIGHT_RATE,2)) | J11: 200 | K11: 100 | L11: =IF(OR($J11="",$K11=""),"",ROUND($J11/$K11,2)) | N11: =IF($G11="","",ROUND($G11+IF($I11="",0,$I11)+IF($L11="",0,$L11)+IF($M11="",0,$M11),2)) | O11: =IFERROR(INDEX('SKU with PRICES'!$J:$J,MATCH($A11,'SKU with PRICES'!$H:$H,0)),"") | P11: =IF($H11="",IF($O11<>"","RECORDED — landed cost typed, no carton data to verify it","NONE — no cost at all; cannot be priced or gated"),IF(COUNTIFS(LOGISTICS_PL!$C:$C,$A11,LOGISTICS_PL!$R:$R,"COMPARABLE")>0,"ESTIMATE — freight from a comparable carton, not this product's own","DERIVED — freight measured from cartons"))
A12: UC-HOU-USF-004 | B12: Aqua Drop | C12: FUTURE | D12: 0 | F12: 1 | G12: =IFERROR(INDEX('SKU with PRICES'!$I:$I,MATCH($A12,'SKU with PRICES'!$H:$H,0)),"") | H12: =IFERROR(SUMIF(LOGISTICS_PL!$C:$C,$A12,LOGISTICS_PL!$N:$N)/SUMIF(LOGISTICS_PL!$C:$C,$A12,LOGISTICS_PL!$E:$E),"") | I12: =IF($H12="","",ROUND($H12*FREIGHT_RATE,2)) | L12: =IF(OR($J12="",$K12=""),"",ROUND($J12/$K12,2)) | N12: =IF($G12="","",ROUND($G12+IF($I12="",0,$I12)+IF($L12="",0,$L12)+IF($M12="",0,$M12),2)) | O12: =IFERROR(INDEX('SKU with PRICES'!$J:$J,MATCH($A12,'SKU with PRICES'!$H:$H,0)),"") | P12: =IF($H12="",IF($O12<>"","RECORDED — landed cost typed, no carton data to verify it","NONE — no cost at all; cannot be priced or gated"),IF(COUNTIFS(LOGISTICS_PL!$C:$C,$A12,LOGISTICS_PL!$R:$R,"COMPARABLE")>0,"ESTIMATE — freight from a comparable carton, not this product's own","DERIVED — freight measured from cartons"))
A13: UC-HOU-TAP-005 | B13: Home sweet Home Filter set | C13: FUTURE | D13: 0 | F13: 1 | G13: =IFERROR(INDEX('SKU with PRICES'!$I:$I,MATCH($A13,'SKU with PRICES'!$H:$H,0)),"") | H13: =IFERROR(SUMIF(LOGISTICS_PL!$C:$C,$A13,LOGISTICS_PL!$N:$N)/SUMIF(LOGISTICS_PL!$C:$C,$A13,LOGISTICS_PL!$E:$E),"") | I13: =IF($H13="","",ROUND($H13*FREIGHT_RATE,2)) | L13: =IF(OR($J13="",$K13=""),"",ROUND($J13/$K13,2)) | N13: =IF($G13="","",ROUND($G13+IF($I13="",0,$I13)+IF($L13="",0,$L13)+IF($M13="",0,$M13),2)) | O13: =IFERROR(INDEX('SKU with PRICES'!$J:$J,MATCH($A13,'SKU with PRICES'!$H:$H,0)),"") | P13: =IF($H13="",IF($O13<>"","RECORDED — landed cost typed, no carton data to verify it","NONE — no cost at all; cannot be priced or gated"),IF(COUNTIFS(LOGISTICS_PL!$C:$C,$A13,LOGISTICS_PL!$R:$R,"COMPARABLE")>0,"ESTIMATE — freight from a comparable carton, not this product's own","DERIVED — freight measured from cartons"))
A14: UC-HOU-TAPF-006 | B14: Home sweet Home Filter | C14: IN_STOCK | D14: 93 | E14: 2026-03-12 | F14: 1 | G14: =IFERROR(INDEX('SKU with PRICES'!$I:$I,MATCH($A14,'SKU with PRICES'!$H:$H,0)),"") | H14: =IFERROR(SUMIF(LOGISTICS_PL!$C:$C,$A14,LOGISTICS_PL!$N:$N)/SUMIF(LOGISTICS_PL!$C:$C,$A14,LOGISTICS_PL!$E:$E),"") | I14: =IF($H14="","",ROUND($H14*FREIGHT_RATE,2)) | L14: =IF(OR($J14="",$K14=""),"",ROUND($J14/$K14,2)) | N14: =IF($G14="","",ROUND($G14+IF($I14="",0,$I14)+IF($L14="",0,$L14)+IF($M14="",0,$M14),2)) | O14: =IFERROR(INDEX('SKU with PRICES'!$J:$J,MATCH($A14,'SKU with PRICES'!$H:$H,0)),"") | P14: =IF($H14="",IF($O14<>"","RECORDED — landed cost typed, no carton data to verify it","NONE — no cost at all; cannot be priced or gated"),IF(COUNTIFS(LOGISTICS_PL!$C:$C,$A14,LOGISTICS_PL!$R:$R,"COMPARABLE")>0,"ESTIMATE — freight from a comparable carton, not this product's own","DERIVED — freight measured from cartons"))
A15: UC-HOU-WDFS-006 | B15: Wireless Dispenser Filter Set | C15: IN_STOCK | D15: 58 | E15: 2026-03-12 | F15: 1 | G15: =IFERROR(INDEX('SKU with PRICES'!$I:$I,MATCH($A15,'SKU with PRICES'!$H:$H,0)),"") | H15: =IFERROR(SUMIF(LOGISTICS_PL!$C:$C,$A15,LOGISTICS_PL!$N:$N)/SUMIF(LOGISTICS_PL!$C:$C,$A15,LOGISTICS_PL!$E:$E),"") | I15: =IF($H15="","",ROUND($H15*FREIGHT_RATE,2)) | L15: =IF(OR($J15="",$K15=""),"",ROUND($J15/$K15,2)) | N15: =IF($G15="","",ROUND($G15+IF($I15="",0,$I15)+IF($L15="",0,$L15)+IF($M15="",0,$M15),2)) | O15: =IFERROR(INDEX('SKU with PRICES'!$J:$J,MATCH($A15,'SKU with PRICES'!$H:$H,0)),"") | P15: =IF($H15="",IF($O15<>"","RECORDED — landed cost typed, no carton data to verify it","NONE — no cost at all; cannot be priced or gated"),IF(COUNTIFS(LOGISTICS_PL!$C:$C,$A15,LOGISTICS_PL!$R:$R,"COMPARABLE")>0,"ESTIMATE — freight from a comparable carton, not this product's own","DERIVED — freight measured from cartons"))
A16: UC-HOU-DF-007 | B16: Dispenser Filter | C16: IN_STOCK | D16: 41 | E16: 2026-03-12 | F16: 1 | G16: =IFERROR(INDEX('SKU with PRICES'!$I:$I,MATCH($A16,'SKU with PRICES'!$H:$H,0)),"") | H16: =IFERROR(SUMIF(LOGISTICS_PL!$C:$C,$A16,LOGISTICS_PL!$N:$N)/SUMIF(LOGISTICS_PL!$C:$C,$A16,LOGISTICS_PL!$E:$E),"") | I16: =IF($H16="","",ROUND($H16*FREIGHT_RATE,2)) | L16: =IF(OR($J16="",$K16=""),"",ROUND($J16/$K16,2)) | N16: =IF($G16="","",ROUND($G16+IF($I16="",0,$I16)+IF($L16="",0,$L16)+IF($M16="",0,$M16),2)) | O16: =IFERROR(INDEX('SKU with PRICES'!$J:$J,MATCH($A16,'SKU with PRICES'!$H:$H,0)),"") | P16: =IF($H16="",IF($O16<>"","RECORDED — landed cost typed, no carton data to verify it","NONE — no cost at all; cannot be priced or gated"),IF(COUNTIFS(LOGISTICS_PL!$C:$C,$A16,LOGISTICS_PL!$R:$R,"COMPARABLE")>0,"ESTIMATE — freight from a comparable carton, not this product's own","DERIVED — freight measured from cartons"))
A17: UC-BOG-SSB-008 | B17: Hydra Flux | C17: IN_STOCK | D17: 21 | E17: 2026-03-12 | F17: 4 | G17: =IFERROR(INDEX('SKU with PRICES'!$I:$I,MATCH($A17,'SKU with PRICES'!$H:$H,0)),"") | H17: =IFERROR(SUMIF(LOGISTICS_PL!$C:$C,$A17,LOGISTICS_PL!$N:$N)/SUMIF(LOGISTICS_PL!$C:$C,$A17,LOGISTICS_PL!$E:$E),"") | I17: =IF($H17="","",ROUND($H17*FREIGHT_RATE,2)) | L17: =IF(OR($J17="",$K17=""),"",ROUND($J17/$K17,2)) | N17: =IF($G17="","",ROUND($G17+IF($I17="",0,$I17)+IF($L17="",0,$L17)+IF($M17="",0,$M17),2)) | O17: =IFERROR(INDEX('SKU with PRICES'!$J:$J,MATCH($A17,'SKU with PRICES'!$H:$H,0)),"") | P17: =IF($H17="",IF($O17<>"","RECORDED — landed cost typed, no carton data to verify it","NONE — no cost at all; cannot be priced or gated"),IF(COUNTIFS(LOGISTICS_PL!$C:$C,$A17,LOGISTICS_PL!$R:$R,"COMPARABLE")>0,"ESTIMATE — freight from a comparable carton, not this product's own","DERIVED — freight measured from cartons"))
A18: UC-BOG-TRB-009 | B18: Truva Go | C18: IN_STOCK | D18: 37 | E18: 2026-03-12 | F18: 3 | G18: =IFERROR(INDEX('SKU with PRICES'!$I:$I,MATCH($A18,'SKU with PRICES'!$H:$H,0)),"") | H18: =IFERROR(SUMIF(LOGISTICS_PL!$C:$C,$A18,LOGISTICS_PL!$N:$N)/SUMIF(LOGISTICS_PL!$C:$C,$A18,LOGISTICS_PL!$E:$E),"") | I18: =IF($H18="","",ROUND($H18*FREIGHT_RATE,2)) | L18: =IF(OR($J18="",$K18=""),"",ROUND($J18/$K18,2)) | N18: =IF($G18="","",ROUND($G18+IF($I18="",0,$I18)+IF($L18="",0,$L18)+IF($M18="",0,$M18),2)) | O18: =IFERROR(INDEX('SKU with PRICES'!$J:$J,MATCH($A18,'SKU with PRICES'!$H:$H,0)),"") | P18: =IF($H18="",IF($O18<>"","RECORDED — landed cost typed, no carton data to verify it","NONE — no cost at all; cannot be priced or gated"),IF(COUNTIFS(LOGISTICS_PL!$C:$C,$A18,LOGISTICS_PL!$R:$R,"COMPARABLE")>0,"ESTIMATE — freight from a comparable carton, not this product's own","DERIVED — freight measured from cartons"))
A19: UC-BOG-TRB-010 | B19: Viva Drop | C19: IN_STOCK | D19: 70 | E19: 2026-03-12 | F19: 2 | G19: =IFERROR(INDEX('SKU with PRICES'!$I:$I,MATCH($A19,'SKU with PRICES'!$H:$H,0)),"") | H19: =IFERROR(SUMIF(LOGISTICS_PL!$C:$C,$A19,LOGISTICS_PL!$N:$N)/SUMIF(LOGISTICS_PL!$C:$C,$A19,LOGISTICS_PL!$E:$E),"") | I19: =IF($H19="","",ROUND($H19*FREIGHT_RATE,2)) | L19: =IF(OR($J19="",$K19=""),"",ROUND($J19/$K19,2)) | N19: =IF($G19="","",ROUND($G19+IF($I19="",0,$I19)+IF($L19="",0,$L19)+IF($M19="",0,$M19),2)) | O19: =IFERROR(INDEX('SKU with PRICES'!$J:$J,MATCH($A19,'SKU with PRICES'!$H:$H,0)),"") | P19: =IF($H19="",IF($O19<>"","RECORDED — landed cost typed, no carton data to verify it","NONE — no cost at all; cannot be priced or gated"),IF(COUNTIFS(LOGISTICS_PL!$C:$C,$A19,LOGISTICS_PL!$R:$R,"COMPARABLE")>0,"ESTIMATE — freight from a comparable carton, not this product's own","DERIVED — freight measured from cartons"))
A20: UC-BOG-TRB-011 | B20: Gym Buddy | C20: IN_STOCK | D20: 24 | E20: 2026-03-12 | F20: 2 | G20: =IFERROR(INDEX('SKU with PRICES'!$I:$I,MATCH($A20,'SKU with PRICES'!$H:$H,0)),"") | H20: =IFERROR(SUMIF(LOGISTICS_PL!$C:$C,$A20,LOGISTICS_PL!$N:$N)/SUMIF(LOGISTICS_PL!$C:$C,$A20,LOGISTICS_PL!$E:$E),"") | I20: =IF($H20="","",ROUND($H20*FREIGHT_RATE,2)) | L20: =IF(OR($J20="",$K20=""),"",ROUND($J20/$K20,2)) | N20: =IF($G20="","",ROUND($G20+IF($I20="",0,$I20)+IF($L20="",0,$L20)+IF($M20="",0,$M20),2)) | O20: =IFERROR(INDEX('SKU with PRICES'!$J:$J,MATCH($A20,'SKU with PRICES'!$H:$H,0)),"") | P20: =IF($H20="",IF($O20<>"","RECORDED — landed cost typed, no carton data to verify it","NONE — no cost at all; cannot be priced or gated"),IF(COUNTIFS(LOGISTICS_PL!$C:$C,$A20,LOGISTICS_PL!$R:$R,"COMPARABLE")>0,"ESTIMATE — freight from a comparable carton, not this product's own","DERIVED — freight measured from cartons"))
A21: UC-BOG-FLB-012 | B21: Timbo | C21: IN_STOCK | D21: 3 | E21: 2026-03-12 | F21: 1 | G21: =IFERROR(INDEX('SKU with PRICES'!$I:$I,MATCH($A21,'SKU with PRICES'!$H:$H,0)),"") | H21: =IFERROR(SUMIF(LOGISTICS_PL!$C:$C,$A21,LOGISTICS_PL!$N:$N)/SUMIF(LOGISTICS_PL!$C:$C,$A21,LOGISTICS_PL!$E:$E),"") | I21: =IF($H21="","",ROUND($H21*FREIGHT_RATE,2)) | L21: =IF(OR($J21="",$K21=""),"",ROUND($J21/$K21,2)) | N21: =IF($G21="","",ROUND($G21+IF($I21="",0,$I21)+IF($L21="",0,$L21)+IF($M21="",0,$M21),2)) | O21: =IFERROR(INDEX('SKU with PRICES'!$J:$J,MATCH($A21,'SKU with PRICES'!$H:$H,0)),"") | P21: =IF($H21="",IF($O21<>"","RECORDED — landed cost typed, no carton data to verify it","NONE — no cost at all; cannot be priced or gated"),IF(COUNTIFS(LOGISTICS_PL!$C:$C,$A21,LOGISTICS_PL!$R:$R,"COMPARABLE")>0,"ESTIMATE — freight from a comparable carton, not this product's own","DERIVED — freight measured from cartons"))
A22: UC-BOG-SQB-013 | B22: Breeze | C22: FUTURE | D22: 0 | F22: 1 | G22: =IFERROR(INDEX('SKU with PRICES'!$I:$I,MATCH($A22,'SKU with PRICES'!$H:$H,0)),"") | H22: =IFERROR(SUMIF(LOGISTICS_PL!$C:$C,$A22,LOGISTICS_PL!$N:$N)/SUMIF(LOGISTICS_PL!$C:$C,$A22,LOGISTICS_PL!$E:$E),"") | I22: =IF($H22="","",ROUND($H22*FREIGHT_RATE,2)) | L22: =IF(OR($J22="",$K22=""),"",ROUND($J22/$K22,2)) | N22: =IF($G22="","",ROUND($G22+IF($I22="",0,$I22)+IF($L22="",0,$L22)+IF($M22="",0,$M22),2)) | O22: =IFERROR(INDEX('SKU with PRICES'!$J:$J,MATCH($A22,'SKU with PRICES'!$H:$H,0)),"") | P22: =IF($H22="",IF($O22<>"","RECORDED — landed cost typed, no carton data to verify it","NONE — no cost at all; cannot be priced or gated"),IF(COUNTIFS(LOGISTICS_PL!$C:$C,$A22,LOGISTICS_PL!$R:$R,"COMPARABLE")>0,"ESTIMATE — freight from a comparable carton, not this product's own","DERIVED — freight measured from cartons"))
A23: UC-BOG-SQB-014 | B23: Flex | C23: IN_STOCK | D23: 76 | E23: 2026-03-12 | F23: 2 | G23: =IFERROR(INDEX('SKU with PRICES'!$I:$I,MATCH($A23,'SKU with PRICES'!$H:$H,0)),"") | H23: =IFERROR(SUMIF(LOGISTICS_PL!$C:$C,$A23,LOGISTICS_PL!$N:$N)/SUMIF(LOGISTICS_PL!$C:$C,$A23,LOGISTICS_PL!$E:$E),"") | I23: =IF($H23="","",ROUND($H23*FREIGHT_RATE,2)) | L23: =IF(OR($J23="",$K23=""),"",ROUND($J23/$K23,2)) | N23: =IF($G23="","",ROUND($G23+IF($I23="",0,$I23)+IF($L23="",0,$L23)+IF($M23="",0,$M23),2)) | O23: =IFERROR(INDEX('SKU with PRICES'!$J:$J,MATCH($A23,'SKU with PRICES'!$H:$H,0)),"") | P23: =IF($H23="",IF($O23<>"","RECORDED — landed cost typed, no carton data to verify it","NONE — no cost at all; cannot be priced or gated"),IF(COUNTIFS(LOGISTICS_PL!$C:$C,$A23,LOGISTICS_PL!$R:$R,"COMPARABLE")>0,"ESTIMATE — freight from a comparable carton, not this product's own","DERIVED — freight measured from cartons"))
A24: UC-BOG-UF-100 | B24: Ultra Fold | C24: FUTURE | D24: 0 | F24: 1 | G24: =IFERROR(INDEX('SKU with PRICES'!$I:$I,MATCH($A24,'SKU with PRICES'!$H:$H,0)),"") | H24: =IFERROR(SUMIF(LOGISTICS_PL!$C:$C,$A24,LOGISTICS_PL!$N:$N)/SUMIF(LOGISTICS_PL!$C:$C,$A24,LOGISTICS_PL!$E:$E),"") | I24: =IF($H24="","",ROUND($H24*FREIGHT_RATE,2)) | L24: =IF(OR($J24="",$K24=""),"",ROUND($J24/$K24,2)) | N24: =IF($G24="","",ROUND($G24+IF($I24="",0,$I24)+IF($L24="",0,$L24)+IF($M24="",0,$M24),2)) | O24: =IFERROR(INDEX('SKU with PRICES'!$J:$J,MATCH($A24,'SKU with PRICES'!$H:$H,0)),"") | P24: =IF($H24="",IF($O24<>"","RECORDED — landed cost typed, no carton data to verify it","NONE — no cost at all; cannot be priced or gated"),IF(COUNTIFS(LOGISTICS_PL!$C:$C,$A24,LOGISTICS_PL!$R:$R,"COMPARABLE")>0,"ESTIMATE — freight from a comparable carton, not this product's own","DERIVED — freight measured from cartons"))
A25: UC-BOG-FCA-015 | B25: Filter Squeeze Ahlstrom | C25: IN_STOCK | D25: 351 | E25: 2026-03-12 | F25: 1 | G25: =IFERROR(INDEX('SKU with PRICES'!$I:$I,MATCH($A25,'SKU with PRICES'!$H:$H,0)),"") | H25: =IFERROR(SUMIF(LOGISTICS_PL!$C:$C,$A25,LOGISTICS_PL!$N:$N)/SUMIF(LOGISTICS_PL!$C:$C,$A25,LOGISTICS_PL!$E:$E),"") | I25: =IF($H25="","",ROUND($H25*FREIGHT_RATE,2)) | L25: =IF(OR($J25="",$K25=""),"",ROUND($J25/$K25,2)) | N25: =IF($G25="","",ROUND($G25+IF($I25="",0,$I25)+IF($L25="",0,$L25)+IF($M25="",0,$M25),2)) | O25: =IFERROR(INDEX('SKU with PRICES'!$J:$J,MATCH($A25,'SKU with PRICES'!$H:$H,0)),"") | P25: =IF($H25="",IF($O25<>"","RECORDED — landed cost typed, no carton data to verify it","NONE — no cost at all; cannot be priced or gated"),IF(COUNTIFS(LOGISTICS_PL!$C:$C,$A25,LOGISTICS_PL!$R:$R,"COMPARABLE")>0,"ESTIMATE — freight from a comparable carton, not this product's own","DERIVED — freight measured from cartons"))
A26: UC-BOG-FST-016 | B26: Survivor | C26: IN_STOCK | D26: 34 | E26: 2026-03-12 | F26: 2 | G26: =IFERROR(INDEX('SKU with PRICES'!$I:$I,MATCH($A26,'SKU with PRICES'!$H:$H,0)),"") | H26: =IFERROR(SUMIF(LOGISTICS_PL!$C:$C,$A26,LOGISTICS_PL!$N:$N)/SUMIF(LOGISTICS_PL!$C:$C,$A26,LOGISTICS_PL!$E:$E),"") | I26: =IF($H26="","",ROUND($H26*FREIGHT_RATE,2)) | L26: =IF(OR($J26="",$K26=""),"",ROUND($J26/$K26,2)) | N26: =IF($G26="","",ROUND($G26+IF($I26="",0,$I26)+IF($L26="",0,$L26)+IF($M26="",0,$M26),2)) | O26: =IFERROR(INDEX('SKU with PRICES'!$J:$J,MATCH($A26,'SKU with PRICES'!$H:$H,0)),"") | P26: =IF($H26="",IF($O26<>"","RECORDED — landed cost typed, no carton data to verify it","NONE — no cost at all; cannot be priced or gated"),IF(COUNTIFS(LOGISTICS_PL!$C:$C,$A26,LOGISTICS_PL!$R:$R,"COMPARABLE")>0,"ESTIMATE — freight from a comparable carton, not this product's own","DERIVED — freight measured from cartons"))
A27: UC-BOG-FCS-017 | B27: Survivor filter | C27: FUTURE | D27: 0 | F27: 1 | G27: =IFERROR(INDEX('SKU with PRICES'!$I:$I,MATCH($A27,'SKU with PRICES'!$H:$H,0)),"") | H27: =IFERROR(SUMIF(LOGISTICS_PL!$C:$C,$A27,LOGISTICS_PL!$N:$N)/SUMIF(LOGISTICS_PL!$C:$C,$A27,LOGISTICS_PL!$E:$E),"") | I27: =IF($H27="","",ROUND($H27*FREIGHT_RATE,2)) | L27: =IF(OR($J27="",$K27=""),"",ROUND($J27/$K27,2)) | N27: =IF($G27="","",ROUND($G27+IF($I27="",0,$I27)+IF($L27="",0,$L27)+IF($M27="",0,$M27),2)) | O27: =IFERROR(INDEX('SKU with PRICES'!$J:$J,MATCH($A27,'SKU with PRICES'!$H:$H,0)),"") | P27: =IF($H27="",IF($O27<>"","RECORDED — landed cost typed, no carton data to verify it","NONE — no cost at all; cannot be priced or gated"),IF(COUNTIFS(LOGISTICS_PL!$C:$C,$A27,LOGISTICS_PL!$R:$R,"COMPARABLE")>0,"ESTIMATE — freight from a comparable carton, not this product's own","DERIVED — freight measured from cartons"))
A28: UC-BOG-SHL-018 | B28: Shell | C28: IN_STOCK | D28: 50 | E28: 2026-03-12 | F28: 1 | G28: =IFERROR(INDEX('SKU with PRICES'!$I:$I,MATCH($A28,'SKU with PRICES'!$H:$H,0)),"") | H28: =IFERROR(SUMIF(LOGISTICS_PL!$C:$C,$A28,LOGISTICS_PL!$N:$N)/SUMIF(LOGISTICS_PL!$C:$C,$A28,LOGISTICS_PL!$E:$E),"") | I28: =IF($H28="","",ROUND($H28*FREIGHT_RATE,2)) | L28: =IF(OR($J28="",$K28=""),"",ROUND($J28/$K28,2)) | N28: =IF($G28="","",ROUND($G28+IF($I28="",0,$I28)+IF($L28="",0,$L28)+IF($M28="",0,$M28),2)) | O28: =IFERROR(INDEX('SKU with PRICES'!$J:$J,MATCH($A28,'SKU with PRICES'!$H:$H,0)),"") | P28: =IF($H28="",IF($O28<>"","RECORDED — landed cost typed, no carton data to verify it","NONE — no cost at all; cannot be priced or gated"),IF(COUNTIFS(LOGISTICS_PL!$C:$C,$A28,LOGISTICS_PL!$R:$R,"COMPARABLE")>0,"ESTIMATE — freight from a comparable carton, not this product's own","DERIVED — freight measured from cartons"))
A29: UC-SKW-SHF-019 | B29: Chanel | C29: IN_STOCK | D29: 60 | E29: 2026-03-12 | F29: 1 | G29: =IFERROR(INDEX('SKU with PRICES'!$I:$I,MATCH($A29,'SKU with PRICES'!$H:$H,0)),"") | H29: =IFERROR(SUMIF(LOGISTICS_PL!$C:$C,$A29,LOGISTICS_PL!$N:$N)/SUMIF(LOGISTICS_PL!$C:$C,$A29,LOGISTICS_PL!$E:$E),"") | I29: =IF($H29="","",ROUND($H29*FREIGHT_RATE,2)) | L29: =IF(OR($J29="",$K29=""),"",ROUND($J29/$K29,2)) | N29: =IF($G29="","",ROUND($G29+IF($I29="",0,$I29)+IF($L29="",0,$L29)+IF($M29="",0,$M29),2)) | O29: =IFERROR(INDEX('SKU with PRICES'!$J:$J,MATCH($A29,'SKU with PRICES'!$H:$H,0)),"") | P29: =IF($H29="",IF($O29<>"","RECORDED — landed cost typed, no carton data to verify it","NONE — no cost at all; cannot be priced or gated"),IF(COUNTIFS(LOGISTICS_PL!$C:$C,$A29,LOGISTICS_PL!$R:$R,"COMPARABLE")>0,"ESTIMATE — freight from a comparable carton, not this product's own","DERIVED — freight measured from cartons"))
A30: UC-SKW-SHF-020 | B30: Derma Care | C30: IN_STOCK | D30: 50 | E30: 2026-03-12 | F30: 1 | G30: =IFERROR(INDEX('SKU with PRICES'!$I:$I,MATCH($A30,'SKU with PRICES'!$H:$H,0)),"") | H30: =IFERROR(SUMIF(LOGISTICS_PL!$C:$C,$A30,LOGISTICS_PL!$N:$N)/SUMIF(LOGISTICS_PL!$C:$C,$A30,LOGISTICS_PL!$E:$E),"") | I30: =IF($H30="","",ROUND($H30*FREIGHT_RATE,2)) | L30: =IF(OR($J30="",$K30=""),"",ROUND($J30/$K30,2)) | N30: =IF($G30="","",ROUND($G30+IF($I30="",0,$I30)+IF($L30="",0,$L30)+IF($M30="",0,$M30),2)) | O30: =IFERROR(INDEX('SKU with PRICES'!$J:$J,MATCH($A30,'SKU with PRICES'!$H:$H,0)),"") | P30: =IF($H30="",IF($O30<>"","RECORDED — landed cost typed, no carton data to verify it","NONE — no cost at all; cannot be priced or gated"),IF(COUNTIFS(LOGISTICS_PL!$C:$C,$A30,LOGISTICS_PL!$R:$R,"COMPARABLE")>0,"ESTIMATE — freight from a comparable carton, not this product's own","DERIVED — freight measured from cartons"))
A31: UC-SKW-SHF-021 | B31: J'adore | C31: IN_STOCK | D31: 65 | E31: 2026-03-12 | F31: 1 | G31: =IFERROR(INDEX('SKU with PRICES'!$I:$I,MATCH($A31,'SKU with PRICES'!$H:$H,0)),"") | H31: =IFERROR(SUMIF(LOGISTICS_PL!$C:$C,$A31,LOGISTICS_PL!$N:$N)/SUMIF(LOGISTICS_PL!$C:$C,$A31,LOGISTICS_PL!$E:$E),"") | I31: =IF($H31="","",ROUND($H31*FREIGHT_RATE,2)) | L31: =IF(OR($J31="",$K31=""),"",ROUND($J31/$K31,2)) | N31: =IF($G31="","",ROUND($G31+IF($I31="",0,$I31)+IF($L31="",0,$L31)+IF($M31="",0,$M31),2)) | O31: =IFERROR(INDEX('SKU with PRICES'!$J:$J,MATCH($A31,'SKU with PRICES'!$H:$H,0)),"") | P31: =IF($H31="",IF($O31<>"","RECORDED — landed cost typed, no carton data to verify it","NONE — no cost at all; cannot be priced or gated"),IF(COUNTIFS(LOGISTICS_PL!$C:$C,$A31,LOGISTICS_PL!$R:$R,"COMPARABLE")>0,"ESTIMATE — freight from a comparable carton, not this product's own","DERIVED — freight measured from cartons"))
A32: UC-SKW-SHF-022 | B32: Pure Drop | C32: IN_STOCK | D32: 10 | E32: 2026-03-12 | F32: 1 | G32: =IFERROR(INDEX('SKU with PRICES'!$I:$I,MATCH($A32,'SKU with PRICES'!$H:$H,0)),"") | H32: =IFERROR(SUMIF(LOGISTICS_PL!$C:$C,$A32,LOGISTICS_PL!$N:$N)/SUMIF(LOGISTICS_PL!$C:$C,$A32,LOGISTICS_PL!$E:$E),"") | I32: =IF($H32="","",ROUND($H32*FREIGHT_RATE,2)) | L32: =IF(OR($J32="",$K32=""),"",ROUND($J32/$K32,2)) | N32: =IF($G32="","",ROUND($G32+IF($I32="",0,$I32)+IF($L32="",0,$L32)+IF($M32="",0,$M32),2)) | O32: =IFERROR(INDEX('SKU with PRICES'!$J:$J,MATCH($A32,'SKU with PRICES'!$H:$H,0)),"") | P32: =IF($H32="",IF($O32<>"","RECORDED — landed cost typed, no carton data to verify it","NONE — no cost at all; cannot be priced or gated"),IF(COUNTIFS(LOGISTICS_PL!$C:$C,$A32,LOGISTICS_PL!$R:$R,"COMPARABLE")>0,"ESTIMATE — freight from a comparable carton, not this product's own","DERIVED — freight measured from cartons"))
A33: UC-SKW-SHC-023 | B33: Shower Filter | C33: IN_STOCK | D33: 94 | E33: 2026-03-12 | F33: 1 | G33: =IFERROR(INDEX('SKU with PRICES'!$I:$I,MATCH($A33,'SKU with PRICES'!$H:$H,0)),"") | H33: =IFERROR(SUMIF(LOGISTICS_PL!$C:$C,$A33,LOGISTICS_PL!$N:$N)/SUMIF(LOGISTICS_PL!$C:$C,$A33,LOGISTICS_PL!$E:$E),"") | I33: =IF($H33="","",ROUND($H33*FREIGHT_RATE,2)) | L33: =IF(OR($J33="",$K33=""),"",ROUND($J33/$K33,2)) | N33: =IF($G33="","",ROUND($G33+IF($I33="",0,$I33)+IF($L33="",0,$L33)+IF($M33="",0,$M33),2)) | O33: =IFERROR(INDEX('SKU with PRICES'!$J:$J,MATCH($A33,'SKU with PRICES'!$H:$H,0)),"") | P33: =IF($H33="",IF($O33<>"","RECORDED — landed cost typed, no carton data to verify it","NONE — no cost at all; cannot be priced or gated"),IF(COUNTIFS(LOGISTICS_PL!$C:$C,$A33,LOGISTICS_PL!$R:$R,"COMPARABLE")>0,"ESTIMATE — freight from a comparable carton, not this product's own","DERIVED — freight measured from cartons"))
A34: UC-SKW-DFS-024 | B34: Derma Flux | C34: IN_STOCK | D34: 2 | E34: 2026-03-12 | F34: 1 | G34: =IFERROR(INDEX('SKU with PRICES'!$I:$I,MATCH($A34,'SKU with PRICES'!$H:$H,0)),"") | H34: =IFERROR(SUMIF(LOGISTICS_PL!$C:$C,$A34,LOGISTICS_PL!$N:$N)/SUMIF(LOGISTICS_PL!$C:$C,$A34,LOGISTICS_PL!$E:$E),"") | I34: =IF($H34="","",ROUND($H34*FREIGHT_RATE,2)) | L34: =IF(OR($J34="",$K34=""),"",ROUND($J34/$K34,2)) | N34: =IF($G34="","",ROUND($G34+IF($I34="",0,$I34)+IF($L34="",0,$L34)+IF($M34="",0,$M34),2)) | O34: =IFERROR(INDEX('SKU with PRICES'!$J:$J,MATCH($A34,'SKU with PRICES'!$H:$H,0)),"") | P34: =IF($H34="",IF($O34<>"","RECORDED — landed cost typed, no carton data to verify it","NONE — no cost at all; cannot be priced or gated"),IF(COUNTIFS(LOGISTICS_PL!$C:$C,$A34,LOGISTICS_PL!$R:$R,"COMPARABLE")>0,"ESTIMATE — freight from a comparable carton, not this product's own","DERIVED — freight measured from cartons"))
A35: UC-SKW-DFS-025 | B35: Derma Flux | C35: FUTURE | D35: 0 | F35: 1 | G35: =IFERROR(INDEX('SKU with PRICES'!$I:$I,MATCH($A35,'SKU with PRICES'!$H:$H,0)),"") | H35: =IFERROR(SUMIF(LOGISTICS_PL!$C:$C,$A35,LOGISTICS_PL!$N:$N)/SUMIF(LOGISTICS_PL!$C:$C,$A35,LOGISTICS_PL!$E:$E),"") | I35: =IF($H35="","",ROUND($H35*FREIGHT_RATE,2)) | L35: =IF(OR($J35="",$K35=""),"",ROUND($J35/$K35,2)) | N35: =IF($G35="","",ROUND($G35+IF($I35="",0,$I35)+IF($L35="",0,$L35)+IF($M35="",0,$M35),2)) | O35: =IFERROR(INDEX('SKU with PRICES'!$J:$J,MATCH($A35,'SKU with PRICES'!$H:$H,0)),"") | P35: =IF($H35="",IF($O35<>"","RECORDED — landed cost typed, no carton data to verify it","NONE — no cost at all; cannot be priced or gated"),IF(COUNTIFS(LOGISTICS_PL!$C:$C,$A35,LOGISTICS_PL!$R:$R,"COMPARABLE")>0,"ESTIMATE — freight from a comparable carton, not this product's own","DERIVED — freight measured from cartons"))
A36: UC-SKW-DFS-026 | B36: Derma Flux | C36: FUTURE | D36: 0 | F36: 1 | G36: =IFERROR(INDEX('SKU with PRICES'!$I:$I,MATCH($A36,'SKU with PRICES'!$H:$H,0)),"") | H36: =IFERROR(SUMIF(LOGISTICS_PL!$C:$C,$A36,LOGISTICS_PL!$N:$N)/SUMIF(LOGISTICS_PL!$C:$C,$A36,LOGISTICS_PL!$E:$E),"") | I36: =IF($H36="","",ROUND($H36*FREIGHT_RATE,2)) | L36: =IF(OR($J36="",$K36=""),"",ROUND($J36/$K36,2)) | N36: =IF($G36="","",ROUND($G36+IF($I36="",0,$I36)+IF($L36="",0,$L36)+IF($M36="",0,$M36),2)) | O36: =IFERROR(INDEX('SKU with PRICES'!$J:$J,MATCH($A36,'SKU with PRICES'!$H:$H,0)),"") | P36: =IF($H36="",IF($O36<>"","RECORDED — landed cost typed, no carton data to verify it","NONE — no cost at all; cannot be priced or gated"),IF(COUNTIFS(LOGISTICS_PL!$C:$C,$A36,LOGISTICS_PL!$R:$R,"COMPARABLE")>0,"ESTIMATE — freight from a comparable carton, not this product's own","DERIVED — freight measured from cartons"))
A37: UC-SKW-DFO-027 | B37: Derma Flux Fiiter | C37: IN_STOCK | D37: 2 | E37: 2026-03-12 | F37: 1 | G37: =IFERROR(INDEX('SKU with PRICES'!$I:$I,MATCH($A37,'SKU with PRICES'!$H:$H,0)),"") | H37: =IFERROR(SUMIF(LOGISTICS_PL!$C:$C,$A37,LOGISTICS_PL!$N:$N)/SUMIF(LOGISTICS_PL!$C:$C,$A37,LOGISTICS_PL!$E:$E),"") | I37: =IF($H37="","",ROUND($H37*FREIGHT_RATE,2)) | L37: =IF(OR($J37="",$K37=""),"",ROUND($J37/$K37,2)) | N37: =IF($G37="","",ROUND($G37+IF($I37="",0,$I37)+IF($L37="",0,$L37)+IF($M37="",0,$M37),2)) | O37: =IFERROR(INDEX('SKU with PRICES'!$J:$J,MATCH($A37,'SKU with PRICES'!$H:$H,0)),"") | P37: =IF($H37="",IF($O37<>"","RECORDED — landed cost typed, no carton data to verify it","NONE — no cost at all; cannot be priced or gated"),IF(COUNTIFS(LOGISTICS_PL!$C:$C,$A37,LOGISTICS_PL!$R:$R,"COMPARABLE")>0,"ESTIMATE — freight from a comparable carton, not this product's own","DERIVED — freight measured from cartons"))
A38: UC-HOU-ROP-PP | B38: RO Replacement | C38: FUTURE | D38: 0 | F38: 1 | G38: =IFERROR(INDEX('SKU with PRICES'!$I:$I,MATCH($A38,'SKU with PRICES'!$H:$H,0)),"") | H38: =IFERROR(SUMIF(LOGISTICS_PL!$C:$C,$A38,LOGISTICS_PL!$N:$N)/SUMIF(LOGISTICS_PL!$C:$C,$A38,LOGISTICS_PL!$E:$E),"") | I38: =IF($H38="","",ROUND($H38*FREIGHT_RATE,2)) | L38: =IF(OR($J38="",$K38=""),"",ROUND($J38/$K38,2)) | N38: =IF($G38="","",ROUND($G38+IF($I38="",0,$I38)+IF($L38="",0,$L38)+IF($M38="",0,$M38),2)) | O38: =IFERROR(INDEX('SKU with PRICES'!$J:$J,MATCH($A38,'SKU with PRICES'!$H:$H,0)),"") | P38: =IF($H38="",IF($O38<>"","RECORDED — landed cost typed, no carton data to verify it","NONE — no cost at all; cannot be priced or gated"),IF(COUNTIFS(LOGISTICS_PL!$C:$C,$A38,LOGISTICS_PL!$R:$R,"COMPARABLE")>0,"ESTIMATE — freight from a comparable carton, not this product's own","DERIVED — freight measured from cartons"))
A39: UC-HOU-ROP-UDF | B39: RO Replacement | C39: FUTURE | D39: 0 | F39: 1 | G39: =IFERROR(INDEX('SKU with PRICES'!$I:$I,MATCH($A39,'SKU with PRICES'!$H:$H,0)),"") | H39: =IFERROR(SUMIF(LOGISTICS_PL!$C:$C,$A39,LOGISTICS_PL!$N:$N)/SUMIF(LOGISTICS_PL!$C:$C,$A39,LOGISTICS_PL!$E:$E),"") | I39: =IF($H39="","",ROUND($H39*FREIGHT_RATE,2)) | L39: =IF(OR($J39="",$K39=""),"",ROUND($J39/$K39,2)) | N39: =IF($G39="","",ROUND($G39+IF($I39="",0,$I39)+IF($L39="",0,$L39)+IF($M39="",0,$M39),2)) | O39: =IFERROR(INDEX('SKU with PRICES'!$J:$J,MATCH($A39,'SKU with PRICES'!$H:$H,0)),"") | P39: =IF($H39="",IF($O39<>"","RECORDED — landed cost typed, no carton data to verify it","NONE — no cost at all; cannot be priced or gated"),IF(COUNTIFS(LOGISTICS_PL!$C:$C,$A39,LOGISTICS_PL!$R:$R,"COMPARABLE")>0,"ESTIMATE — freight from a comparable carton, not this product's own","DERIVED — freight measured from cartons"))
A40: UC-HOU-ROP-CTO | B40: RO Replacement | C40: FUTURE | D40: 0 | F40: 1 | G40: =IFERROR(INDEX('SKU with PRICES'!$I:$I,MATCH($A40,'SKU with PRICES'!$H:$H,0)),"") | H40: =IFERROR(SUMIF(LOGISTICS_PL!$C:$C,$A40,LOGISTICS_PL!$N:$N)/SUMIF(LOGISTICS_PL!$C:$C,$A40,LOGISTICS_PL!$E:$E),"") | I40: =IF($H40="","",ROUND($H40*FREIGHT_RATE,2)) | L40: =IF(OR($J40="",$K40=""),"",ROUND($J40/$K40,2)) | N40: =IF($G40="","",ROUND($G40+IF($I40="",0,$I40)+IF($L40="",0,$L40)+IF($M40="",0,$M40),2)) | O40: =IFERROR(INDEX('SKU with PRICES'!$J:$J,MATCH($A40,'SKU with PRICES'!$H:$H,0)),"") | P40: =IF($H40="",IF($O40<>"","RECORDED — landed cost typed, no carton data to verify it","NONE — no cost at all; cannot be priced or gated"),IF(COUNTIFS(LOGISTICS_PL!$C:$C,$A40,LOGISTICS_PL!$R:$R,"COMPARABLE")>0,"ESTIMATE — freight from a comparable carton, not this product's own","DERIVED — freight measured from cartons"))
A41: UC-HOU-ROM-100g | B41: RO Replacement | C41: FUTURE | D41: 0 | F41: 1 | G41: =IFERROR(INDEX('SKU with PRICES'!$I:$I,MATCH($A41,'SKU with PRICES'!$H:$H,0)),"") | H41: =IFERROR(SUMIF(LOGISTICS_PL!$C:$C,$A41,LOGISTICS_PL!$N:$N)/SUMIF(LOGISTICS_PL!$C:$C,$A41,LOGISTICS_PL!$E:$E),"") | I41: =IF($H41="","",ROUND($H41*FREIGHT_RATE,2)) | L41: =IF(OR($J41="",$K41=""),"",ROUND($J41/$K41,2)) | N41: =IF($G41="","",ROUND($G41+IF($I41="",0,$I41)+IF($L41="",0,$L41)+IF($M41="",0,$M41),2)) | O41: =IFERROR(INDEX('SKU with PRICES'!$J:$J,MATCH($A41,'SKU with PRICES'!$H:$H,0)),"") | P41: =IF($H41="",IF($O41<>"","RECORDED — landed cost typed, no carton data to verify it","NONE — no cost at all; cannot be priced or gated"),IF(COUNTIFS(LOGISTICS_PL!$C:$C,$A41,LOGISTICS_PL!$R:$R,"COMPARABLE")>0,"ESTIMATE — freight from a comparable carton, not this product's own","DERIVED — freight measured from cartons"))
A42: UC-HOU-RO-YMT33 | B42: RO Replacement | C42: FUTURE | D42: 0 | F42: 1 | G42: =IFERROR(INDEX('SKU with PRICES'!$I:$I,MATCH($A42,'SKU with PRICES'!$H:$H,0)),"") | H42: =IFERROR(SUMIF(LOGISTICS_PL!$C:$C,$A42,LOGISTICS_PL!$N:$N)/SUMIF(LOGISTICS_PL!$C:$C,$A42,LOGISTICS_PL!$E:$E),"") | I42: =IF($H42="","",ROUND($H42*FREIGHT_RATE,2)) | L42: =IF(OR($J42="",$K42=""),"",ROUND($J42/$K42,2)) | N42: =IF($G42="","",ROUND($G42+IF($I42="",0,$I42)+IF($L42="",0,$L42)+IF($M42="",0,$M42),2)) | O42: =IFERROR(INDEX('SKU with PRICES'!$J:$J,MATCH($A42,'SKU with PRICES'!$H:$H,0)),"") | P42: =IF($H42="",IF($O42<>"","RECORDED — landed cost typed, no carton data to verify it","NONE — no cost at all; cannot be priced or gated"),IF(COUNTIFS(LOGISTICS_PL!$C:$C,$A42,LOGISTICS_PL!$R:$R,"COMPARABLE")>0,"ESTIMATE — freight from a comparable carton, not this product's own","DERIVED — freight measured from cartons"))
A43: UC-HOU-RO-CBT33 | B43: RO Replacement | C43: FUTURE | D43: 0 | F43: 1 | G43: =IFERROR(INDEX('SKU with PRICES'!$I:$I,MATCH($A43,'SKU with PRICES'!$H:$H,0)),"") | H43: =IFERROR(SUMIF(LOGISTICS_PL!$C:$C,$A43,LOGISTICS_PL!$N:$N)/SUMIF(LOGISTICS_PL!$C:$C,$A43,LOGISTICS_PL!$E:$E),"") | I43: =IF($H43="","",ROUND($H43*FREIGHT_RATE,2)) | L43: =IF(OR($J43="",$K43=""),"",ROUND($J43/$K43,2)) | N43: =IF($G43="","",ROUND($G43+IF($I43="",0,$I43)+IF($L43="",0,$L43)+IF($M43="",0,$M43),2)) | O43: =IFERROR(INDEX('SKU with PRICES'!$J:$J,MATCH($A43,'SKU with PRICES'!$H:$H,0)),"") | P43: =IF($H43="",IF($O43<>"","RECORDED — landed cost typed, no carton data to verify it","NONE — no cost at all; cannot be priced or gated"),IF(COUNTIFS(LOGISTICS_PL!$C:$C,$A43,LOGISTICS_PL!$R:$R,"COMPARABLE")>0,"ESTIMATE — freight from a comparable carton, not this product's own","DERIVED — freight measured from cartons"))
A44: UC-BOG-ECO-ECF1 | B44: Ecosmart Filter | C44: FUTURE | D44: 0 | F44: 1 | G44: =IFERROR(INDEX('SKU with PRICES'!$I:$I,MATCH($A44,'SKU with PRICES'!$H:$H,0)),"") | H44: =IFERROR(SUMIF(LOGISTICS_PL!$C:$C,$A44,LOGISTICS_PL!$N:$N)/SUMIF(LOGISTICS_PL!$C:$C,$A44,LOGISTICS_PL!$E:$E),"") | I44: =IF($H44="","",ROUND($H44*FREIGHT_RATE,2)) | L44: =IF(OR($J44="",$K44=""),"",ROUND($J44/$K44,2)) | N44: =IF($G44="","",ROUND($G44+IF($I44="",0,$I44)+IF($L44="",0,$L44)+IF($M44="",0,$M44),2)) | O44: =IFERROR(INDEX('SKU with PRICES'!$J:$J,MATCH($A44,'SKU with PRICES'!$H:$H,0)),"") | P44: =IF($H44="",IF($O44<>"","RECORDED — landed cost typed, no carton data to verify it","NONE — no cost at all; cannot be priced or gated"),IF(COUNTIFS(LOGISTICS_PL!$C:$C,$A44,LOGISTICS_PL!$R:$R,"COMPARABLE")>0,"ESTIMATE — freight from a comparable carton, not this product's own","DERIVED — freight measured from cartons"))
A45: UC-HOU-ROT-029 | B45: RO Mini Tank | C45: FUTURE | D45: 0 | F45: 1 | G45: =IFERROR(INDEX('SKU with PRICES'!$I:$I,MATCH($A45,'SKU with PRICES'!$H:$H,0)),"") | H45: =IFERROR(SUMIF(LOGISTICS_PL!$C:$C,$A45,LOGISTICS_PL!$N:$N)/SUMIF(LOGISTICS_PL!$C:$C,$A45,LOGISTICS_PL!$E:$E),"") | I45: =IF($H45="","",ROUND($H45*FREIGHT_RATE,2)) | L45: =IF(OR($J45="",$K45=""),"",ROUND($J45/$K45,2)) | N45: =IF($G45="","",ROUND($G45+IF($I45="",0,$I45)+IF($L45="",0,$L45)+IF($M45="",0,$M45),2)) | O45: =IFERROR(INDEX('SKU with PRICES'!$J:$J,MATCH($A45,'SKU with PRICES'!$H:$H,0)),"") | P45: =IF($H45="",IF($O45<>"","RECORDED — landed cost typed, no carton data to verify it","NONE — no cost at all; cannot be priced or gated"),IF(COUNTIFS(LOGISTICS_PL!$C:$C,$A45,LOGISTICS_PL!$R:$R,"COMPARABLE")>0,"ESTIMATE — freight from a comparable carton, not this product's own","DERIVED — freight measured from cartons"))
B47: TOTAL | D47: =SUM(D6:D44) | G47: =SUM(G6:G44) | N47: =SUM(N6:N44)

Sheet INBOUND_SHIPMENT
A1: INBOUND SHIPMENT — every future-stock arrival gets a row here before it gets stock.
A3: SHIPMENT_ID | B3: SUPPLIER | C3: INCOTERM | D3: MODE | E3: RATE USD/CBM | F3: TOTAL_CBM | G3: FREIGHT_USD | H3: ETD | I3: ETA | J3: STATUS | K3: EVIDENCE / NOTE
A4: SHP-BG-2024-01 | B4: Guangzhou Begreat Smart Life Co., Ltd. | C4: DDP | D4: LCL | E4: 400 | F4: 3.0404 | G4: 1216 | H4: 2024-08 | I4: 2024-12 | J4: LANDED | K4: PI BGE422408081911, 08 Aug 2024. Freight 1,216 / 3.0404 CBM = 399.95/CBM — matches the 400 rate exactly.
A5: SHP-NEXT | B5: (to be confirmed) | C5: TBC | D5: LCL | E5: 500 | G5: =IF(F4="","",ROUND(F4*E4,2)) | J5: PLANNED | K5: Shipping Estimate, Sep 2026. Same 3.0404 CBM at 500/CBM would be 1,520.20 — a 25% freight increase on identical cargo.
B7: Items quoted outside the packing list (no carton data):
A8: MFR_MODEL | B8: PARENT_SKU | C8: QTY | D8: EXW_USD | E8: ONE_TIME_FEE | F8: ONE_TIME/UNIT | G8: FREIGHT/UNIT | H8: LANDED/UNIT | I8: TOTAL | J8: BASIS | K8: NOTE
A9: ER800-4 Auto flush | B9: UC-HOU-PHRO-001 | C9: 30 | D9: 108 | E9: 440 | F9: 14.67 | G9: 32 | H9: 154.67 | I9: 4640 | J9: RECORDED | K9: Freight/unit of 32.00 is implied by the recorded landed cost of 140, not measured. A comparable RO carton (41x25x81, 25/ctn) gives 41.51 at 500/CBM — 30% higher.
A10: ET-2S Electric Pitcher | B10: UC-HOU-WPF-003 | C10: 100 | D10: 44 | E10: 200 | F10: 2 | G10: 11 | H10: 57 | I10: 5700 | J10: RECORDED | K10: Implied 11.00/unit = 0.022 CBM at 500/CBM. Plausible for a pitcher carton, but still implied, not measured.
A11: MT-0.5 Mini Water Tank | B11: (no SKU issued) | C11: 30 | D11: 9 | E11: 0 | F11: 0 | J11: NONE | K11: No carton data, no landed cost, and no SKU. Cannot be costed, cannot be counted, cannot be sold. Needs a SKU from the master before anything else.

Sheet SKU with PRICES
A1: Category | B1: Pricing Category | C1: Manufactuere Model SKU | D1: Descriptions | E1: License Certification | F1: Product | G1: Model Name | H1: SKU | I1: producution Cost | J1: Landing Cost | K1: Cost_KES | L1: Retail_KES | M1: Pychological Pricing | N1: Retail_USD | O1: Wholesale_KES | P1: Wholesale_USD | Q1: Corporate_KES | R1: Corporate_USD | S1: Influencer_KES | T1: Influencer_USD | U1: Quantity | V1: REVENUE
A2: Home & Utility | B2: Core | C2: ER800-4 Auto flush | D2: 800G tankless RO with TDS display and Filter life light reminder with auto flushing funtion with Wifi + App control | E2: Certification : SGS/ROHS/FDA | F2: Smart RO Tankless | G2: Pure Home | H2: UC-HOU-PHRO-001 | I2: 108 | J2: 140 | K2: =IF(NOT(ISNUMBER(Table1[[#This Row],[Landing Cost]])),"",Table1[[#This Row],[Landing Cost]]*FX_USD_KES) | L2: =IF(NOT(ISNUMBER(Table1[[#This Row],[Cost_KES]])),"",Table1[[#This Row],[Cost_KES]]*MULT_RETAIL_CORE) | M2: =IF(NOT(ISNUMBER(Table1[[#This Row],[Retail_KES]])),"",IF(Table1[[#This Row],[Retail_KES]]<=0,"",IF(Table1[[#This Row],[Retail_KES]]>=10000, ROUNDUP(Table1[[#This Row],[Retail_KES]]/1000,0)*1000-10, IF(Table1[[#This Row],[Retail_KES]]>=3000, ROUNDUP(Table1[[#This Row],[Retail_KES]]/100,0)*100-1, ROUNDUP(Table1[[#This Row],[Retail_KES]]/10,0)*10-0.01)))) | N2: =IFERROR(Table1[[#This Row],[Pychological Pricing]]/FX_USD_KES,"") | O2: =IF(NOT(ISNUMBER(Table1[[#This Row],[Retail_KES]])),"",IF(Table1[[#This Row],[Retail_KES]]<=0,"",IF(Table1[[#This Row],[Retail_KES]]>=10000, ROUNDUP(Table1[[#This Row],[Retail_KES]]*RATE_WHOLESALE/1000,0)*1000-10, IF(Table1[[#This Row],[Retail_KES]]>=3000, ROUNDUP(Table1[[#This Row],[Retail_KES]]*RATE_WHOLESALE/100,0)*100-1, ROUNDUP(Table1[[#This Row],[Retail_KES]]*RATE_WHOLESALE/10,0)*10-0.01)))) | P2: =IFERROR(Table1[[#This Row],[Wholesale_KES]]/FX_USD_KES,"") | Q2: =IF(NOT(ISNUMBER(Table1[[#This Row],[Retail_KES]])),"",IF(Table1[[#This Row],[Retail_KES]]<=0,"",IF(Table1[[#This Row],[Retail_KES]]>=10000, ROUNDUP(Table1[[#This Row],[Retail_KES]]*RATE_CORPORATE/1000,0)*1000-10, IF(Table1[[#This Row],[Retail_KES]]>=3000, ROUNDUP(Table1[[#This Row],[Retail_KES]]*RATE_CORPORATE/100,0)*100-1, ROUNDUP(Table1[[#This Row],[Retail_KES]]*RATE_CORPORATE/10,0)*10-0.01)))) | R2: =IFERROR(Table1[[#This Row],[Corporate_KES]]/FX_USD_KES,"") | S2: =IF(NOT(ISNUMBER(Table1[[#This Row],[Retail_KES]])),"",IF(Table1[[#This Row],[Retail_KES]]<=0,"",IF(Table1[[#This Row],[Retail_KES]]>=10000, ROUNDUP(Table1[[#This Row],[Retail_KES]]*RATE_INFLUENCER/1000,0)*1000-10, IF(Table1[[#This Row],[Retail_KES]]>=3000, ROUNDUP(Table1[[#This Row],[Retail_KES]]*RATE_INFLUENCER/100,0)*100-1, ROUNDUP(Table1[[#This Row],[Retail_KES]]*RATE_INFLUENCER/10,0)*10-0.01)))) | T2: =IFERROR(Table1[[#This Row],[Influencer_KES]]/FX_USD_KES,"") | U2: 0 | V2: =IF(NOT(ISNUMBER(Table1[[#This Row],[Pychological Pricing]])),"",Table1[[#This Row],[Quantity]]*Table1[[#This Row],[Pychological Pricing]])
A3: Home & Utility | B3: Core | C3: MF1080-S | D3: Faucet Body SS304 Pre-installed Filter * 1 (Carbon+Lead remove) Aerator (vary by model)Escutcheon PlateRed Line (hot water) Blue Line (cold water) Optional Quick-Connect Components Waterproof Rubber Ring Threaded Metal Pipe Rubber Gasket Metal Gasket Mounting Nut Screws * 2 | E3: Certification : SGS/ROHS/FDA | F3: Single Faucet Filter | G3: Ultra Pure | H3: UC-HOU-URO-001 | I3: 30 | J3: 60 | K3: =IF(NOT(ISNUMBER(Table1[[#This Row],[Landing Cost]])),"",Table1[[#This Row],[Landing Cost]]*FX_USD_KES) | L3: =IF(NOT(ISNUMBER(Table1[[#This Row],[Cost_KES]])),"",Table1[[#This Row],[Cost_KES]]*MULT_RETAIL_CORE) | M3: =IF(NOT(ISNUMBER(Table1[[#This Row],[Retail_KES]])),"",IF(Table1[[#This Row],[Retail_KES]]<=0,"",IF(Table1[[#This Row],[Retail_KES]]>=10000, ROUNDUP(Table1[[#This Row],[Retail_KES]]/1000,0)*1000-10, IF(Table1[[#This Row],[Retail_KES]]>=3000, ROUNDUP(Table1[[#This Row],[Retail_KES]]/100,0)*100-1, ROUNDUP(Table1[[#This Row],[Retail_KES]]/10,0)*10-0.01)))) | N3: =IFERROR(Table1[[#This Row],[Pychological Pricing]]/FX_USD_KES,"") | O3: =IF(NOT(ISNUMBER(Table1[[#This Row],[Retail_KES]])),"",IF(Table1[[#This Row],[Retail_KES]]<=0,"",IF(Table1[[#This Row],[Retail_KES]]>=10000, ROUNDUP(Table1[[#This Row],[Retail_KES]]*RATE_WHOLESALE/1000,0)*1000-10, IF(Table1[[#This Row],[Retail_KES]]>=3000, ROUNDUP(Table1[[#This Row],[Retail_KES]]*RATE_WHOLESALE/100,0)*100-1, ROUNDUP(Table1[[#This Row],[Retail_KES]]*RATE_WHOLESALE/10,0)*10-0.01)))) | P3: =IFERROR(Table1[[#This Row],[Wholesale_KES]]/FX_USD_KES,"") | Q3: =IF(NOT(ISNUMBER(Table1[[#This Row],[Retail_KES]])),"",IF(Table1[[#This Row],[Retail_KES]]<=0,"",IF(Table1[[#This Row],[Retail_KES]]>=10000, ROUNDUP(Table1[[#This Row],[Retail_KES]]*RATE_CORPORATE/1000,0)*1000-10, IF(Table1[[#This Row],[Retail_KES]]>=3000, ROUNDUP(Table1[[#This Row],[Retail_KES]]*RATE_CORPORATE/100,0)*100-1, ROUNDUP(Table1[[#This Row],[Retail_KES]]*RATE_CORPORATE/10,0)*10-0.01)))) | R3: =IFERROR(Table1[[#This Row],[Corporate_KES]]/FX_USD_KES,"") | S3: =IF(NOT(ISNUMBER(Table1[[#This Row],[Retail_KES]])),"",IF(Table1[[#This Row],[Retail_KES]]<=0,"",IF(Table1[[#This Row],[Retail_KES]]>=10000, ROUNDUP(Table1[[#This Row],[Retail_KES]]*RATE_INFLUENCER/1000,0)*1000-10, IF(Table1[[#This Row],[Retail_KES]]>=3000, ROUNDUP(Table1[[#This Row],[Retail_KES]]*RATE_INFLUENCER/100,0)*100-1, ROUNDUP(Table1[[#This Row],[Retail_KES]]*RATE_INFLUENCER/10,0)*10-0.01)))) | T3: =IFERROR(Table1[[#This Row],[Influencer_KES]]/FX_USD_KES,"") | U3: 0 | V3: =IF(NOT(ISNUMBER(Table1[[#This Row],[Pychological Pricing]])),"",Table1[[#This Row],[Quantity]]*Table1[[#This Row],[Pychological Pricing]])
A4: Home & Utility | B4: Core | C4: MF1080-D | D4: Pre-installed Filter * 1 (Carbon+Lead remove) Aerator (vary by model)Escutcheon PlateRed Line (hot water) Blue Line (cold water) Optional Quick-Connect Components Waterproof Rubber Ring Threaded Metal Pipe Rubber Gasket Metal Gasket Mounting Nut Screws * 2 | E4: Certification : SGS/ROHS/FDA | F4: Double Inline Faucet Filter | G4: Ultra Pure 2 | H4: UC-HOU-URO-002 | I4: 34 | J4: 65 | K4: =IF(NOT(ISNUMBER(Table1[[#This Row],[Landing Cost]])),"",Table1[[#This Row],[Landing Cost]]*FX_USD_KES) | L4: =IF(NOT(ISNUMBER(Table1[[#This Row],[Cost_KES]])),"",Table1[[#This Row],[Cost_KES]]*MULT_RETAIL_CORE) | M4: =IF(NOT(ISNUMBER(Table1[[#This Row],[Retail_KES]])),"",IF(Table1[[#This Row],[Retail_KES]]<=0,"",IF(Table1[[#This Row],[Retail_KES]]>=10000, ROUNDUP(Table1[[#This Row],[Retail_KES]]/1000,0)*1000-10, IF(Table1[[#This Row],[Retail_KES]]>=3000, ROUNDUP(Table1[[#This Row],[Retail_KES]]/100,0)*100-1, ROUNDUP(Table1[[#This Row],[Retail_KES]]/10,0)*10-0.01)))) | N4: =IFERROR(Table1[[#This Row],[Pychological Pricing]]/FX_USD_KES,"") | O4: =IF(NOT(ISNUMBER(Table1[[#This Row],[Retail_KES]])),"",IF(Table1[[#This Row],[Retail_KES]]<=0,"",IF(Table1[[#This Row],[Retail_KES]]>=10000, ROUNDUP(Table1[[#This Row],[Retail_KES]]*RATE_WHOLESALE/1000,0)*1000-10, IF(Table1[[#This Row],[Retail_KES]]>=3000, ROUNDUP(Table1[[#This Row],[Retail_KES]]*RATE_WHOLESALE/100,0)*100-1, ROUNDUP(Table1[[#This Row],[Retail_KES]]*RATE_WHOLESALE/10,0)*10-0.01)))) | P4: =IFERROR(Table1[[#This Row],[Wholesale_KES]]/FX_USD_KES,"") | Q4: =IF(NOT(ISNUMBER(Table1[[#This Row],[Retail_KES]])),"",IF(Table1[[#This Row],[Retail_KES]]<=0,"",IF(Table1[[#This Row],[Retail_KES]]>=10000, ROUNDUP(Table1[[#This Row],[Retail_KES]]*RATE_CORPORATE/1000,0)*1000-10, IF(Table1[[#This Row],[Retail_KES]]>=3000, ROUNDUP(Table1[[#This Row],[Retail_KES]]*RATE_CORPORATE/100,0)*100-1, ROUNDUP(Table1[[#This Row],[Retail_KES]]*RATE_CORPORATE/10,0)*10-0.01)))) | R4: =IFERROR(Table1[[#This Row],[Corporate_KES]]/FX_USD_KES,"") | S4: =IF(NOT(ISNUMBER(Table1[[#This Row],[Retail_KES]])),"",IF(Table1[[#This Row],[Retail_KES]]<=0,"",IF(Table1[[#This Row],[Retail_KES]]>=10000, ROUNDUP(Table1[[#This Row],[Retail_KES]]*RATE_INFLUENCER/1000,0)*1000-10, IF(Table1[[#This Row],[Retail_KES]]>=3000, ROUNDUP(Table1[[#This Row],[Retail_KES]]*RATE_INFLUENCER/100,0)*100-1, ROUNDUP(Table1[[#This Row],[Retail_KES]]*RATE_INFLUENCER/10,0)*10-0.01)))) | T4: =IFERROR(Table1[[#This Row],[Influencer_KES]]/FX_USD_KES,"") | V4: =IF(NOT(ISNUMBER(Table1[[#This Row],[Pychological Pricing]])),"",Table1[[#This Row],[Quantity]]*Table1[[#This Row],[Pychological Pricing]])
A5: Home & Utility | B5: Core | C5: 6 stage plastic stand bracket RO unit | D5: 6 stage plastic stand bracket RO unit *6 stage: PP+GAC+CTO+RO+T33+Mineral *Booster pump *Reverse osmosis(RO) membrane *Purifying capacity:100G *Power adapter *304 Stainless steel drinking faucet *3.2G pressure water tank *Auto flush/Manual flush *Metal inflow valve *under sink / wall hanging *Applicable water: 0.1-0.4Mpa/5-38 ℃ *Applicable voltage: 110-220V | E5: Certification : SGS/ROHS/FDA | F5: 6-stage RO transparent | G5: Pure Blue | H5: UC-HOU-ROS-001 | I5: 47 | J5: 101.72 | K5: =IF(NOT(ISNUMBER(Table1[[#This Row],[Landing Cost]])),"",Table1[[#This Row],[Landing Cost]]*FX_USD_KES) | L5: =IF(NOT(ISNUMBER(Table1[[#This Row],[Cost_KES]])),"",Table1[[#This Row],[Cost_KES]]*MULT_RETAIL_CORE) | M5: =IF(NOT(ISNUMBER(Table1[[#This Row],[Retail_KES]])),"",IF(Table1[[#This Row],[Retail_KES]]<=0,"",IF(Table1[[#This Row],[Retail_KES]]>=10000, ROUNDUP(Table1[[#This Row],[Retail_KES]]/1000,0)*1000-10, IF(Table1[[#This Row],[Retail_KES]]>=3000, ROUNDUP(Table1[[#This Row],[Retail_KES]]/100,0)*100-1, ROUNDUP(Table1[[#This Row],[Retail_KES]]/10,0)*10-0.01)))) | N5: =IFERROR(Table1[[#This Row],[Pychological Pricing]]/FX_USD_KES,"") | O5: =IF(NOT(ISNUMBER(Table1[[#This Row],[Retail_KES]])),"",IF(Table1[[#This Row],[Retail_KES]]<=0,"",IF(Table1[[#This Row],[Retail_KES]]>=10000, ROUNDUP(Table1[[#This Row],[Retail_KES]]*RATE_WHOLESALE/1000,0)*1000-10, IF(Table1[[#This Row],[Retail_KES]]>=3000, ROUNDUP(Table1[[#This Row],[Retail_KES]]*RATE_WHOLESALE/100,0)*100-1, ROUNDUP(Table1[[#This Row],[Retail_KES]]*RATE_WHOLESALE/10,0)*10-0.01)))) | P5: =IFERROR(Table1[[#This Row],[Wholesale_KES]]/FX_USD_KES,"") | Q5: =IF(NOT(ISNUMBER(Table1[[#This Row],[Retail_KES]])),"",IF(Table1[[#This Row],[Retail_KES]]<=0,"",IF(Table1[[#This Row],[Retail_KES]]>=10000, ROUNDUP(Table1[[#This Row],[Retail_KES]]*RATE_CORPORATE/1000,0)*1000-10, IF(Table1[[#This Row],[Retail_KES]]>=3000, ROUNDUP(Table1[[#This Row],[Retail_KES]]*RATE_CORPORATE/100,0)*100-1, ROUNDUP(Table1[[#This Row],[Retail_KES]]*RATE_CORPORATE/10,0)*10-0.01)))) | R5: =IFERROR(Table1[[#This Row],[Corporate_KES]]/FX_USD_KES,"") | S5: =IF(NOT(ISNUMBER(Table1[[#This Row],[Retail_KES]])),"",IF(Table1[[#This Row],[Retail_KES]]<=0,"",IF(Table1[[#This Row],[Retail_KES]]>=10000, ROUNDUP(Table1[[#This Row],[Retail_KES]]*RATE_INFLUENCER/1000,0)*1000-10, IF(Table1[[#This Row],[Retail_KES]]>=3000, ROUNDUP(Table1[[#This Row],[Retail_KES]]*RATE_INFLUENCER/100,0)*100-1, ROUNDUP(Table1[[#This Row],[Retail_KES]]*RATE_INFLUENCER/10,0)*10-0.01)))) | T5: =IFERROR(Table1[[#This Row],[Influencer_KES]]/FX_USD_KES,"") | U5: 0 | V5: =IF(NOT(ISNUMBER(Table1[[#This Row],[Pychological Pricing]])),"",Table1[[#This Row],[Quantity]]*Table1[[#This Row],[Pychological Pricing]])
A6: Commercial | B6: Core | C6: Commercial RO Water Filter System 1200GPD | D6: 1200 GPD RO System Digital Display Dual Booster Pumps Dual RO Membranes Dual Power Adapters 304 Stainless Steel Faucet | E6: Certification : SGS/ROHS/FDA | F6: Commercial RO System | G6: Aqua Stream 1200D | H6: UC-COM-ROS-002 | I6: 140 | J6: =ROUND($I6+0.083025*FREIGHT_RATE,2) | K6: =IF(NOT(ISNUMBER(Table1[[#This Row],[Landing Cost]])),"",Table1[[#This Row],[Landing Cost]]*FX_USD_KES) | L6: =IF(NOT(ISNUMBER(Table1[[#This Row],[Cost_KES]])),"",Table1[[#This Row],[Cost_KES]]*MULT_RETAIL_CORE) | M6: =IF(NOT(ISNUMBER(Table1[[#This Row],[Retail_KES]])),"",IF(Table1[[#This Row],[Retail_KES]]<=0,"",IF(Table1[[#This Row],[Retail_KES]]>=10000, ROUNDUP(Table1[[#This Row],[Retail_KES]]/1000,0)*1000-10, IF(Table1[[#This Row],[Retail_KES]]>=3000, ROUNDUP(Table1[[#This Row],[Retail_KES]]/100,0)*100-1, ROUNDUP(Table1[[#This Row],[Retail_KES]]/10,0)*10-0.01)))) | N6: =IFERROR(Table1[[#This Row],[Pychological Pricing]]/FX_USD_KES,"") | O6: =IF(NOT(ISNUMBER(Table1[[#This Row],[Retail_KES]])),"",IF(Table1[[#This Row],[Retail_KES]]<=0,"",IF(Table1[[#This Row],[Retail_KES]]>=10000, ROUNDUP(Table1[[#This Row],[Retail_KES]]*RATE_WHOLESALE/1000,0)*1000-10, IF(Table1[[#This Row],[Retail_KES]]>=3000, ROUNDUP(Table1[[#This Row],[Retail_KES]]*RATE_WHOLESALE/100,0)*100-1, ROUNDUP(Table1[[#This Row],[Retail_KES]]*RATE_WHOLESALE/10,0)*10-0.01)))) | P6: =IFERROR(Table1[[#This Row],[Wholesale_KES]]/FX_USD_KES,"") | Q6: =IF(NOT(ISNUMBER(Table1[[#This Row],[Retail_KES]])),"",IF(Table1[[#This Row],[Retail_KES]]<=0,"",IF(Table1[[#This Row],[Retail_KES]]>=10000, ROUNDUP(Table1[[#This Row],[Retail_KES]]*RATE_CORPORATE/1000,0)*1000-10, IF(Table1[[#This Row],[Retail_KES]]>=3000, ROUNDUP(Table1[[#This Row],[Retail_KES]]*RATE_CORPORATE/100,0)*100-1, ROUNDUP(Table1[[#This Row],[Retail_KES]]*RATE_CORPORATE/10,0)*10-0.01)))) | R6: =IFERROR(Table1[[#This Row],[Corporate_KES]]/FX_USD_KES,"") | S6: =IF(NOT(ISNUMBER(Table1[[#This Row],[Retail_KES]])),"",IF(Table1[[#This Row],[Retail_KES]]<=0,"",IF(Table1[[#This Row],[Retail_KES]]>=10000, ROUNDUP(Table1[[#This Row],[Retail_KES]]*RATE_INFLUENCER/1000,0)*1000-10, IF(Table1[[#This Row],[Retail_KES]]>=3000, ROUNDUP(Table1[[#This Row],[Retail_KES]]*RATE_INFLUENCER/100,0)*100-1, ROUNDUP(Table1[[#This Row],[Retail_KES]]*RATE_INFLUENCER/10,0)*10-0.01)))) | T6: =IFERROR(Table1[[#This Row],[Influencer_KES]]/FX_USD_KES,"") | U6: 0 | V6: =IF(NOT(ISNUMBER(Table1[[#This Row],[Pychological Pricing]])),"",Table1[[#This Row],[Quantity]]*Table1[[#This Row],[Pychological Pricing]]) | AD6: Manufacturers Model code (Packing List SKU)
A7: Home & Utility | B7: Core | C7: ET-2S | D7: Electric Water Filter Pitcher 2 stage water filters 1st stage: 1 micron carbon block with lead remove 2st stage: 1 micron carbon block with lead remove | E7: Certification : SGS/ROHS/FDA | F7: Wireless Pitcher Filter | G7: Pure Shield | H7: UC-HOU-WPF-003 | I7: 44 | J7: 55 | K7: =IF(NOT(ISNUMBER(Table1[[#This Row],[Landing Cost]])),"",Table1[[#This Row],[Landing Cost]]*FX_USD_KES) | L7: =IF(NOT(ISNUMBER(Table1[[#This Row],[Cost_KES]])),"",Table1[[#This Row],[Cost_KES]]*MULT_RETAIL_CORE) | M7: =IF(NOT(ISNUMBER(Table1[[#This Row],[Retail_KES]])),"",IF(Table1[[#This Row],[Retail_KES]]<=0,"",IF(Table1[[#This Row],[Retail_KES]]>=10000, ROUNDUP(Table1[[#This Row],[Retail_KES]]/1000,0)*1000-10, IF(Table1[[#This Row],[Retail_KES]]>=3000, ROUNDUP(Table1[[#This Row],[Retail_KES]]/100,0)*100-1, ROUNDUP(Table1[[#This Row],[Retail_KES]]/10,0)*10-0.01)))) | N7: =IFERROR(Table1[[#This Row],[Pychological Pricing]]/FX_USD_KES,"") | O7: =IF(NOT(ISNUMBER(Table1[[#This Row],[Retail_KES]])),"",IF(Table1[[#This Row],[Retail_KES]]<=0,"",IF(Table1[[#This Row],[Retail_KES]]>=10000, ROUNDUP(Table1[[#This Row],[Retail_KES]]*RATE_WHOLESALE/1000,0)*1000-10, IF(Table1[[#This Row],[Retail_KES]]>=3000, ROUNDUP(Table1[[#This Row],[Retail_KES]]*RATE_WHOLESALE/100,0)*100-1, ROUNDUP(Table1[[#This Row],[Retail_KES]]*RATE_WHOLESALE/10,0)*10-0.01)))) | P7: =IFERROR(Table1[[#This Row],[Wholesale_KES]]/FX_USD_KES,"") | Q7: =IF(NOT(ISNUMBER(Table1[[#This Row],[Retail_KES]])),"",IF(Table1[[#This Row],[Retail_KES]]<=0,"",IF(Table1[[#This Row],[Retail_KES]]>=10000, ROUNDUP(Table1[[#This Row],[Retail_KES]]*RATE_CORPORATE/1000,0)*1000-10, IF(Table1[[#This Row],[Retail_KES]]>=3000, ROUNDUP(Table1[[#This Row],[Retail_KES]]*RATE_CORPORATE/100,0)*100-1, ROUNDUP(Table1[[#This Row],[Retail_KES]]*RATE_CORPORATE/10,0)*10-0.01)))) | R7: =IFERROR(Table1[[#This Row],[Corporate_KES]]/FX_USD_KES,"") | S7: =IF(NOT(ISNUMBER(Table1[[#This Row],[Retail_KES]])),"",IF(Table1[[#This Row],[Retail_KES]]<=0,"",IF(Table1[[#This Row],[Retail_KES]]>=10000, ROUNDUP(Table1[[#This Row],[Retail_KES]]*RATE_INFLUENCER/1000,0)*1000-10, IF(Table1[[#This Row],[Retail_KES]]>=3000, ROUNDUP(Table1[[#This Row],[Retail_KES]]*RATE_INFLUENCER/100,0)*100-1, ROUNDUP(Table1[[#This Row],[Retail_KES]]*RATE_INFLUENCER/10,0)*10-0.01)))) | T7: =IFERROR(Table1[[#This Row],[Influencer_KES]]/FX_USD_KES,"") | U7: 0 | V7: =IF(NOT(ISNUMBER(Table1[[#This Row],[Pychological Pricing]])),"",Table1[[#This Row],[Quantity]]*Table1[[#This Row],[Pychological Pricing]]) | W7: Forex Rate USD | AD7: 740ml stainless steel water filter bottle BG-B01
A8: Home & Utility | B8: Core | C8: ER800-4 Auto flush | E8: Certification : SGS/ROHS/FDA | F8: Undersink 3-stage filter | G8: Aqua Drop | H8: UC-HOU-USF-004 | J8: 50.32 | K8: =IF(NOT(ISNUMBER(Table1[[#This Row],[Landing Cost]])),"",Table1[[#This Row],[Landing Cost]]*FX_USD_KES) | L8: =IF(NOT(ISNUMBER(Table1[[#This Row],[Cost_KES]])),"",Table1[[#This Row],[Cost_KES]]*MULT_RETAIL_CORE) | M8: =IF(NOT(ISNUMBER(Table1[[#This Row],[Retail_KES]])),"",IF(Table1[[#This Row],[Retail_KES]]<=0,"",IF(Table1[[#This Row],[Retail_KES]]>=10000, ROUNDUP(Table1[[#This Row],[Retail_KES]]/1000,0)*1000-10, IF(Table1[[#This Row],[Retail_KES]]>=3000, ROUNDUP(Table1[[#This Row],[Retail_KES]]/100,0)*100-1, ROUNDUP(Table1[[#This Row],[Retail_KES]]/10,0)*10-0.01)))) | N8: =IFERROR(Table1[[#This Row],[Pychological Pricing]]/FX_USD_KES,"") | O8: =IF(NOT(ISNUMBER(Table1[[#This Row],[Retail_KES]])),"",IF(Table1[[#This Row],[Retail_KES]]<=0,"",IF(Table1[[#This Row],[Retail_KES]]>=10000, ROUNDUP(Table1[[#This Row],[Retail_KES]]*RATE_WHOLESALE/1000,0)*1000-10, IF(Table1[[#This Row],[Retail_KES]]>=3000, ROUNDUP(Table1[[#This Row],[Retail_KES]]*RATE_WHOLESALE/100,0)*100-1, ROUNDUP(Table1[[#This Row],[Retail_KES]]*RATE_WHOLESALE/10,0)*10-0.01)))) | P8: =IFERROR(Table1[[#This Row],[Wholesale_KES]]/FX_USD_KES,"") | Q8: =IF(NOT(ISNUMBER(Table1[[#This Row],[Retail_KES]])),"",IF(Table1[[#This Row],[Retail_KES]]<=0,"",IF(Table1[[#This Row],[Retail_KES]]>=10000, ROUNDUP(Table1[[#This Row],[Retail_KES]]*RATE_CORPORATE/1000,0)*1000-10, IF(Table1[[#This Row],[Retail_KES]]>=3000, ROUNDUP(Table1[[#This Row],[Retail_KES]]*RATE_CORPORATE/100,0)*100-1, ROUNDUP(Table1[[#This Row],[Retail_KES]]*RATE_CORPORATE/10,0)*10-0.01)))) | R8: =IFERROR(Table1[[#This Row],[Corporate_KES]]/FX_USD_KES,"") | S8: =IF(NOT(ISNUMBER(Table1[[#This Row],[Retail_KES]])),"",IF(Table1[[#This Row],[Retail_KES]]<=0,"",IF(Table1[[#This Row],[Retail_KES]]>=10000, ROUNDUP(Table1[[#This Row],[Retail_KES]]*RATE_INFLUENCER/1000,0)*1000-10, IF(Table1[[#This Row],[Retail_KES]]>=3000, ROUNDUP(Table1[[#This Row],[Retail_KES]]*RATE_INFLUENCER/100,0)*100-1, ROUNDUP(Table1[[#This Row],[Retail_KES]]*RATE_INFLUENCER/10,0)*10-0.01)))) | T8: =IFERROR(Table1[[#This Row],[Influencer_KES]]/FX_USD_KES,"") | V8: =IF(NOT(ISNUMBER(Table1[[#This Row],[Pychological Pricing]])),"",Table1[[#This Row],[Quantity]]*Table1[[#This Row],[Pychological Pricing]]) | W8: =FX_USD_KES | AD8: 769ml tritan water filter bottle BG-B02
A9: Home & Utility | B9: Core | C9: ultra filter faucet BG-T01U | D9: Stage1: Non-woven fabric Stage2: Carbon fiber Stage3: Granular Carbon Stage4: Ultrafiltration membrane Function: Remove sand, rust and other particulate impurities, absorb residual chlorine and other organic compounds, color,odor, and remove bacteria . lifetime: 1500L ( 3-4 months ) Carton Capacity: 45x37.5x37cm/30pcs/16.6KG | E9: Certification : SGS/ROHS/FDA Bacterial removal rate 99.999% Virus removal rate 99.9% | F9: Advanced tap water filter | G9: Home sweet Home Filter set | H9: UC-HOU-TAP-005 | I9: 7 | J9: 12 | K9: =IF(NOT(ISNUMBER(Table1[[#This Row],[Landing Cost]])),"",Table1[[#This Row],[Landing Cost]]*FX_USD_KES) | L9: =IF(NOT(ISNUMBER(Table1[[#This Row],[Cost_KES]])),"",Table1[[#This Row],[Cost_KES]]*MULT_RETAIL_CORE) | M9: =IF(NOT(ISNUMBER(Table1[[#This Row],[Retail_KES]])),"",IF(Table1[[#This Row],[Retail_KES]]<=0,"",IF(Table1[[#This Row],[Retail_KES]]>=10000, ROUNDUP(Table1[[#This Row],[Retail_KES]]/1000,0)*1000-10, IF(Table1[[#This Row],[Retail_KES]]>=3000, ROUNDUP(Table1[[#This Row],[Retail_KES]]/100,0)*100-1, ROUNDUP(Table1[[#This Row],[Retail_KES]]/10,0)*10-0.01)))) | N9: =IFERROR(Table1[[#This Row],[Pychological Pricing]]/FX_USD_KES,"") | O9: =IF(NOT(ISNUMBER(Table1[[#This Row],[Retail_KES]])),"",IF(Table1[[#This Row],[Retail_KES]]<=0,"",IF(Table1[[#This Row],[Retail_KES]]>=10000, ROUNDUP(Table1[[#This Row],[Retail_KES]]*RATE_WHOLESALE/1000,0)*1000-10, IF(Table1[[#This Row],[Retail_KES]]>=3000, ROUNDUP(Table1[[#This Row],[Retail_KES]]*RATE_WHOLESALE/100,0)*100-1, ROUNDUP(Table1[[#This Row],[Retail_KES]]*RATE_WHOLESALE/10,0)*10-0.01)))) | P9: =IFERROR(Table1[[#This Row],[Wholesale_KES]]/FX_USD_KES,"") | Q9: =IF(NOT(ISNUMBER(Table1[[#This Row],[Retail_KES]])),"",IF(Table1[[#This Row],[Retail_KES]]<=0,"",IF(Table1[[#This Row],[Retail_KES]]>=10000, ROUNDUP(Table1[[#This Row],[Retail_KES]]*RATE_CORPORATE/1000,0)*1000-10, IF(Table1[[#This Row],[Retail_KES]]>=3000, ROUNDUP(Table1[[#This Row],[Retail_KES]]*RATE_CORPORATE/100,0)*100-1, ROUNDUP(Table1[[#This Row],[Retail_KES]]*RATE_CORPORATE/10,0)*10-0.01)))) | R9: =IFERROR(Table1[[#This Row],[Corporate_KES]]/FX_USD_KES,"") | S9: =IF(NOT(ISNUMBER(Table1[[#This Row],[Retail_KES]])),"",IF(Table1[[#This Row],[Retail_KES]]<=0,"",IF(Table1[[#This Row],[Retail_KES]]>=10000, ROUNDUP(Table1[[#This Row],[Retail_KES]]*RATE_INFLUENCER/1000,0)*1000-10, IF(Table1[[#This Row],[Retail_KES]]>=3000, ROUNDUP(Table1[[#This Row],[Retail_KES]]*RATE_INFLUENCER/100,0)*100-1, ROUNDUP(Table1[[#This Row],[Retail_KES]]*RATE_INFLUENCER/10,0)*10-0.01)))) | T9: =IFERROR(Table1[[#This Row],[Influencer_KES]]/FX_USD_KES,"") | U9: 0 | V9: =IF(NOT(ISNUMBER(Table1[[#This Row],[Pychological Pricing]])),"",Table1[[#This Row],[Quantity]]*Table1[[#This Row],[Pychological Pricing]])
A10: Home & Utility | B10: consumables | C10: faucet filter cartridge BG-F01U | D10: Stage1: Non-woven fabric Stage2: Carbon fiber Stage3: Granular Carbon Stage4: Ultrafiltration membrane Function: Remove sand, rust and other particulate impurities, absorb residual chlorine and other organic compounds, color,odor, and remove bacteria . lifetime: 1500L ( 3-4 months ) 49*19.5*30cm/120pcs | E10: Certification : SGS/ROHS/FDA Bacterial removal rate 99.999% Virus removal rate 99.9% | F10: Advanced tap filter only | G10: Home sweet Home Filter | H10: UC-HOU-TAPF-006 | I10: 5 | J10: 5.5 | K10: =IF(NOT(ISNUMBER(Table1[[#This Row],[Landing Cost]])),"",Table1[[#This Row],[Landing Cost]]*FX_USD_KES) | L10: =IF(NOT(ISNUMBER(Table1[[#This Row],[Cost_KES]])),"",Table1[[#This Row],[Cost_KES]]*MULT_RETAIL_CORE) | M10: =IF(NOT(ISNUMBER(Table1[[#This Row],[Retail_KES]])),"",IF(Table1[[#This Row],[Retail_KES]]<=0,"",IF(Table1[[#This Row],[Retail_KES]]>=10000, ROUNDUP(Table1[[#This Row],[Retail_KES]]/1000,0)*1000-10, IF(Table1[[#This Row],[Retail_KES]]>=3000, ROUNDUP(Table1[[#This Row],[Retail_KES]]/100,0)*100-1, ROUNDUP(Table1[[#This Row],[Retail_KES]]/10,0)*10-0.01)))) | N10: =IFERROR(Table1[[#This Row],[Pychological Pricing]]/FX_USD_KES,"") | O10: =IF(NOT(ISNUMBER(Table1[[#This Row],[Retail_KES]])),"",IF(Table1[[#This Row],[Retail_KES]]<=0,"",IF(Table1[[#This Row],[Retail_KES]]>=10000, ROUNDUP(Table1[[#This Row],[Retail_KES]]*RATE_WHOLESALE/1000,0)*1000-10, IF(Table1[[#This Row],[Retail_KES]]>=3000, ROUNDUP(Table1[[#This Row],[Retail_KES]]*RATE_WHOLESALE/100,0)*100-1, ROUNDUP(Table1[[#This Row],[Retail_KES]]*RATE_WHOLESALE/10,0)*10-0.01)))) | P10: =IFERROR(Table1[[#This Row],[Wholesale_KES]]/FX_USD_KES,"") | Q10: =IF(NOT(ISNUMBER(Table1[[#This Row],[Retail_KES]])),"",IF(Table1[[#This Row],[Retail_KES]]<=0,"",IF(Table1[[#This Row],[Retail_KES]]>=10000, ROUNDUP(Table1[[#This Row],[Retail_KES]]*RATE_CORPORATE/1000,0)*1000-10, IF(Table1[[#This Row],[Retail_KES]]>=3000, ROUNDUP(Table1[[#This Row],[Retail_KES]]*RATE_CORPORATE/100,0)*100-1, ROUNDUP(Table1[[#This Row],[Retail_KES]]*RATE_CORPORATE/10,0)*10-0.01)))) | R10: =IFERROR(Table1[[#This Row],[Corporate_KES]]/FX_USD_KES,"") | S10: =IF(NOT(ISNUMBER(Table1[[#This Row],[Retail_KES]])),"",IF(Table1[[#This Row],[Retail_KES]]<=0,"",IF(Table1[[#This Row],[Retail_KES]]>=10000, ROUNDUP(Table1[[#This Row],[Retail_KES]]*RATE_INFLUENCER/1000,0)*1000-10, IF(Table1[[#This Row],[Retail_KES]]>=3000, ROUNDUP(Table1[[#This Row],[Retail_KES]]*RATE_INFLUENCER/100,0)*100-1, ROUNDUP(Table1[[#This Row],[Retail_KES]]*RATE_INFLUENCER/10,0)*10-0.01)))) | T10: =IFERROR(Table1[[#This Row],[Influencer_KES]]/FX_USD_KES,"") | U10: 93 | V10: =IF(NOT(ISNUMBER(Table1[[#This Row],[Pychological Pricing]])),"",Table1[[#This Row],[Quantity]]*Table1[[#This Row],[Pychological Pricing]]) | X10: Discount Categories | Y10: Core Product Discounts | Z10: Consumables | AD10: 500ml tritan water filter bottle(black) BG-B06
A11: Home & Utility | B11: Core | D11: *Bacterial removal rate 99.999% *Virus removal rate 99.9% *Initial removal rate of heavy metals: 99% | E11: Certification : SGS/ROHS Bacterial removal rate 99.999% Virus removal rate 99.9% Initial removal rate of heavy metals: 99% lifetime: 150L | F11: Water filter pump | G11: Wireless Dispenser Filter Set | H11: UC-HOU-WDFS-006 | I11: 8 | J11: 12 | K11: =IF(NOT(ISNUMBER(Table1[[#This Row],[Landing Cost]])),"",Table1[[#This Row],[Landing Cost]]*FX_USD_KES) | L11: =IF(NOT(ISNUMBER(Table1[[#This Row],[Cost_KES]])),"",Table1[[#This Row],[Cost_KES]]*MULT_RETAIL_CORE) | M11: =IF(NOT(ISNUMBER(Table1[[#This Row],[Retail_KES]])),"",IF(Table1[[#This Row],[Retail_KES]]<=0,"",IF(Table1[[#This Row],[Retail_KES]]>=10000, ROUNDUP(Table1[[#This Row],[Retail_KES]]/1000,0)*1000-10, IF(Table1[[#This Row],[Retail_KES]]>=3000, ROUNDUP(Table1[[#This Row],[Retail_KES]]/100,0)*100-1, ROUNDUP(Table1[[#This Row],[Retail_KES]]/10,0)*10-0.01)))) | N11: =IFERROR(Table1[[#This Row],[Pychological Pricing]]/FX_USD_KES,"") | O11: =IF(NOT(ISNUMBER(Table1[[#This Row],[Retail_KES]])),"",IF(Table1[[#This Row],[Retail_KES]]<=0,"",IF(Table1[[#This Row],[Retail_KES]]>=10000, ROUNDUP(Table1[[#This Row],[Retail_KES]]*RATE_WHOLESALE/1000,0)*1000-10, IF(Table1[[#This Row],[Retail_KES]]>=3000, ROUNDUP(Table1[[#This Row],[Retail_KES]]*RATE_WHOLESALE/100,0)*100-1, ROUNDUP(Table1[[#This Row],[Retail_KES]]*RATE_WHOLESALE/10,0)*10-0.01)))) | P11: =IFERROR(Table1[[#This Row],[Wholesale_KES]]/FX_USD_KES,"") | Q11: =IF(NOT(ISNUMBER(Table1[[#This Row],[Retail_KES]])),"",IF(Table1[[#This Row],[Retail_KES]]<=0,"",IF(Table1[[#This Row],[Retail_KES]]>=10000, ROUNDUP(Table1[[#This Row],[Retail_KES]]*RATE_CORPORATE/1000,0)*1000-10, IF(Table1[[#This Row],[Retail_KES]]>=3000, ROUNDUP(Table1[[#This Row],[Retail_KES]]*RATE_CORPORATE/100,0)*100-1, ROUNDUP(Table1[[#This Row],[Retail_KES]]*RATE_CORPORATE/10,0)*10-0.01)))) | R11: =IFERROR(Table1[[#This Row],[Corporate_KES]]/FX_USD_KES,"") | S11: =IF(NOT(ISNUMBER(Table1[[#This Row],[Retail_KES]])),"",IF(Table1[[#This Row],[Retail_KES]]<=0,"",IF(Table1[[#This Row],[Retail_KES]]>=10000, ROUNDUP(Table1[[#This Row],[Retail_KES]]*RATE_INFLUENCER/1000,0)*1000-10, IF(Table1[[#This Row],[Retail_KES]]>=3000, ROUNDUP(Table1[[#This Row],[Retail_KES]]*RATE_INFLUENCER/100,0)*100-1, ROUNDUP(Table1[[#This Row],[Retail_KES]]*RATE_INFLUENCER/10,0)*10-0.01)))) | T11: =IFERROR(Table1[[#This Row],[Influencer_KES]]/FX_USD_KES,"") | U11: 58 | V11: =IF(NOT(ISNUMBER(Table1[[#This Row],[Pychological Pricing]])),"",Table1[[#This Row],[Quantity]]*Table1[[#This Row],[Pychological Pricing]]) | X11: Retail_KES = Cost_KES x MULT_RETAIL (derived on GUARDRAILS — do not type) | Y11: =MULT_RETAIL | Z11: 1.45
A12: Home & Utility | B12: consumables | C12: pump filter cartridge BG-F04A | D12: *Bacterial removal rate 99.999% *Virus removal rate 99.9% *Initial removal rate of heavy metals: 99% | F12: Cartridge – pump | G12: Dispenser Filter | H12: UC-HOU-DF-007 | I12: 4.5 | J12: 7 | K12: =IF(NOT(ISNUMBER(Table1[[#This Row],[Landing Cost]])),"",Table1[[#This Row],[Landing Cost]]*FX_USD_KES) | L12: =IF(NOT(ISNUMBER(Table1[[#This Row],[Cost_KES]])),"",Table1[[#This Row],[Cost_KES]]*MULT_RETAIL_CORE) | M12: =IF(NOT(ISNUMBER(Table1[[#This Row],[Retail_KES]])),"",IF(Table1[[#This Row],[Retail_KES]]<=0,"",IF(Table1[[#This Row],[Retail_KES]]>=10000, ROUNDUP(Table1[[#This Row],[Retail_KES]]/1000,0)*1000-10, IF(Table1[[#This Row],[Retail_KES]]>=3000, ROUNDUP(Table1[[#This Row],[Retail_KES]]/100,0)*100-1, ROUNDUP(Table1[[#This Row],[Retail_KES]]/10,0)*10-0.01)))) | N12: =IFERROR(Table1[[#This Row],[Pychological Pricing]]/FX_USD_KES,"") | O12: =IF(NOT(ISNUMBER(Table1[[#This Row],[Retail_KES]])),"",IF(Table1[[#This Row],[Retail_KES]]<=0,"",IF(Table1[[#This Row],[Retail_KES]]>=10000, ROUNDUP(Table1[[#This Row],[Retail_KES]]*RATE_WHOLESALE/1000,0)*1000-10, IF(Table1[[#This Row],[Retail_KES]]>=3000, ROUNDUP(Table1[[#This Row],[Retail_KES]]*RATE_WHOLESALE/100,0)*100-1, ROUNDUP(Table1[[#This Row],[Retail_KES]]*RATE_WHOLESALE/10,0)*10-0.01)))) | P12: =IFERROR(Table1[[#This Row],[Wholesale_KES]]/FX_USD_KES,"") | Q12: =IF(NOT(ISNUMBER(Table1[[#This Row],[Retail_KES]])),"",IF(Table1[[#This Row],[Retail_KES]]<=0,"",IF(Table1[[#This Row],[Retail_KES]]>=10000, ROUNDUP(Table1[[#This Row],[Retail_KES]]*RATE_CORPORATE/1000,0)*1000-10, IF(Table1[[#This Row],[Retail_KES]]>=3000, ROUNDUP(Table1[[#This Row],[Retail_KES]]*RATE_CORPORATE/100,0)*100-1, ROUNDUP(Table1[[#This Row],[Retail_KES]]*RATE_CORPORATE/10,0)*10-0.01)))) | R12: =IFERROR(Table1[[#This Row],[Corporate_KES]]/FX_USD_KES,"") | S12: =IF(NOT(ISNUMBER(Table1[[#This Row],[Retail_KES]])),"",IF(Table1[[#This Row],[Retail_KES]]<=0,"",IF(Table1[[#This Row],[Retail_KES]]>=10000, ROUNDUP(Table1[[#This Row],[Retail_KES]]*RATE_INFLUENCER/1000,0)*1000-10, IF(Table1[[#This Row],[Retail_KES]]>=3000, ROUNDUP(Table1[[#This Row],[Retail_KES]]*RATE_INFLUENCER/100,0)*100-1, ROUNDUP(Table1[[#This Row],[Retail_KES]]*RATE_INFLUENCER/10,0)*10-0.01)))) | T12: =IFERROR(Table1[[#This Row],[Influencer_KES]]/FX_USD_KES,"") | U12: 41 | V12: =IF(NOT(ISNUMBER(Table1[[#This Row],[Pychological Pricing]])),"",Table1[[#This Row],[Quantity]]*Table1[[#This Row],[Pychological Pricing]]) | X12: Wholesale_KES = Retail_KES × 0.8 (or Cost_KES × 1.2) | Y12: =TIER_WHOLESALE | Z12: 0.5
A13: Bottles & On-the-Go | B13: Core | C13: 740ml stainless steel water filter bottle BG-B01 | D13: Product name：740ML stainless steel bottle with filter straw Model NO : B01 Main material: Food-grade 304 Stainless Steel Color: Blue, gray, pink, dark green (other colors available) Filter material: Ahlstrom Rated filtering water : 150L Function : Filter wild water sources such as river water, lake water, and spring water to become drinkable water Product size : 78*261mm Package including: filter*1, manual *1, color box *1 Carton: 610*270*305mm/21pcs/11.5KG Suggestion change filter time : 2-3 months Certification : SGS/ROHS/FDA | E13: Bacterial removal rate 99.999% Virus removal rate 99.9% Initial removal rate of heavy metals: 99% lifetime: 150L Certification : SGS/ROHS/FDA | F13: 740ml stainless bottle with filter straw | G13: Hydra Flux | H13: UC-BOG-SSB-008 | I13: 10 | J13: 16 | K13: =IF(NOT(ISNUMBER(Table1[[#This Row],[Landing Cost]])),"",Table1[[#This Row],[Landing Cost]]*FX_USD_KES) | L13: =IF(NOT(ISNUMBER(Table1[[#This Row],[Cost_KES]])),"",Table1[[#This Row],[Cost_KES]]*MULT_RETAIL_CORE) | M13: =IF(NOT(ISNUMBER(Table1[[#This Row],[Retail_KES]])),"",IF(Table1[[#This Row],[Retail_KES]]<=0,"",IF(Table1[[#This Row],[Retail_KES]]>=10000, ROUNDUP(Table1[[#This Row],[Retail_KES]]/1000,0)*1000-10, IF(Table1[[#This Row],[Retail_KES]]>=3000, ROUNDUP(Table1[[#This Row],[Retail_KES]]/100,0)*100-1, ROUNDUP(Table1[[#This Row],[Retail_KES]]/10,0)*10-0.01)))) | N13: =IFERROR(Table1[[#This Row],[Pychological Pricing]]/FX_USD_KES,"") | O13: =IF(NOT(ISNUMBER(Table1[[#This Row],[Retail_KES]])),"",IF(Table1[[#This Row],[Retail_KES]]<=0,"",IF(Table1[[#This Row],[Retail_KES]]>=10000, ROUNDUP(Table1[[#This Row],[Retail_KES]]*RATE_WHOLESALE/1000,0)*1000-10, IF(Table1[[#This Row],[Retail_KES]]>=3000, ROUNDUP(Table1[[#This Row],[Retail_KES]]*RATE_WHOLESALE/100,0)*100-1, ROUNDUP(Table1[[#This Row],[Retail_KES]]*RATE_WHOLESALE/10,0)*10-0.01)))) | P13: =IFERROR(Table1[[#This Row],[Wholesale_KES]]/FX_USD_KES,"") | Q13: =IF(NOT(ISNUMBER(Table1[[#This Row],[Retail_KES]])),"",IF(Table1[[#This Row],[Retail_KES]]<=0,"",IF(Table1[[#This Row],[Retail_KES]]>=10000, ROUNDUP(Table1[[#This Row],[Retail_KES]]*RATE_CORPORATE/1000,0)*1000-10, IF(Table1[[#This Row],[Retail_KES]]>=3000, ROUNDUP(Table1[[#This Row],[Retail_KES]]*RATE_CORPORATE/100,0)*100-1, ROUNDUP(Table1[[#This Row],[Retail_KES]]*RATE_CORPORATE/10,0)*10-0.01)))) | R13: =IFERROR(Table1[[#This Row],[Corporate_KES]]/FX_USD_KES,"") | S13: =IF(NOT(ISNUMBER(Table1[[#This Row],[Retail_KES]])),"",IF(Table1[[#This Row],[Retail_KES]]<=0,"",IF(Table1[[#This Row],[Retail_KES]]>=10000, ROUNDUP(Table1[[#This Row],[Retail_KES]]*RATE_INFLUENCER/1000,0)*1000-10, IF(Table1[[#This Row],[Retail_KES]]>=3000, ROUNDUP(Table1[[#This Row],[Retail_KES]]*RATE_INFLUENCER/100,0)*100-1, ROUNDUP(Table1[[#This Row],[Retail_KES]]*RATE_INFLUENCER/10,0)*10-0.01)))) | T13: =IFERROR(Table1[[#This Row],[Influencer_KES]]/FX_USD_KES,"") | U13: 21 | V13: =IF(NOT(ISNUMBER(Table1[[#This Row],[Pychological Pricing]])),"",Table1[[#This Row],[Quantity]]*Table1[[#This Row],[Pychological Pricing]]) | X13: Corporate_KES = Retail_KES × 0.85 (or Cost_KES × 1.35) | Y13: =TIER_CORPORATE | Z13: 0.6 | AD13: 1000ml tritan water filter bottle BG-B09
A14: Bottles & On-the-Go | B14: Core | C14: 769ml tritan water filter bottle BG-B02 | D14: Product name：769ML Tritan bottle with filter straw Model NO : B02 Main material: Food-grade Tritan plastic (BPA free) Color: Blue, gray, pink (other colors available) Filter material: Ahlstrom Rated filtering water : 150L Function : Filter wild water sources such as river water, lake water, and spring water to become drinkable water Product size : 78*261mm Package including: filter*1, manual *1, color box *1 Carton: 545*450*325mm/30pcs/10.5kg Suggestion change filter time : 2-3 months Certification : SGS/ROHS/FDA | E14: Certification : SGS/ROHS/FDA Bacterial removal rate 99.999% Virus removal rate 99.9% Initial removal rate of heavy metals: 99% lifetime: 150L | F14: 769ml Tritan bottle with filter straw | G14: Truva Go | H14: UC-BOG-TRB-009 | I14: 6.8 | J14: 11.5 | K14: =IF(NOT(ISNUMBER(Table1[[#This Row],[Landing Cost]])),"",Table1[[#This Row],[Landing Cost]]*FX_USD_KES) | L14: =IF(NOT(ISNUMBER(Table1[[#This Row],[Cost_KES]])),"",Table1[[#This Row],[Cost_KES]]*MULT_RETAIL_CORE) | M14: =IF(NOT(ISNUMBER(Table1[[#This Row],[Retail_KES]])),"",IF(Table1[[#This Row],[Retail_KES]]<=0,"",IF(Table1[[#This Row],[Retail_KES]]>=10000, ROUNDUP(Table1[[#This Row],[Retail_KES]]/1000,0)*1000-10, IF(Table1[[#This Row],[Retail_KES]]>=3000, ROUNDUP(Table1[[#This Row],[Retail_KES]]/100,0)*100-1, ROUNDUP(Table1[[#This Row],[Retail_KES]]/10,0)*10-0.01)))) | N14: =IFERROR(Table1[[#This Row],[Pychological Pricing]]/FX_USD_KES,"") | O14: =IF(NOT(ISNUMBER(Table1[[#This Row],[Retail_KES]])),"",IF(Table1[[#This Row],[Retail_KES]]<=0,"",IF(Table1[[#This Row],[Retail_KES]]>=10000, ROUNDUP(Table1[[#This Row],[Retail_KES]]*RATE_WHOLESALE/1000,0)*1000-10, IF(Table1[[#This Row],[Retail_KES]]>=3000, ROUNDUP(Table1[[#This Row],[Retail_KES]]*RATE_WHOLESALE/100,0)*100-1, ROUNDUP(Table1[[#This Row],[Retail_KES]]*RATE_WHOLESALE/10,0)*10-0.01)))) | P14: =IFERROR(Table1[[#This Row],[Wholesale_KES]]/FX_USD_KES,"") | Q14: =IF(NOT(ISNUMBER(Table1[[#This Row],[Retail_KES]])),"",IF(Table1[[#This Row],[Retail_KES]]<=0,"",IF(Table1[[#This Row],[Retail_KES]]>=10000, ROUNDUP(Table1[[#This Row],[Retail_KES]]*RATE_CORPORATE/1000,0)*1000-10, IF(Table1[[#This Row],[Retail_KES]]>=3000, ROUNDUP(Table1[[#This Row],[Retail_KES]]*RATE_CORPORATE/100,0)*100-1, ROUNDUP(Table1[[#This Row],[Retail_KES]]*RATE_CORPORATE/10,0)*10-0.01)))) | R14: =IFERROR(Table1[[#This Row],[Corporate_KES]]/FX_USD_KES,"") | S14: =IF(NOT(ISNUMBER(Table1[[#This Row],[Retail_KES]])),"",IF(Table1[[#This Row],[Retail_KES]]<=0,"",IF(Table1[[#This Row],[Retail_KES]]>=10000, ROUNDUP(Table1[[#This Row],[Retail_KES]]*RATE_INFLUENCER/1000,0)*1000-10, IF(Table1[[#This Row],[Retail_KES]]>=3000, ROUNDUP(Table1[[#This Row],[Retail_KES]]*RATE_INFLUENCER/100,0)*100-1, ROUNDUP(Table1[[#This Row],[Retail_KES]]*RATE_INFLUENCER/10,0)*10-0.01)))) | T14: =IFERROR(Table1[[#This Row],[Influencer_KES]]/FX_USD_KES,"") | U14: 37 | V14: =IF(NOT(ISNUMBER(Table1[[#This Row],[Pychological Pricing]])),"",Table1[[#This Row],[Quantity]]*Table1[[#This Row],[Pychological Pricing]]) | X14: Influencers | Y14: =TIER_INFLUENCER | Z14: 0.65
A15: Bottles & On-the-Go | B15: Core | C15: 500ml tritan water filter bottle(black) BG-B06 | D15: Product name：500ML Tritan bottle with filter straw Model NO : B06 Main material: Food-grade Tritan plastic (BPA free) Color: Black, green (other colors available) Filter material: Ahlstrom Rated filtering water : 150L Function : Filter wild water sources such as river water, lake water, and spring water to become drinkable water Product size : 85*210mm Package including: filter*1, manual *1, color box *1 Suggestion change filter time : 2-3 | E15: Certification : SGS/ROHS Bacterial removal rate 99.999% Virus removal rate 99.9% Initial removal rate of heavy metals: 99% lifetime: 150L | F15: 500ml Tritan bottle with filter straw | G15: Viva Drop | H15: UC-BOG-TRB-010 | I15: 6 | J15: 8.5 | K15: =IF(NOT(ISNUMBER(Table1[[#This Row],[Landing Cost]])),"",Table1[[#This Row],[Landing Cost]]*FX_USD_KES) | L15: =IF(NOT(ISNUMBER(Table1[[#This Row],[Cost_KES]])),"",Table1[[#This Row],[Cost_KES]]*MULT_RETAIL_CORE) | M15: =IF(NOT(ISNUMBER(Table1[[#This Row],[Retail_KES]])),"",IF(Table1[[#This Row],[Retail_KES]]<=0,"",IF(Table1[[#This Row],[Retail_KES]]>=10000, ROUNDUP(Table1[[#This Row],[Retail_KES]]/1000,0)*1000-10, IF(Table1[[#This Row],[Retail_KES]]>=3000, ROUNDUP(Table1[[#This Row],[Retail_KES]]/100,0)*100-1, ROUNDUP(Table1[[#This Row],[Retail_KES]]/10,0)*10-0.01)))) | N15: =IFERROR(Table1[[#This Row],[Pychological Pricing]]/FX_USD_KES,"") | O15: =IF(NOT(ISNUMBER(Table1[[#This Row],[Retail_KES]])),"",IF(Table1[[#This Row],[Retail_KES]]<=0,"",IF(Table1[[#This Row],[Retail_KES]]>=10000, ROUNDUP(Table1[[#This Row],[Retail_KES]]*RATE_WHOLESALE/1000,0)*1000-10, IF(Table1[[#This Row],[Retail_KES]]>=3000, ROUNDUP(Table1[[#This Row],[Retail_KES]]*RATE_WHOLESALE/100,0)*100-1, ROUNDUP(Table1[[#This Row],[Retail_KES]]*RATE_WHOLESALE/10,0)*10-0.01)))) | P15: =IFERROR(Table1[[#This Row],[Wholesale_KES]]/FX_USD_KES,"") | Q15: =IF(NOT(ISNUMBER(Table1[[#This Row],[Retail_KES]])),"",IF(Table1[[#This Row],[Retail_KES]]<=0,"",IF(Table1[[#This Row],[Retail_KES]]>=10000, ROUNDUP(Table1[[#This Row],[Retail_KES]]*RATE_CORPORATE/1000,0)*1000-10, IF(Table1[[#This Row],[Retail_KES]]>=3000, ROUNDUP(Table1[[#This Row],[Retail_KES]]*RATE_CORPORATE/100,0)*100-1, ROUNDUP(Table1[[#This Row],[Retail_KES]]*RATE_CORPORATE/10,0)*10-0.01)))) | R15: =IFERROR(Table1[[#This Row],[Corporate_KES]]/FX_USD_KES,"") | S15: =IF(NOT(ISNUMBER(Table1[[#This Row],[Retail_KES]])),"",IF(Table1[[#This Row],[Retail_KES]]<=0,"",IF(Table1[[#This Row],[Retail_KES]]>=10000, ROUNDUP(Table1[[#This Row],[Retail_KES]]*RATE_INFLUENCER/1000,0)*1000-10, IF(Table1[[#This Row],[Retail_KES]]>=3000, ROUNDUP(Table1[[#This Row],[Retail_KES]]*RATE_INFLUENCER/100,0)*100-1, ROUNDUP(Table1[[#This Row],[Retail_KES]]*RATE_INFLUENCER/10,0)*10-0.01)))) | T15: =IFERROR(Table1[[#This Row],[Influencer_KES]]/FX_USD_KES,"") | U15: 70 | V15: =IF(NOT(ISNUMBER(Table1[[#This Row],[Pychological Pricing]])),"",Table1[[#This Row],[Quantity]]*Table1[[#This Row],[Pychological Pricing]]) | AD15: 350ml collapsible water filter bottle BG-B04
A16: Bottles & On-the-Go | B16: Core | C16: 1000ml tritan water filter bottle BG-B09 | D16: *Bacterial removal rate 99.999% *Virus removal rate 99.9% *Initial removal rate of heavy metals: 99% *lifetime: 150L *575*465*440mm/40pcs/14KG | E16: Certification : SGS/ROHS Bacterial removal rate 99.999% Virus removal rate 99.9% Initial removal rate of heavy metals: 99% lifetime: 150L | F16: 1200ml Tritan bottle with filter straw | G16: Gym Buddy | H16: UC-BOG-TRB-011 | I16: 8.5 | J16: 13 | K16: =IF(NOT(ISNUMBER(Table1[[#This Row],[Landing Cost]])),"",Table1[[#This Row],[Landing Cost]]*FX_USD_KES) | L16: =IF(NOT(ISNUMBER(Table1[[#This Row],[Cost_KES]])),"",Table1[[#This Row],[Cost_KES]]*MULT_RETAIL_CORE) | M16: =IF(NOT(ISNUMBER(Table1[[#This Row],[Retail_KES]])),"",IF(Table1[[#This Row],[Retail_KES]]<=0,"",IF(Table1[[#This Row],[Retail_KES]]>=10000, ROUNDUP(Table1[[#This Row],[Retail_KES]]/1000,0)*1000-10, IF(Table1[[#This Row],[Retail_KES]]>=3000, ROUNDUP(Table1[[#This Row],[Retail_KES]]/100,0)*100-1, ROUNDUP(Table1[[#This Row],[Retail_KES]]/10,0)*10-0.01)))) | N16: =IFERROR(Table1[[#This Row],[Pychological Pricing]]/FX_USD_KES,"") | O16: =IF(NOT(ISNUMBER(Table1[[#This Row],[Retail_KES]])),"",IF(Table1[[#This Row],[Retail_KES]]<=0,"",IF(Table1[[#This Row],[Retail_KES]]>=10000, ROUNDUP(Table1[[#This Row],[Retail_KES]]*RATE_WHOLESALE/1000,0)*1000-10, IF(Table1[[#This Row],[Retail_KES]]>=3000, ROUNDUP(Table1[[#This Row],[Retail_KES]]*RATE_WHOLESALE/100,0)*100-1, ROUNDUP(Table1[[#This Row],[Retail_KES]]*RATE_WHOLESALE/10,0)*10-0.01)))) | P16: =IFERROR(Table1[[#This Row],[Wholesale_KES]]/FX_USD_KES,"") | Q16: =IF(NOT(ISNUMBER(Table1[[#This Row],[Retail_KES]])),"",IF(Table1[[#This Row],[Retail_KES]]<=0,"",IF(Table1[[#This Row],[Retail_KES]]>=10000, ROUNDUP(Table1[[#This Row],[Retail_KES]]*RATE_CORPORATE/1000,0)*1000-10, IF(Table1[[#This Row],[Retail_KES]]>=3000, ROUNDUP(Table1[[#This Row],[Retail_KES]]*RATE_CORPORATE/100,0)*100-1, ROUNDUP(Table1[[#This Row],[Retail_KES]]*RATE_CORPORATE/10,0)*10-0.01)))) | R16: =IFERROR(Table1[[#This Row],[Corporate_KES]]/FX_USD_KES,"") | S16: =IF(NOT(ISNUMBER(Table1[[#This Row],[Retail_KES]])),"",IF(Table1[[#This Row],[Retail_KES]]<=0,"",IF(Table1[[#This Row],[Retail_KES]]>=10000, ROUNDUP(Table1[[#This Row],[Retail_KES]]*RATE_INFLUENCER/1000,0)*1000-10, IF(Table1[[#This Row],[Retail_KES]]>=3000, ROUNDUP(Table1[[#This Row],[Retail_KES]]*RATE_INFLUENCER/100,0)*100-1, ROUNDUP(Table1[[#This Row],[Retail_KES]]*RATE_INFLUENCER/10,0)*10-0.01)))) | T16: =IFERROR(Table1[[#This Row],[Influencer_KES]]/FX_USD_KES,"") | U16: 24 | V16: =IF(NOT(ISNUMBER(Table1[[#This Row],[Pychological Pricing]])),"",Table1[[#This Row],[Quantity]]*Table1[[#This Row],[Pychological Pricing]]) | AD16: 1000ml squeeze water filter bottle BG-B07
A17: Bottles & On-the-Go | B17: Core | C17: 350ml collapsible water filter bottle BG-B04 | D17: Product name：350mL Foldable water bottle with filter Model NO : B04 Main material: Food-grade TPU Color: Blue, green, pink (other colors available) Filter material: Ahlstrom Rated filtering water : 100L Function : Filter wild water sources such as river water, lake water, and spring water to become drinkable water Product size : 70*260mm Package including: filter*1, manual *1, color box *1 Suggestion change filter time : 2-3 months Carton Capacity:400*350*375mm 268g 40pcs | E17: Certification : SGS/ROHS Bacterial removal rate 99.999% Virus removal rate 99.9% Initial removal rate of heavy metals: 99% lifetime: 150L | F17: 350ml foldable bottle with filter | G17: Timbo | H17: UC-BOG-FLB-012 | I17: 6 | J17: 5 | K17: =IF(NOT(ISNUMBER(Table1[[#This Row],[Landing Cost]])),"",Table1[[#This Row],[Landing Cost]]*FX_USD_KES) | L17: =IF(NOT(ISNUMBER(Table1[[#This Row],[Cost_KES]])),"",Table1[[#This Row],[Cost_KES]]*MULT_RETAIL_CORE) | M17: =IF(NOT(ISNUMBER(Table1[[#This Row],[Retail_KES]])),"",IF(Table1[[#This Row],[Retail_KES]]<=0,"",IF(Table1[[#This Row],[Retail_KES]]>=10000, ROUNDUP(Table1[[#This Row],[Retail_KES]]/1000,0)*1000-10, IF(Table1[[#This Row],[Retail_KES]]>=3000, ROUNDUP(Table1[[#This Row],[Retail_KES]]/100,0)*100-1, ROUNDUP(Table1[[#This Row],[Retail_KES]]/10,0)*10-0.01)))) | N17: =IFERROR(Table1[[#This Row],[Pychological Pricing]]/FX_USD_KES,"") | O17: =IF(NOT(ISNUMBER(Table1[[#This Row],[Retail_KES]])),"",IF(Table1[[#This Row],[Retail_KES]]<=0,"",IF(Table1[[#This Row],[Retail_KES]]>=10000, ROUNDUP(Table1[[#This Row],[Retail_KES]]*RATE_WHOLESALE/1000,0)*1000-10, IF(Table1[[#This Row],[Retail_KES]]>=3000, ROUNDUP(Table1[[#This Row],[Retail_KES]]*RATE_WHOLESALE/100,0)*100-1, ROUNDUP(Table1[[#This Row],[Retail_KES]]*RATE_WHOLESALE/10,0)*10-0.01)))) | P17: =IFERROR(Table1[[#This Row],[Wholesale_KES]]/FX_USD_KES,"") | Q17: =IF(NOT(ISNUMBER(Table1[[#This Row],[Retail_KES]])),"",IF(Table1[[#This Row],[Retail_KES]]<=0,"",IF(Table1[[#This Row],[Retail_KES]]>=10000, ROUNDUP(Table1[[#This Row],[Retail_KES]]*RATE_CORPORATE/1000,0)*1000-10, IF(Table1[[#This Row],[Retail_KES]]>=3000, ROUNDUP(Table1[[#This Row],[Retail_KES]]*RATE_CORPORATE/100,0)*100-1, ROUNDUP(Table1[[#This Row],[Retail_KES]]*RATE_CORPORATE/10,0)*10-0.01)))) | R17: =IFERROR(Table1[[#This Row],[Corporate_KES]]/FX_USD_KES,"") | S17: =IF(NOT(ISNUMBER(Table1[[#This Row],[Retail_KES]])),"",IF(Table1[[#This Row],[Retail_KES]]<=0,"",IF(Table1[[#This Row],[Retail_KES]]>=10000, ROUNDUP(Table1[[#This Row],[Retail_KES]]*RATE_INFLUENCER/1000,0)*1000-10, IF(Table1[[#This Row],[Retail_KES]]>=3000, ROUNDUP(Table1[[#This Row],[Retail_KES]]*RATE_INFLUENCER/100,0)*100-1, ROUNDUP(Table1[[#This Row],[Retail_KES]]*RATE_INFLUENCER/10,0)*10-0.01)))) | T17: =IFERROR(Table1[[#This Row],[Influencer_KES]]/FX_USD_KES,"") | U17: 3 | V17: =IF(NOT(ISNUMBER(Table1[[#This Row],[Pychological Pricing]])),"",Table1[[#This Row],[Quantity]]*Table1[[#This Row],[Pychological Pricing]]) | X17: Pricing Category
